Test/Test.v
module edge_detector(
    input wire clk,      // Входной сигнал clock
    input wire reset,    // Входной сигнал сброса
    output reg rise      // Выходной сигнал для обнаружения фронта
);

reg clk_prev;

always @(posedge clk or posedge reset) begin
    if (reset) begin
        clk_prev <= 0;
        rise <= 0;
    end else begin
        rise <= ~clk_prev & clk; // Обнаружение фронта
        clk_prev <= clk;
    end
end

endmodule

Test/Test_tb.v
`include "Test.v"
module tb_edge_detector;

reg clk;          // Тестовый сигнал clock
reg reset;        // Тестовый сигнал сброса
wire rise;        // Выходной сигнал для обнаружения фронта

// Инстанцируем модуль edge_detector
edge_detector uut (
    .clk(clk),
    .reset(reset),
    .rise(rise)
);

initial begin
    $dumpfile("Test.vcd");
    $dumpvars(0, uut);
    // Инициализация сигналов
    clk = 0;
    reset = 1;
    #10 reset = 0;

    // Генерация тестовых импульсов clock
    #20 clk = 1;
    #20 clk = 0;
    #20 clk = 1;
    #20 clk = 0;
    #20 clk = 1;
    #20 clk = 0;

    // Устанавливаем reset
    #30 reset = 1;
    #10 reset = 0;
    
    // Повторная генерация тестовых импульсов clock
    #20 clk = 1;
    #20 clk = 0;
    #20 clk = 1;
    #20 clk = 0;
    #20 clk = 1;
    #20 clk = 0;

    // Завершаем тест
    #50 $finish;
end

always #10 clk = ~clk;  // Генерация тактового сигнала

endmodule

Test/Test.vcd
$date
	Sun Jan 12 23:32:41 2025
$end
$version
	Icarus Verilog
$end
$timescale
	1s
$end
$scope module tb_edge_detector $end
$scope module uut $end
$var wire 1 ! clk $end
$var wire 1 " reset $end
$var reg 1 # clk_prev $end
$var reg 1 $ rise $end
$upscope $end
$upscope $end
$enddefinitions $end
#0
$dumpvars
0$
0#
1"
0!
$end
#10
1#
1$
1!
0"
#20
0!
#30
0#
0$
0!
#40
1#
1$
1!
#50
0$
1!
#60
0!
#70
0#
0!
#80
1#
1$
1!
#90
0$
1!
#100
0!
#110
0#
0!
#120
1#
1$
1!
#130
0$
1!
#140
0!
#150
1!
#160
0#
0!
1"
#170
1#
1$
1!
0"
#180
0!
#190
0#
0$
0!
#200
1#
1$
1!
#210
0$
1!
#220
0!
#230
0#
0!
#240
1#
1$
1!
#250
0$
1!
#260
0!
#270
0#
0!
#280
1#
1$
1!
#290
0$
1!
