ALU/ALU.v
module ALU(
    input [7:0] data1,
    input [7:0] data2,
    input cs,
    input [1:0] opcode,
    output reg[7:0] result
);

always @(*) begin
    case (opcode)
        2'b00: result = data1 + data2;
        2'b01: result = data1 - data2;
        2'b10: result = data1 & data2;
        2'b11: result = data1 | data2;
    endcase
end


endmodule

SRAM/SRAM.v
module SRAM #(
    parameter ADDR=8, 
    parameter WIDTH=32, 
    parameter LENGTH=256
    )(
    input clk,
    input CS,
    input WE,
    input [ADDR-1:0] addr,
    input [WIDTH-1:0] data_in,
    output [WIDTH-1:0] instruction,
    output reg[WIDTH-1:0] data_out
);

reg [WIDTH-1:0] mem[0:LENGTH-1];

initial begin
    $readmemb("C:/Users/HP/Desktop/CPU-RTL/SRAM/file.txt", mem);
end

assign instruction=mem[addr];

always @(posedge clk) begin
    if(CS)begin
        if (WE) begin
            mem[addr] <= data_in;
        end 
        else begin
            data_out <= mem[addr];
        end
    end
end

endmodule

CPU/CPU.v
`include "../SRAM/SRAM.v"
`include "../ALU/ALU.v"

module CPU(
    input clk,
    input cs,
    input we,
    input reset,
    output reg [7:0] reg1,
    output reg [7:0] reg2,
    output reg [7:0] reg3,
    output reg [7:0] reg4
);

reg [3:0]programm_counter;
reg [7:0] data_in;
wire [7:0] result;
wire [7:0] instruction;

always@(posedge clk)begin
    if(reset)begin
        reg1 <= 8'b0;
        reg2 <= 8'b0;
        reg3 <= 8'b0;
        reg4 <= 8'b0;
        programm_counter<=4'b0;
    end
    else begin
        programm_counter<=programm_counter+1;
        if(~we)begin
            case(instruction[7:6])
                2'b00:begin
                    reg1<=instruction[3:0];
                end
                2'b01:begin
                    reg2<=instruction[3:0];
                end
                2'b10:begin
                    reg3<=instruction[3:0];
                end
                2'b11:begin
                    reg4<=instruction[3:0];
                end
            endcase
        end
    end
end

SRAM #(
    .ADDR(4),
    .WIDTH(8),
    .LENGTH(16)
)u_SRAM(
    .clk(clk),
    .CS(cs),
    .WE(we),
    .addr(programm_counter),
    .data_in(data_in),
    .instruction(instruction)
);

ALU u_ALU(
    .data1(reg1),
    .data2(reg2),
    .cs(cs),
    .opcode(instruction[5:4]),
    .result(result)
);

endmodule

CPU/CPU_tb.v
`include "CPU.v"

module CPU_tb;

reg clk;
reg cs;
reg we;
reg reset;
wire [7:0] reg1;
wire [7:0] reg2;
wire [7:0] reg3;
wire [7:0] reg4;

always #1 clk = ~clk;

CPU u_CPU(
    .clk(clk),
    .cs(cs),
    .we(we),
    .reset(reset),
    .reg1(reg1),
    .reg2(reg2),
    .reg3(reg3),
    .reg4(reg4)
);

initial begin
    $dumpfile("CPU.vcd");
    $dumpvars(0, CPU_tb);
    clk=0;
    reset=1;
    #10;
    reset=0;
    cs=1;
    we=0;
    //Load 0x02 into R1.
    //Load 0x04 into R2.
    #4;
    cs=0;
    //Add R1 and R2, store in R1.
    #2;
    cs=1;
    //Load 0x05 into R1.
    //Load 0x0E into R2.
    #4;
    cs=0;
    //Subtract R2 from R1, store in R1.
    #2;
    we=1;
    //Store R1 to memory address 0x06.
    cs=1;
    //Load 0x03 into R2.
    #4;
    cs=0;
    //Add R2 and R2, store in R1.
    #2;
    cs=1;
    //Store R1 to memory address 0x04.
    we=1;
    #4;
    we=0;
    //Load 0x0A into R3.
    //Load 0x0B into R4.
    #4;
    cs=0;
    //Subtract R3 from R4, store in R4.
    #2;
    cs=1;
    we=1;
    //Store R4 to memory address 0x0B.
    #2;
    we=0;
    //Load 0x0F into R3.
    #2;
    we=1;
    //Store R3 to memory address 0x0F.
    $finish;
end

initial begin
    $monitor("Time=%0t | Reg1=%b | Reg2=%b | Reg3=%b | Reg4=%b | PC=%b", $time, reg1, reg2, reg3, reg4, u_CPU.programm_counter);
end

endmodule

CPU/CPU.vcd
$date
	Tue Jan 28 23:10:07 2025
$end
$version
	Icarus Verilog
$end
$timescale
	1s
$end
$scope module CPU_tb $end
$var wire 8 ! reg4 [7:0] $end
$var wire 8 " reg3 [7:0] $end
$var wire 8 # reg2 [7:0] $end
$var wire 8 $ reg1 [7:0] $end
$var reg 1 % clk $end
$var reg 1 & cs $end
$var reg 1 ' reset $end
$var reg 1 ( we $end
$scope module u_CPU $end
$var wire 1 % clk $end
$var wire 1 & cs $end
$var wire 1 ' reset $end
$var wire 1 ( we $end
$var wire 8 ) result [7:0] $end
$var wire 8 * instruction [7:0] $end
$var reg 8 + data_in [7:0] $end
$var reg 4 , programm_counter [3:0] $end
$var reg 8 - reg1 [7:0] $end
$var reg 8 . reg2 [7:0] $end
$var reg 8 / reg3 [7:0] $end
$var reg 8 0 reg4 [7:0] $end
$scope module u_ALU $end
$var wire 1 & cs $end
$var wire 8 1 data1 [7:0] $end
$var wire 8 2 data2 [7:0] $end
$var wire 2 3 opcode [1:0] $end
$var reg 8 4 result [7:0] $end
$upscope $end
$scope module u_SRAM $end
$var wire 1 & CS $end
$var wire 1 ( WE $end
$var wire 4 5 addr [3:0] $end
$var wire 1 % clk $end
$var wire 8 6 data_in [7:0] $end
$var wire 8 7 instruction [7:0] $end
$var reg 8 8 data_out [7:0] $end
$upscope $end
$upscope $end
$upscope $end
$enddefinitions $end
#0
$dumpvars
bx 8
bx 7
bx 6
bx 5
bx 4
bx 3
bx 2
bx 1
bx 0
bx /
bx .
bx -
bx ,
bx +
bx *
bx )
x(
1'
x&
0%
bx $
bx #
bx "
bx !
$end
#1
b1 3
b10010 *
b10010 7
b0 ,
b0 5
b0 !
b0 0
b0 "
b0 /
b0 #
b0 .
b0 2
b0 $
b0 -
b0 1
1%
#2
0%
#3
1%
#4
0%
#5
1%
#6
0%
#7
1%
#8
0%
#9
1%
#10
0%
0(
1&
0'
#11
b10 3
b10 $
b10 -
b10 1
b100100 *
b100100 7
b1 ,
b1 5
b10010 8
1%
#12
0%
#13
b1 3
b100100 8
b100 $
b100 -
b100 1
b1010000 *
b1010000 7
b10 ,
b10 5
1%
#14
b100 )
b100 4
0%
0&
#15
b10101 *
b10101 7
b11 ,
b11 5
1%
#16
0%
1&
#17
b10 3
b10101 8
b101 $
b101 -
b101 1
b101110 *
b101110 7
b100 ,
b100 5
1%
#18
0%
#19
b11 3
b1110 $
b1110 -
b1110 1
b10110000 *
b10110000 7
b101 ,
b101 5
b101110 8
1%
#20
b1110 )
b1110 4
0%
0&
#21
b1 3
b11010110 *
b11010110 7
b110 ,
b110 5
1%
#22
0%
1&
1(
#23
b10 3
b111 ,
b111 5
b100011 *
b100011 7
1%
#24
0%
#25
b1 3
b1011000 *
b1011000 7
b1000 ,
b1000 5
1%
#26
0%
0&
#27
b11010100 *
b11010100 7
b1001 ,
b1001 5
1%
#28
0%
1&
#29
b11010 *
b11010 7
b1010 ,
b1010 5
1%
#30
0%
#31
b11 3
b1011 ,
b1011 5
b111011 *
b111011 7
1%
#32
0%
0(
#33
b111011 8
b1011 $
b1011 -
b1011 1
b10111100 *
b10111100 7
b1100 ,
b1100 5
1%
#34
0%
#35
b1 3
b1100 "
b1100 /
b11011011 *
b11011011 7
b1101 ,
b1101 5
b10111100 8
1%
#36
b1011 )
b1011 4
0%
0&
#37
b1011 !
b1011 0
b11111 *
b11111 7
b1110 ,
b1110 5
1%
#38
0%
1(
1&
#39
b11 3
b1111 ,
b1111 5
b11111111 *
b11111111 7
1%
#40
0%
0(
#41
b1 3
b11111111 8
b1111 !
b1111 0
b10010 *
b10010 7
b0 ,
b0 5
1%
#42
0%
1(
