ALU/ALU.v
module ALU(
    input [7:0] data1,
    input [7:0] data2,
    input cs,
    input [1:0] opcode,
    output reg[7:0] result
);

always @(*) begin
    case (opcode)
        2'b00: result = data1 + data2;
        2'b01: result = data1 - data2;
        2'b10: result = data1 & data2;
        2'b11: result = data1 | data2;
    endcase
end


endmodule

SRAM/SRAM.v
module SRAM #(
    parameter ADDR=8, 
    parameter WIDTH=32, 
    parameter LENGTH=256
    )(
    input clk,
    input CS,
    input WE,
    input [ADDR-1:0] addr,
    input [WIDTH-1:0] data_in,
    output reg[WIDTH-1:0] data_out
);

reg [WIDTH-1:0] mem[0:LENGTH-1];

initial begin
    $readmemb("C:/Users/HP/Desktop/CPU-RTL/SRAM/file.txt", mem);
end

always @(posedge clk) begin
    if(CS)begin
        if (WE) begin
            mem[15+addr] <= data_in;
        end 
        else begin
            data_out <= mem[addr];
        end
    end
end

endmodule

Decoder/Decoder.v
module decoder(
    input [7:0]register1,
    input [7:0]register2,
    input [7:0]register3,
    input [7:0]register4,
    input [1:0]sel,
    output reg[7:0]data
);

always @(sel) begin
    case(sel)
        2'b00: data = register1;
        2'b01: data = register2;
        2'b10: data = register3;
        2'b11: data = register4;
    endcase
end

endmodule

CPU/CPU.v
`include "../SRAM/SRAM.v"
`include "../ALU/ALU.v"
`include "../Decoder/Decoder.v"

module CPU(
    input clk,
    input cs,
    input we,
    input reset,
    output reg [7:0] reg1,
    output reg [7:0] reg2,
    output reg [7:0] reg3,
    output reg [7:0] reg4,
    output [7:0] reg5
);

reg [3:0] program_counter;
reg [7:0] data_in;
wire [7:0] result;
wire [7:0] instruction;
wire [7:0] data1;
wire [7:0] data2;

assign reg5 = result;

always @(posedge clk) begin
    if (reset) begin
        reg1 <= 8'b0;
        reg2 <= 8'b0;
        reg3 <= 8'b0;
        reg4 <= 8'b0;
        program_counter <= 4'b0;
    end else begin
        program_counter <= program_counter + 1;
        if (~we) begin
            if (instruction[7:6] == 2'b00) begin
                case (instruction[5:4])
                    2'b00: reg1 <= instruction[7:0]; // Verify this indexing
                    2'b01: reg2 <= instruction[7:0]; // Verify this indexing
                    2'b10: reg3 <= instruction[7:0]; // Verify this indexing
                    2'b11: reg4 <= instruction[7:0]; // Verify this indexing
                endcase
            end
        end else begin
            data_in <= reg5;
        end
    end
end

decoder u1_decoder(
    .register1(reg1),
    .register2(reg2),
    .register3(reg3),
    .register4(reg4),
    .sel(instruction[3:2]),
    .data(data1)
);

decoder u2_decoder(
    .register1(reg1),
    .register2(reg2),
    .register3(reg3),
    .register4(reg4),
    .sel(instruction[1:0]),
    .data(data2)
);

SRAM #(
    .ADDR(4),
    .WIDTH(8),
    .LENGTH(16)
) u_SRAM(
    .clk(clk),
    .CS(cs),
    .WE(we),
    .addr(program_counter),
    .data_in(data_in),
    .data_out(instruction)
);

ALU u_ALU(
    .data1(data1),
    .data2(data2),
    .opcode(instruction[5:4]),
    .result(result)
);

endmodule

CPU/CPU_tb.v
`include "CPU.v"

module CPU_tb;

reg clk;
reg cs;
reg we;
reg reset;
wire [7:0] reg1;
wire [7:0] reg2;
wire [7:0] reg3;
wire [7:0] reg4;
wire [7:0] reg5;

always #1 clk = ~clk;

CPU u_CPU(
    .clk(clk),
    .cs(cs),
    .we(we),
    .reset(reset),
    .reg1(reg1),
    .reg2(reg2),
    .reg3(reg3),
    .reg4(reg4),
    .reg5(reg5)
);

initial begin
    $dumpfile("CPU.vcd");
    $dumpvars(0, CPU_tb);
    clk = 0;
    reset = 1;
    cs = 0;
    we = 0;
    #10;
    reset = 0;
    cs = 1;
    
    // Load 0x02 into R1
    // Load 0x04 into R2
    #4; cs = 0;

    // Add R1 and R2, store in R1
    #2; cs = 1;

    // Load 0x05 into R1
    // Load 0x0E into R2
    #4; cs = 0;

    // Subtract R2 from R1, store in R1
    #2; we = 1;

    // Store R1 to memory address 0x06
    #2; cs = 1;

    // Load 0x03 into R2
    #4; cs = 0;

    // Add R2 and R2, store in R1
    #2; cs = 1;

    // Store R1 to memory address 0x04
    #2; we = 1;

    // Load 0x0A into R3
    // Load 0x0B into R4
    #4; cs = 0;

    // Subtract R3 from R4, store in R4
    #2; cs = 1;

    // Store R4 to memory address 0x0B
    #2; we = 1;

    // Load 0x0F into R3
    #2; cs = 0;

    // Store R3 to memory address 0x0F
    $finish;
end

initial begin
    $monitor("Time=%0t | Reg1=%b | Reg2=%b | Reg3=%b | Reg4=%b | Reg5=%b | PC=%b ", 
    $time, reg1, reg2, reg3, reg4, reg5, u_CPU.program_counter);
end

endmodule

CPU/CPU.vcd
$date
	Tue Apr  1 23:37:59 2025
$end
$version
	Icarus Verilog
$end
$timescale
	1s
$end
$scope module CPU_tb $end
$var wire 8 ! reg5 [7:0] $end
$var wire 8 " reg4 [7:0] $end
$var wire 8 # reg3 [7:0] $end
$var wire 8 $ reg2 [7:0] $end
$var wire 8 % reg1 [7:0] $end
$var reg 1 & clk $end
$var reg 1 ' cs $end
$var reg 1 ( reset $end
$var reg 1 ) we $end
$scope module u_CPU $end
$var wire 1 & clk $end
$var wire 1 ' cs $end
$var wire 8 * reg5 [7:0] $end
$var wire 1 ( reset $end
$var wire 1 ) we $end
$var wire 8 + result [7:0] $end
$var wire 8 , instruction [7:0] $end
$var wire 8 - data2 [7:0] $end
$var wire 8 . data1 [7:0] $end
$var reg 8 / data_in [7:0] $end
$var reg 4 0 program_counter [3:0] $end
$var reg 8 1 reg1 [7:0] $end
$var reg 8 2 reg2 [7:0] $end
$var reg 8 3 reg3 [7:0] $end
$var reg 8 4 reg4 [7:0] $end
$scope module u1_decoder $end
$var wire 8 5 register1 [7:0] $end
$var wire 8 6 register2 [7:0] $end
$var wire 8 7 register3 [7:0] $end
$var wire 8 8 register4 [7:0] $end
$var wire 2 9 sel [1:0] $end
$var reg 8 : data [7:0] $end
$upscope $end
$scope module u2_decoder $end
$var wire 8 ; register1 [7:0] $end
$var wire 8 < register2 [7:0] $end
$var wire 8 = register3 [7:0] $end
$var wire 8 > register4 [7:0] $end
$var wire 2 ? sel [1:0] $end
$var reg 8 @ data [7:0] $end
$upscope $end
$scope module u_ALU $end
$var wire 8 A data1 [7:0] $end
$var wire 8 B data2 [7:0] $end
$var wire 2 C opcode [1:0] $end
$var reg 8 D result [7:0] $end
$upscope $end
$scope module u_SRAM $end
$var wire 1 ' CS $end
$var wire 1 ) WE $end
$var wire 4 E addr [3:0] $end
$var wire 1 & clk $end
$var wire 8 F data_in [7:0] $end
$var parameter 32 G ADDR $end
$var parameter 32 H LENGTH $end
$var parameter 32 I WIDTH $end
$var reg 8 J data_out [7:0] $end
$upscope $end
$upscope $end
$upscope $end
$enddefinitions $end
$comment Show the parameter values. $end
$dumpall
b1000 I
b10000 H
b100 G
$end
#0
$dumpvars
bx J
bx F
bx E
bx D
bx C
bx B
bx A
bx @
bx ?
bx >
bx =
bx <
bx ;
bx :
bx 9
bx 8
bx 7
bx 6
bx 5
bx 4
bx 3
bx 2
bx 1
bx 0
bx /
bx .
bx -
bx ,
bx +
bx *
0)
1(
0'
0&
bx %
bx $
bx #
bx "
bx !
$end
#1
b0 0
b0 E
b0 "
b0 4
b0 8
b0 >
b0 #
b0 3
b0 7
b0 =
b0 $
b0 2
b0 6
b0 <
b0 %
b0 1
b0 5
b0 ;
1&
#2
0&
#3
1&
#4
0&
#5
1&
#6
0&
#7
1&
#8
0&
#9
1&
#10
0&
1'
0(
#11
b1 0
b1 E
1&
#12
0&
#13
b10 0
b10 E
1&
#14
0&
0'
#15
b11 0
b11 E
1&
#16
0&
1'
#17
b100 0
b100 E
1&
#18
0&
#19
b101 0
b101 E
1&
#20
0&
0'
#21
b110 0
b110 E
1&
#22
0&
1)
#23
b111 0
b111 E
1&
#24
0&
1'
#25
b1000 0
b1000 E
1&
#26
0&
#27
b1001 0
b1001 E
1&
#28
0&
0'
#29
b1010 0
b1010 E
1&
#30
0&
1'
#31
b1011 0
b1011 E
1&
#32
0&
#33
b1100 0
b1100 E
1&
#34
0&
#35
b1101 0
b1101 E
1&
#36
0&
0'
#37
b1110 0
b1110 E
1&
#38
0&
1'
#39
b1111 0
b1111 E
1&
#40
0&
#41
b0 0
b0 E
1&
#42
0&
0'
