SRAM/SRAM.v
module SRAM(
    input clk,
    input res,
    input WE,
    input [7:0] addr,
    input [31:0] data_in,
    output reg [31:0] data_out
);

reg [31:0] mem[0:255];
integer i;  

always @(posedge clk or posedge res) begin
    if (res) begin
        for (i = 0; i < 256; i = i + 1) begin
            mem[i] = 0;
        end
    end else begin
        if (WE) begin
            mem[addr] <= data_in;
        end 
        else begin
            data_out <= mem[addr];
        end
    end
end

endmodule

SRAM/SRAM_tb.v
`include "SRAM.v"

module SRAM_tb();

reg clk;
reg res;
reg WE;
reg [7:0] addr;
reg [31:0] data_in;
wire [31:0] data_out;

always #1 clk = ~clk; 

SRAM u_sram(
    .clk(clk),
    .res(res),
    .WE(WE),
    .addr(addr),
    .data_in(data_in),
    .data_out(data_out)
);

task my_task;
    begin
    $dumpfile("SRAM.vcd");
    $dumpvars(0, SRAM_tb);
    clk = 0;
    res = 1;  
    #5; 
    res = 0;
    for (addr = 0; addr < 33; addr = addr + 1) begin
        #5;
        WE = 0;  
        if (addr <= 15) begin
            data_in = 32'b0;
            data_in[15 - addr] = 1;  
            data_in[15 + addr] = 1;  
        end 
        else begin
            data_in = 32'b0;
            data_in[addr - 15] = 1;  
            data_in[32 - (addr - 15)] = 1;  
        end
        #5;
        WE = 1;  
    end
    $finish; 
    end 

endtask

initial begin
    my_task();
end

initial begin
    $monitor("Data In: %b | Data Out: %b", data_in, data_out);
end

endmodule

SRAM/SRAM.vcd
$date
	Sun Dec 22 12:13:05 2024
$end
$version
	Icarus Verilog
$end
$timescale
	1s
$end
$scope module SRAM_tb $end
$var wire 32 ! data_out [31:0] $end
$var reg 1 " WE $end
$var reg 8 # addr [7:0] $end
$var reg 1 $ clk $end
$var reg 32 % data_in [31:0] $end
$var reg 1 & res $end
$scope module u_sram $end
$var wire 1 " WE $end
$var wire 8 ' addr [7:0] $end
$var wire 1 $ clk $end
$var wire 32 ( data_in [31:0] $end
$var wire 1 & res $end
$var reg 32 ) data_out [31:0] $end
$var integer 32 * i [31:0] $end
$upscope $end
$scope task my_task $end
$upscope $end
$upscope $end
$enddefinitions $end
#0
$dumpvars
b100000000 *
bx )
bx (
bx '
1&
bx %
0$
bx #
x"
bx !
$end
#1
b100000000 *
1$
#2
0$
#3
b100000000 *
1$
#4
0$
#5
b0 !
b0 )
1$
b0 #
b0 '
0&
#6
0$
#7
1$
#8
0$
#9
1$
#10
0$
b10000000000000000 %
b10000000000000000 (
0"
#11
1$
#12
0$
#13
1$
#14
0$
#15
1$
b1 #
b1 '
1"
#16
0$
#17
1$
#18
0$
#19
1$
#20
0$
b10000000000000000 %
b10000000000000000 (
0"
#21
b10000000000000000 !
b10000000000000000 )
1$
#22
0$
#23
1$
#24
0$
#25
1$
b10 #
b10 '
1"
#26
0$
#27
1$
#28
0$
#29
1$
#30
0$
b10000000000000000 %
b10000000000000000 (
0"
#31
1$
#32
0$
#33
1$
#34
0$
#35
1$
b11 #
b11 '
1"
#36
0$
#37
1$
#38
0$
#39
1$
#40
0$
b10000000000000000 %
b10000000000000000 (
0"
#41
1$
#42
0$
#43
1$
#44
0$
#45
1$
b100 #
b100 '
1"
#46
0$
#47
1$
#48
0$
#49
1$
#50
0$
b10000000000000000 %
b10000000000000000 (
0"
#51
1$
#52
0$
#53
1$
#54
0$
#55
1$
b101 #
b101 '
1"
#56
0$
#57
1$
#58
0$
#59
1$
#60
0$
b10000000000000000 %
b10000000000000000 (
0"
#61
1$
#62
0$
#63
1$
#64
0$
#65
1$
b110 #
b110 '
1"
#66
0$
#67
1$
#68
0$
#69
1$
#70
0$
b10000000000000000 %
b10000000000000000 (
0"
#71
1$
#72
0$
#73
1$
#74
0$
#75
1$
b111 #
b111 '
1"
#76
0$
#77
1$
#78
0$
#79
1$
#80
0$
b10000000000000000 %
b10000000000000000 (
0"
#81
1$
#82
0$
#83
1$
#84
0$
#85
1$
b1000 #
b1000 '
1"
#86
0$
#87
1$
#88
0$
#89
1$
#90
0$
b10000000000000000 %
b10000000000000000 (
0"
#91
1$
#92
0$
#93
1$
#94
0$
#95
1$
b1001 #
b1001 '
1"
#96
0$
#97
1$
#98
0$
#99
1$
#100
0$
b10000000000000000 %
b10000000000000000 (
0"
#101
1$
#102
0$
#103
1$
#104
0$
#105
1$
b1010 #
b1010 '
1"
#106
0$
#107
1$
#108
0$
#109
1$
#110
0$
b10000000000000000 %
b10000000000000000 (
0"
#111
1$
#112
0$
#113
1$
#114
0$
#115
1$
b1011 #
b1011 '
1"
#116
0$
#117
1$
#118
0$
#119
1$
#120
0$
b10000000000000000 %
b10000000000000000 (
0"
#121
1$
#122
0$
#123
1$
#124
0$
#125
1$
b1100 #
b1100 '
1"
#126
0$
#127
1$
#128
0$
#129
1$
#130
0$
b10000000000000000 %
b10000000000000000 (
0"
#131
1$
#132
0$
#133
1$
#134
0$
#135
1$
b1101 #
b1101 '
1"
#136
0$
#137
1$
#138
0$
#139
1$
#140
0$
b10000000000000000 %
b10000000000000000 (
0"
#141
1$
#142
0$
#143
1$
#144
0$
#145
1$
b1110 #
b1110 '
1"
#146
0$
#147
1$
#148
0$
#149
1$
#150
0$
b10000000000000000 %
b10000000000000000 (
0"
#151
1$
#152
0$
#153
1$
#154
0$
#155
1$
b1111 #
b1111 '
1"
#156
0$
#157
1$
#158
0$
#159
1$
#160
0$
b10000000000000000 %
b10000000000000000 (
0"
#161
1$
#162
0$
#163
1$
#164
0$
#165
1$
b10000 #
b10000 '
1"
#166
0$
#167
1$
#168
0$
#169
1$
#170
0$
b11111111111111111111111111111111 %
b11111111111111111111111111111111 (
0"
#171
1$
#172
0$
#173
1$
#174
0$
#175
1$
b10001 #
b10001 '
1"
#176
0$
#177
1$
#178
0$
#179
1$
#180
0$
b10000000000000000 %
b10000000000000000 (
0"
#181
b11111111111111111111111111111111 !
b11111111111111111111111111111111 )
1$
#182
0$
#183
1$
#184
0$
#185
1$
b10010 #
b10010 '
1"
#186
0$
#187
1$
#188
0$
#189
1$
#190
0$
b10000000000000000 %
b10000000000000000 (
0"
#191
b10000000000000000 !
b10000000000000000 )
1$
#192
0$
#193
1$
#194
0$
#195
1$
b10011 #
b10011 '
1"
#196
0$
#197
1$
#198
0$
#199
1$
#200
0$
b10000000000000000 %
b10000000000000000 (
0"
#201
1$
#202
0$
#203
1$
#204
0$
#205
1$
b10100 #
b10100 '
1"
#206
0$
#207
1$
#208
0$
#209
1$
#210
0$
b10000000000000000 %
b10000000000000000 (
0"
#211
1$
#212
0$
#213
1$
#214
0$
#215
1$
b10101 #
b10101 '
1"
#216
0$
#217
1$
#218
0$
#219
1$
#220
0$
b10000000000000000 %
b10000000000000000 (
0"
#221
1$
#222
0$
#223
1$
#224
0$
#225
1$
b10110 #
b10110 '
1"
#226
0$
#227
1$
#228
0$
#229
1$
#230
0$
b10000000000000000 %
b10000000000000000 (
0"
#231
1$
#232
0$
#233
1$
#234
0$
#235
1$
b10111 #
b10111 '
1"
#236
0$
#237
1$
#238
0$
#239
1$
#240
0$
b10000000000000000 %
b10000000000000000 (
0"
#241
1$
#242
0$
#243
1$
#244
0$
#245
1$
b11000 #
b11000 '
1"
#246
0$
#247
1$
#248
0$
#249
1$
#250
0$
b10000000000000000 %
b10000000000000000 (
0"
#251
1$
#252
0$
#253
1$
#254
0$
#255
1$
b11001 #
b11001 '
1"
#256
0$
#257
1$
#258
0$
#259
1$
#260
0$
b10000000000000000 %
b10000000000000000 (
0"
#261
1$
#262
0$
#263
1$
#264
0$
#265
1$
b11010 #
b11010 '
1"
#266
0$
#267
1$
#268
0$
#269
1$
#270
0$
b10000000000000000 %
b10000000000000000 (
0"
#271
1$
#272
0$
#273
1$
#274
0$
#275
1$
b11011 #
b11011 '
1"
#276
0$
#277
1$
#278
0$
#279
1$
#280
0$
b10000000000000000 %
b10000000000000000 (
0"
#281
1$
#282
0$
#283
1$
#284
0$
#285
1$
b11100 #
b11100 '
1"
#286
0$
#287
1$
#288
0$
#289
1$
#290
0$
b10000000000000000 %
b10000000000000000 (
0"
#291
1$
#292
0$
#293
1$
#294
0$
#295
1$
b11101 #
b11101 '
1"
#296
0$
#297
1$
#298
0$
#299
1$
#300
0$
b10000000000000000 %
b10000000000000000 (
0"
#301
1$
#302
0$
#303
1$
#304
0$
#305
1$
b11110 #
b11110 '
1"
#306
0$
#307
1$
#308
0$
#309
1$
#310
0$
b10000000000000000 %
b10000000000000000 (
0"
#311
1$
#312
0$
#313
1$
#314
0$
#315
1$
b11111 #
b11111 '
1"
#316
0$
#317
1$
#318
0$
#319
1$
#320
0$
b10000000000000000 %
b10000000000000000 (
0"
#321
1$
#322
0$
#323
1$
#324
0$
#325
1$
b100000 #
b100000 '
1"
#326
0$
#327
1$
#328
0$
#329
1$
#330
0$
b10000000000000000 %
b10000000000000000 (
0"
#331
1$
#332
0$
#333
1$
#334
0$
#335
1$
b100001 #
b100001 '
1"
