SRAM/SRAM.v
module SRAM(
    input clk,
    input res,
    input WE,
    input [7:0] addr,
    input [31:0] data_in,
    output reg [31:0] data_out
);

reg [31:0] mem[0:255];
integer i;  

always @(posedge clk or posedge res) begin
    if (res) begin
        for (i = 0; i < 256; i = i + 1) begin
            mem[i] = 0;
        end
    end else begin
        if (WE) begin
            mem[addr] <= data_in;
        end 
        else begin
            data_out <= mem[addr];
        end
    end
end

endmodule

SRAM/SRAM_tb.v
`include "SRAM.v"

module SRAM_tb();

reg clk;
reg res;
reg WE;
reg [7:0] addr;
reg [31:0] data_in;
wire [31:0] data_out;

always #1 clk = ~clk; 

SRAM u_sram(
    .clk(clk),
    .res(res),
    .WE(WE),
    .addr(addr),
    .data_in(data_in),
    .data_out(data_out)
);

task my_task;

    begin
    clk = 0;
    res = 1;  
    #5; 
    res = 0;
    for (addr = 0; addr < 255; addr = addr + 1) begin
        #5;
        WE = 0;  
        if (addr%32 <= 15) begin
            data_in = 32'b0;
            data_in[15 - addr%32] = 1;  
            data_in[15 + addr%32] = 1;  
        end 
        else begin
            data_in = 32'b0;
            data_in[addr%32 - 15] = 1;  
            data_in[32 - (addr%32 - 15)] = 1;  
        end
        #5;
        WE = 1;  
    end
    $finish; 
    end 
endtask

initial begin
    $dumpfile("SRAM.vcd");
    $dumpvars(0, SRAM_tb);
    my_task();
end

initial begin
    $monitor("Addr: %d | Data In: %b | Data Out: %b", addr, data_in, data_out);
end

endmodule

SRAM/SRAM.vcd
$date
	Sun Dec 22 16:59:09 2024
$end
$version
	Icarus Verilog
$end
$timescale
	1s
$end
$scope module SRAM_tb $end
$var wire 32 ! data_out [31:0] $end
$var reg 1 " WE $end
$var reg 8 # addr [7:0] $end
$var reg 1 $ clk $end
$var reg 32 % data_in [31:0] $end
$var reg 1 & res $end
$scope module u_sram $end
$var wire 1 " WE $end
$var wire 8 ' addr [7:0] $end
$var wire 1 $ clk $end
$var wire 32 ( data_in [31:0] $end
$var wire 1 & res $end
$var reg 32 ) data_out [31:0] $end
$var integer 32 * i [31:0] $end
$upscope $end
$scope task my_task $end
$upscope $end
$upscope $end
$enddefinitions $end
#0
$dumpvars
b100000000 *
bx )
bx (
bx '
1&
bx %
0$
bx #
x"
bx !
$end
#1
b100000000 *
1$
#2
0$
#3
b100000000 *
1$
#4
0$
#5
b0 !
b0 )
1$
b0 #
b0 '
0&
#6
0$
#7
1$
#8
0$
#9
1$
#10
0$
b1000000000000000 %
b1000000000000000 (
0"
#11
1$
#12
0$
#13
1$
#14
0$
#15
1$
b1 #
b1 '
1"
#16
0$
#17
1$
#18
0$
#19
1$
#20
0$
b10100000000000000 %
b10100000000000000 (
0"
#21
b1000000000000000 !
b1000000000000000 )
1$
#22
0$
#23
1$
#24
0$
#25
1$
b10 #
b10 '
1"
#26
0$
#27
1$
#28
0$
#29
1$
#30
0$
b100010000000000000 %
b100010000000000000 (
0"
#31
b10100000000000000 !
b10100000000000000 )
1$
#32
0$
#33
1$
#34
0$
#35
1$
b11 #
b11 '
1"
#36
0$
#37
1$
#38
0$
#39
1$
#40
0$
b1000001000000000000 %
b1000001000000000000 (
0"
#41
b100010000000000000 !
b100010000000000000 )
1$
#42
0$
#43
1$
#44
0$
#45
1$
b100 #
b100 '
1"
#46
0$
#47
1$
#48
0$
#49
1$
#50
0$
b10000000100000000000 %
b10000000100000000000 (
0"
#51
b1000001000000000000 !
b1000001000000000000 )
1$
#52
0$
#53
1$
#54
0$
#55
1$
b101 #
b101 '
1"
#56
0$
#57
1$
#58
0$
#59
1$
#60
0$
b100000000010000000000 %
b100000000010000000000 (
0"
#61
b10000000100000000000 !
b10000000100000000000 )
1$
#62
0$
#63
1$
#64
0$
#65
1$
b110 #
b110 '
1"
#66
0$
#67
1$
#68
0$
#69
1$
#70
0$
b1000000000001000000000 %
b1000000000001000000000 (
0"
#71
b100000000010000000000 !
b100000000010000000000 )
1$
#72
0$
#73
1$
#74
0$
#75
1$
b111 #
b111 '
1"
#76
0$
#77
1$
#78
0$
#79
1$
#80
0$
b10000000000000100000000 %
b10000000000000100000000 (
0"
#81
b1000000000001000000000 !
b1000000000001000000000 )
1$
#82
0$
#83
1$
#84
0$
#85
1$
b1000 #
b1000 '
1"
#86
0$
#87
1$
#88
0$
#89
1$
#90
0$
b100000000000000010000000 %
b100000000000000010000000 (
0"
#91
b10000000000000100000000 !
b10000000000000100000000 )
1$
#92
0$
#93
1$
#94
0$
#95
1$
b1001 #
b1001 '
1"
#96
0$
#97
1$
#98
0$
#99
1$
#100
0$
b1000000000000000001000000 %
b1000000000000000001000000 (
0"
#101
b100000000000000010000000 !
b100000000000000010000000 )
1$
#102
0$
#103
1$
#104
0$
#105
1$
b1010 #
b1010 '
1"
#106
0$
#107
1$
#108
0$
#109
1$
#110
0$
b10000000000000000000100000 %
b10000000000000000000100000 (
0"
#111
b1000000000000000001000000 !
b1000000000000000001000000 )
1$
#112
0$
#113
1$
#114
0$
#115
1$
b1011 #
b1011 '
1"
#116
0$
#117
1$
#118
0$
#119
1$
#120
0$
b100000000000000000000010000 %
b100000000000000000000010000 (
0"
#121
b10000000000000000000100000 !
b10000000000000000000100000 )
1$
#122
0$
#123
1$
#124
0$
#125
1$
b1100 #
b1100 '
1"
#126
0$
#127
1$
#128
0$
#129
1$
#130
0$
b1000000000000000000000001000 %
b1000000000000000000000001000 (
0"
#131
b100000000000000000000010000 !
b100000000000000000000010000 )
1$
#132
0$
#133
1$
#134
0$
#135
1$
b1101 #
b1101 '
1"
#136
0$
#137
1$
#138
0$
#139
1$
#140
0$
b10000000000000000000000000100 %
b10000000000000000000000000100 (
0"
#141
b1000000000000000000000001000 !
b1000000000000000000000001000 )
1$
#142
0$
#143
1$
#144
0$
#145
1$
b1110 #
b1110 '
1"
#146
0$
#147
1$
#148
0$
#149
1$
#150
0$
b100000000000000000000000000010 %
b100000000000000000000000000010 (
0"
#151
b10000000000000000000000000100 !
b10000000000000000000000000100 )
1$
#152
0$
#153
1$
#154
0$
#155
1$
b1111 #
b1111 '
1"
#156
0$
#157
1$
#158
0$
#159
1$
#160
0$
b1000000000000000000000000000001 %
b1000000000000000000000000000001 (
0"
#161
b100000000000000000000000000010 !
b100000000000000000000000000010 )
1$
#162
0$
#163
1$
#164
0$
#165
1$
b10000 #
b10000 '
1"
#166
0$
#167
1$
#168
0$
#169
1$
#170
0$
b10000000000000000000000000000010 %
b10000000000000000000000000000010 (
0"
#171
b1000000000000000000000000000001 !
b1000000000000000000000000000001 )
1$
#172
0$
#173
1$
#174
0$
#175
1$
b10001 #
b10001 '
1"
#176
0$
#177
1$
#178
0$
#179
1$
#180
0$
b1000000000000000000000000000100 %
b1000000000000000000000000000100 (
0"
#181
b10000000000000000000000000000010 !
b10000000000000000000000000000010 )
1$
#182
0$
#183
1$
#184
0$
#185
1$
b10010 #
b10010 '
1"
#186
0$
#187
1$
#188
0$
#189
1$
#190
0$
b100000000000000000000000001000 %
b100000000000000000000000001000 (
0"
#191
b1000000000000000000000000000100 !
b1000000000000000000000000000100 )
1$
#192
0$
#193
1$
#194
0$
#195
1$
b10011 #
b10011 '
1"
#196
0$
#197
1$
#198
0$
#199
1$
#200
0$
b10000000000000000000000010000 %
b10000000000000000000000010000 (
0"
#201
b100000000000000000000000001000 !
b100000000000000000000000001000 )
1$
#202
0$
#203
1$
#204
0$
#205
1$
b10100 #
b10100 '
1"
#206
0$
#207
1$
#208
0$
#209
1$
#210
0$
b1000000000000000000000100000 %
b1000000000000000000000100000 (
0"
#211
b10000000000000000000000010000 !
b10000000000000000000000010000 )
1$
#212
0$
#213
1$
#214
0$
#215
1$
b10101 #
b10101 '
1"
#216
0$
#217
1$
#218
0$
#219
1$
#220
0$
b100000000000000000001000000 %
b100000000000000000001000000 (
0"
#221
b1000000000000000000000100000 !
b1000000000000000000000100000 )
1$
#222
0$
#223
1$
#224
0$
#225
1$
b10110 #
b10110 '
1"
#226
0$
#227
1$
#228
0$
#229
1$
#230
0$
b10000000000000000010000000 %
b10000000000000000010000000 (
0"
#231
b100000000000000000001000000 !
b100000000000000000001000000 )
1$
#232
0$
#233
1$
#234
0$
#235
1$
b10111 #
b10111 '
1"
#236
0$
#237
1$
#238
0$
#239
1$
#240
0$
b1000000000000000100000000 %
b1000000000000000100000000 (
0"
#241
b10000000000000000010000000 !
b10000000000000000010000000 )
1$
#242
0$
#243
1$
#244
0$
#245
1$
b11000 #
b11000 '
1"
#246
0$
#247
1$
#248
0$
#249
1$
#250
0$
b100000000000001000000000 %
b100000000000001000000000 (
0"
#251
b1000000000000000100000000 !
b1000000000000000100000000 )
1$
#252
0$
#253
1$
#254
0$
#255
1$
b11001 #
b11001 '
1"
#256
0$
#257
1$
#258
0$
#259
1$
#260
0$
b10000000000010000000000 %
b10000000000010000000000 (
0"
#261
b100000000000001000000000 !
b100000000000001000000000 )
1$
#262
0$
#263
1$
#264
0$
#265
1$
b11010 #
b11010 '
1"
#266
0$
#267
1$
#268
0$
#269
1$
#270
0$
b1000000000100000000000 %
b1000000000100000000000 (
0"
#271
b10000000000010000000000 !
b10000000000010000000000 )
1$
#272
0$
#273
1$
#274
0$
#275
1$
b11011 #
b11011 '
1"
#276
0$
#277
1$
#278
0$
#279
1$
#280
0$
b100000001000000000000 %
b100000001000000000000 (
0"
#281
b1000000000100000000000 !
b1000000000100000000000 )
1$
#282
0$
#283
1$
#284
0$
#285
1$
b11100 #
b11100 '
1"
#286
0$
#287
1$
#288
0$
#289
1$
#290
0$
b10000010000000000000 %
b10000010000000000000 (
0"
#291
b100000001000000000000 !
b100000001000000000000 )
1$
#292
0$
#293
1$
#294
0$
#295
1$
b11101 #
b11101 '
1"
#296
0$
#297
1$
#298
0$
#299
1$
#300
0$
b1000100000000000000 %
b1000100000000000000 (
0"
#301
b10000010000000000000 !
b10000010000000000000 )
1$
#302
0$
#303
1$
#304
0$
#305
1$
b11110 #
b11110 '
1"
#306
0$
#307
1$
#308
0$
#309
1$
#310
0$
b101000000000000000 %
b101000000000000000 (
0"
#311
b1000100000000000000 !
b1000100000000000000 )
1$
#312
0$
#313
1$
#314
0$
#315
1$
b11111 #
b11111 '
1"
#316
0$
#317
1$
#318
0$
#319
1$
#320
0$
b10000000000000000 %
b10000000000000000 (
0"
#321
b101000000000000000 !
b101000000000000000 )
1$
#322
0$
#323
1$
#324
0$
#325
1$
b100000 #
b100000 '
1"
#326
0$
#327
1$
#328
0$
#329
1$
#330
0$
b1000000000000000 %
b1000000000000000 (
0"
#331
b10000000000000000 !
b10000000000000000 )
1$
#332
0$
#333
1$
#334
0$
#335
1$
b100001 #
b100001 '
1"
#336
0$
#337
1$
#338
0$
#339
1$
#340
0$
b10100000000000000 %
b10100000000000000 (
0"
#341
b1000000000000000 !
b1000000000000000 )
1$
#342
0$
#343
1$
#344
0$
#345
1$
b100010 #
b100010 '
1"
#346
0$
#347
1$
#348
0$
#349
1$
#350
0$
b100010000000000000 %
b100010000000000000 (
0"
#351
b10100000000000000 !
b10100000000000000 )
1$
#352
0$
#353
1$
#354
0$
#355
1$
b100011 #
b100011 '
1"
#356
0$
#357
1$
#358
0$
#359
1$
#360
0$
b1000001000000000000 %
b1000001000000000000 (
0"
#361
b100010000000000000 !
b100010000000000000 )
1$
#362
0$
#363
1$
#364
0$
#365
1$
b100100 #
b100100 '
1"
#366
0$
#367
1$
#368
0$
#369
1$
#370
0$
b10000000100000000000 %
b10000000100000000000 (
0"
#371
b1000001000000000000 !
b1000001000000000000 )
1$
#372
0$
#373
1$
#374
0$
#375
1$
b100101 #
b100101 '
1"
#376
0$
#377
1$
#378
0$
#379
1$
#380
0$
b100000000010000000000 %
b100000000010000000000 (
0"
#381
b10000000100000000000 !
b10000000100000000000 )
1$
#382
0$
#383
1$
#384
0$
#385
1$
b100110 #
b100110 '
1"
#386
0$
#387
1$
#388
0$
#389
1$
#390
0$
b1000000000001000000000 %
b1000000000001000000000 (
0"
#391
b100000000010000000000 !
b100000000010000000000 )
1$
#392
0$
#393
1$
#394
0$
#395
1$
b100111 #
b100111 '
1"
#396
0$
#397
1$
#398
0$
#399
1$
#400
0$
b10000000000000100000000 %
b10000000000000100000000 (
0"
#401
b1000000000001000000000 !
b1000000000001000000000 )
1$
#402
0$
#403
1$
#404
0$
#405
1$
b101000 #
b101000 '
1"
#406
0$
#407
1$
#408
0$
#409
1$
#410
0$
b100000000000000010000000 %
b100000000000000010000000 (
0"
#411
b10000000000000100000000 !
b10000000000000100000000 )
1$
#412
0$
#413
1$
#414
0$
#415
1$
b101001 #
b101001 '
1"
#416
0$
#417
1$
#418
0$
#419
1$
#420
0$
b1000000000000000001000000 %
b1000000000000000001000000 (
0"
#421
b100000000000000010000000 !
b100000000000000010000000 )
1$
#422
0$
#423
1$
#424
0$
#425
1$
b101010 #
b101010 '
1"
#426
0$
#427
1$
#428
0$
#429
1$
#430
0$
b10000000000000000000100000 %
b10000000000000000000100000 (
0"
#431
b1000000000000000001000000 !
b1000000000000000001000000 )
1$
#432
0$
#433
1$
#434
0$
#435
1$
b101011 #
b101011 '
1"
#436
0$
#437
1$
#438
0$
#439
1$
#440
0$
b100000000000000000000010000 %
b100000000000000000000010000 (
0"
#441
b10000000000000000000100000 !
b10000000000000000000100000 )
1$
#442
0$
#443
1$
#444
0$
#445
1$
b101100 #
b101100 '
1"
#446
0$
#447
1$
#448
0$
#449
1$
#450
0$
b1000000000000000000000001000 %
b1000000000000000000000001000 (
0"
#451
b100000000000000000000010000 !
b100000000000000000000010000 )
1$
#452
0$
#453
1$
#454
0$
#455
1$
b101101 #
b101101 '
1"
#456
0$
#457
1$
#458
0$
#459
1$
#460
0$
b10000000000000000000000000100 %
b10000000000000000000000000100 (
0"
#461
b1000000000000000000000001000 !
b1000000000000000000000001000 )
1$
#462
0$
#463
1$
#464
0$
#465
1$
b101110 #
b101110 '
1"
#466
0$
#467
1$
#468
0$
#469
1$
#470
0$
b100000000000000000000000000010 %
b100000000000000000000000000010 (
0"
#471
b10000000000000000000000000100 !
b10000000000000000000000000100 )
1$
#472
0$
#473
1$
#474
0$
#475
1$
b101111 #
b101111 '
1"
#476
0$
#477
1$
#478
0$
#479
1$
#480
0$
b1000000000000000000000000000001 %
b1000000000000000000000000000001 (
0"
#481
b100000000000000000000000000010 !
b100000000000000000000000000010 )
1$
#482
0$
#483
1$
#484
0$
#485
1$
b110000 #
b110000 '
1"
#486
0$
#487
1$
#488
0$
#489
1$
#490
0$
b10000000000000000000000000000010 %
b10000000000000000000000000000010 (
0"
#491
b1000000000000000000000000000001 !
b1000000000000000000000000000001 )
1$
#492
0$
#493
1$
#494
0$
#495
1$
b110001 #
b110001 '
1"
#496
0$
#497
1$
#498
0$
#499
1$
#500
0$
b1000000000000000000000000000100 %
b1000000000000000000000000000100 (
0"
#501
b10000000000000000000000000000010 !
b10000000000000000000000000000010 )
1$
#502
0$
#503
1$
#504
0$
#505
1$
b110010 #
b110010 '
1"
#506
0$
#507
1$
#508
0$
#509
1$
#510
0$
b100000000000000000000000001000 %
b100000000000000000000000001000 (
0"
#511
b1000000000000000000000000000100 !
b1000000000000000000000000000100 )
1$
#512
0$
#513
1$
#514
0$
#515
1$
b110011 #
b110011 '
1"
#516
0$
#517
1$
#518
0$
#519
1$
#520
0$
b10000000000000000000000010000 %
b10000000000000000000000010000 (
0"
#521
b100000000000000000000000001000 !
b100000000000000000000000001000 )
1$
#522
0$
#523
1$
#524
0$
#525
1$
b110100 #
b110100 '
1"
#526
0$
#527
1$
#528
0$
#529
1$
#530
0$
b1000000000000000000000100000 %
b1000000000000000000000100000 (
0"
#531
b10000000000000000000000010000 !
b10000000000000000000000010000 )
1$
#532
0$
#533
1$
#534
0$
#535
1$
b110101 #
b110101 '
1"
#536
0$
#537
1$
#538
0$
#539
1$
#540
0$
b100000000000000000001000000 %
b100000000000000000001000000 (
0"
#541
b1000000000000000000000100000 !
b1000000000000000000000100000 )
1$
#542
0$
#543
1$
#544
0$
#545
1$
b110110 #
b110110 '
1"
#546
0$
#547
1$
#548
0$
#549
1$
#550
0$
b10000000000000000010000000 %
b10000000000000000010000000 (
0"
#551
b100000000000000000001000000 !
b100000000000000000001000000 )
1$
#552
0$
#553
1$
#554
0$
#555
1$
b110111 #
b110111 '
1"
#556
0$
#557
1$
#558
0$
#559
1$
#560
0$
b1000000000000000100000000 %
b1000000000000000100000000 (
0"
#561
b10000000000000000010000000 !
b10000000000000000010000000 )
1$
#562
0$
#563
1$
#564
0$
#565
1$
b111000 #
b111000 '
1"
#566
0$
#567
1$
#568
0$
#569
1$
#570
0$
b100000000000001000000000 %
b100000000000001000000000 (
0"
#571
b1000000000000000100000000 !
b1000000000000000100000000 )
1$
#572
0$
#573
1$
#574
0$
#575
1$
b111001 #
b111001 '
1"
#576
0$
#577
1$
#578
0$
#579
1$
#580
0$
b10000000000010000000000 %
b10000000000010000000000 (
0"
#581
b100000000000001000000000 !
b100000000000001000000000 )
1$
#582
0$
#583
1$
#584
0$
#585
1$
b111010 #
b111010 '
1"
#586
0$
#587
1$
#588
0$
#589
1$
#590
0$
b1000000000100000000000 %
b1000000000100000000000 (
0"
#591
b10000000000010000000000 !
b10000000000010000000000 )
1$
#592
0$
#593
1$
#594
0$
#595
1$
b111011 #
b111011 '
1"
#596
0$
#597
1$
#598
0$
#599
1$
#600
0$
b100000001000000000000 %
b100000001000000000000 (
0"
#601
b1000000000100000000000 !
b1000000000100000000000 )
1$
#602
0$
#603
1$
#604
0$
#605
1$
b111100 #
b111100 '
1"
#606
0$
#607
1$
#608
0$
#609
1$
#610
0$
b10000010000000000000 %
b10000010000000000000 (
0"
#611
b100000001000000000000 !
b100000001000000000000 )
1$
#612
0$
#613
1$
#614
0$
#615
1$
b111101 #
b111101 '
1"
#616
0$
#617
1$
#618
0$
#619
1$
#620
0$
b1000100000000000000 %
b1000100000000000000 (
0"
#621
b10000010000000000000 !
b10000010000000000000 )
1$
#622
0$
#623
1$
#624
0$
#625
1$
b111110 #
b111110 '
1"
#626
0$
#627
1$
#628
0$
#629
1$
#630
0$
b101000000000000000 %
b101000000000000000 (
0"
#631
b1000100000000000000 !
b1000100000000000000 )
1$
#632
0$
#633
1$
#634
0$
#635
1$
b111111 #
b111111 '
1"
#636
0$
#637
1$
#638
0$
#639
1$
#640
0$
b10000000000000000 %
b10000000000000000 (
0"
#641
b101000000000000000 !
b101000000000000000 )
1$
#642
0$
#643
1$
#644
0$
#645
1$
b1000000 #
b1000000 '
1"
#646
0$
#647
1$
#648
0$
#649
1$
#650
0$
b1000000000000000 %
b1000000000000000 (
0"
#651
b10000000000000000 !
b10000000000000000 )
1$
#652
0$
#653
1$
#654
0$
#655
1$
b1000001 #
b1000001 '
1"
#656
0$
#657
1$
#658
0$
#659
1$
#660
0$
b10100000000000000 %
b10100000000000000 (
0"
#661
b1000000000000000 !
b1000000000000000 )
1$
#662
0$
#663
1$
#664
0$
#665
1$
b1000010 #
b1000010 '
1"
#666
0$
#667
1$
#668
0$
#669
1$
#670
0$
b100010000000000000 %
b100010000000000000 (
0"
#671
b10100000000000000 !
b10100000000000000 )
1$
#672
0$
#673
1$
#674
0$
#675
1$
b1000011 #
b1000011 '
1"
#676
0$
#677
1$
#678
0$
#679
1$
#680
0$
b1000001000000000000 %
b1000001000000000000 (
0"
#681
b100010000000000000 !
b100010000000000000 )
1$
#682
0$
#683
1$
#684
0$
#685
1$
b1000100 #
b1000100 '
1"
#686
0$
#687
1$
#688
0$
#689
1$
#690
0$
b10000000100000000000 %
b10000000100000000000 (
0"
#691
b1000001000000000000 !
b1000001000000000000 )
1$
#692
0$
#693
1$
#694
0$
#695
1$
b1000101 #
b1000101 '
1"
#696
0$
#697
1$
#698
0$
#699
1$
#700
0$
b100000000010000000000 %
b100000000010000000000 (
0"
#701
b10000000100000000000 !
b10000000100000000000 )
1$
#702
0$
#703
1$
#704
0$
#705
1$
b1000110 #
b1000110 '
1"
#706
0$
#707
1$
#708
0$
#709
1$
#710
0$
b1000000000001000000000 %
b1000000000001000000000 (
0"
#711
b100000000010000000000 !
b100000000010000000000 )
1$
#712
0$
#713
1$
#714
0$
#715
1$
b1000111 #
b1000111 '
1"
#716
0$
#717
1$
#718
0$
#719
1$
#720
0$
b10000000000000100000000 %
b10000000000000100000000 (
0"
#721
b1000000000001000000000 !
b1000000000001000000000 )
1$
#722
0$
#723
1$
#724
0$
#725
1$
b1001000 #
b1001000 '
1"
#726
0$
#727
1$
#728
0$
#729
1$
#730
0$
b100000000000000010000000 %
b100000000000000010000000 (
0"
#731
b10000000000000100000000 !
b10000000000000100000000 )
1$
#732
0$
#733
1$
#734
0$
#735
1$
b1001001 #
b1001001 '
1"
#736
0$
#737
1$
#738
0$
#739
1$
#740
0$
b1000000000000000001000000 %
b1000000000000000001000000 (
0"
#741
b100000000000000010000000 !
b100000000000000010000000 )
1$
#742
0$
#743
1$
#744
0$
#745
1$
b1001010 #
b1001010 '
1"
#746
0$
#747
1$
#748
0$
#749
1$
#750
0$
b10000000000000000000100000 %
b10000000000000000000100000 (
0"
#751
b1000000000000000001000000 !
b1000000000000000001000000 )
1$
#752
0$
#753
1$
#754
0$
#755
1$
b1001011 #
b1001011 '
1"
#756
0$
#757
1$
#758
0$
#759
1$
#760
0$
b100000000000000000000010000 %
b100000000000000000000010000 (
0"
#761
b10000000000000000000100000 !
b10000000000000000000100000 )
1$
#762
0$
#763
1$
#764
0$
#765
1$
b1001100 #
b1001100 '
1"
#766
0$
#767
1$
#768
0$
#769
1$
#770
0$
b1000000000000000000000001000 %
b1000000000000000000000001000 (
0"
#771
b100000000000000000000010000 !
b100000000000000000000010000 )
1$
#772
0$
#773
1$
#774
0$
#775
1$
b1001101 #
b1001101 '
1"
#776
0$
#777
1$
#778
0$
#779
1$
#780
0$
b10000000000000000000000000100 %
b10000000000000000000000000100 (
0"
#781
b1000000000000000000000001000 !
b1000000000000000000000001000 )
1$
#782
0$
#783
1$
#784
0$
#785
1$
b1001110 #
b1001110 '
1"
#786
0$
#787
1$
#788
0$
#789
1$
#790
0$
b100000000000000000000000000010 %
b100000000000000000000000000010 (
0"
#791
b10000000000000000000000000100 !
b10000000000000000000000000100 )
1$
#792
0$
#793
1$
#794
0$
#795
1$
b1001111 #
b1001111 '
1"
#796
0$
#797
1$
#798
0$
#799
1$
#800
0$
b1000000000000000000000000000001 %
b1000000000000000000000000000001 (
0"
#801
b100000000000000000000000000010 !
b100000000000000000000000000010 )
1$
#802
0$
#803
1$
#804
0$
#805
1$
b1010000 #
b1010000 '
1"
#806
0$
#807
1$
#808
0$
#809
1$
#810
0$
b10000000000000000000000000000010 %
b10000000000000000000000000000010 (
0"
#811
b1000000000000000000000000000001 !
b1000000000000000000000000000001 )
1$
#812
0$
#813
1$
#814
0$
#815
1$
b1010001 #
b1010001 '
1"
#816
0$
#817
1$
#818
0$
#819
1$
#820
0$
b1000000000000000000000000000100 %
b1000000000000000000000000000100 (
0"
#821
b10000000000000000000000000000010 !
b10000000000000000000000000000010 )
1$
#822
0$
#823
1$
#824
0$
#825
1$
b1010010 #
b1010010 '
1"
#826
0$
#827
1$
#828
0$
#829
1$
#830
0$
b100000000000000000000000001000 %
b100000000000000000000000001000 (
0"
#831
b1000000000000000000000000000100 !
b1000000000000000000000000000100 )
1$
#832
0$
#833
1$
#834
0$
#835
1$
b1010011 #
b1010011 '
1"
#836
0$
#837
1$
#838
0$
#839
1$
#840
0$
b10000000000000000000000010000 %
b10000000000000000000000010000 (
0"
#841
b100000000000000000000000001000 !
b100000000000000000000000001000 )
1$
#842
0$
#843
1$
#844
0$
#845
1$
b1010100 #
b1010100 '
1"
#846
0$
#847
1$
#848
0$
#849
1$
#850
0$
b1000000000000000000000100000 %
b1000000000000000000000100000 (
0"
#851
b10000000000000000000000010000 !
b10000000000000000000000010000 )
1$
#852
0$
#853
1$
#854
0$
#855
1$
b1010101 #
b1010101 '
1"
#856
0$
#857
1$
#858
0$
#859
1$
#860
0$
b100000000000000000001000000 %
b100000000000000000001000000 (
0"
#861
b1000000000000000000000100000 !
b1000000000000000000000100000 )
1$
#862
0$
#863
1$
#864
0$
#865
1$
b1010110 #
b1010110 '
1"
#866
0$
#867
1$
#868
0$
#869
1$
#870
0$
b10000000000000000010000000 %
b10000000000000000010000000 (
0"
#871
b100000000000000000001000000 !
b100000000000000000001000000 )
1$
#872
0$
#873
1$
#874
0$
#875
1$
b1010111 #
b1010111 '
1"
#876
0$
#877
1$
#878
0$
#879
1$
#880
0$
b1000000000000000100000000 %
b1000000000000000100000000 (
0"
#881
b10000000000000000010000000 !
b10000000000000000010000000 )
1$
#882
0$
#883
1$
#884
0$
#885
1$
b1011000 #
b1011000 '
1"
#886
0$
#887
1$
#888
0$
#889
1$
#890
0$
b100000000000001000000000 %
b100000000000001000000000 (
0"
#891
b1000000000000000100000000 !
b1000000000000000100000000 )
1$
#892
0$
#893
1$
#894
0$
#895
1$
b1011001 #
b1011001 '
1"
#896
0$
#897
1$
#898
0$
#899
1$
#900
0$
b10000000000010000000000 %
b10000000000010000000000 (
0"
#901
b100000000000001000000000 !
b100000000000001000000000 )
1$
#902
0$
#903
1$
#904
0$
#905
1$
b1011010 #
b1011010 '
1"
#906
0$
#907
1$
#908
0$
#909
1$
#910
0$
b1000000000100000000000 %
b1000000000100000000000 (
0"
#911
b10000000000010000000000 !
b10000000000010000000000 )
1$
#912
0$
#913
1$
#914
0$
#915
1$
b1011011 #
b1011011 '
1"
#916
0$
#917
1$
#918
0$
#919
1$
#920
0$
b100000001000000000000 %
b100000001000000000000 (
0"
#921
b1000000000100000000000 !
b1000000000100000000000 )
1$
#922
0$
#923
1$
#924
0$
#925
1$
b1011100 #
b1011100 '
1"
#926
0$
#927
1$
#928
0$
#929
1$
#930
0$
b10000010000000000000 %
b10000010000000000000 (
0"
#931
b100000001000000000000 !
b100000001000000000000 )
1$
#932
0$
#933
1$
#934
0$
#935
1$
b1011101 #
b1011101 '
1"
#936
0$
#937
1$
#938
0$
#939
1$
#940
0$
b1000100000000000000 %
b1000100000000000000 (
0"
#941
b10000010000000000000 !
b10000010000000000000 )
1$
#942
0$
#943
1$
#944
0$
#945
1$
b1011110 #
b1011110 '
1"
#946
0$
#947
1$
#948
0$
#949
1$
#950
0$
b101000000000000000 %
b101000000000000000 (
0"
#951
b1000100000000000000 !
b1000100000000000000 )
1$
#952
0$
#953
1$
#954
0$
#955
1$
b1011111 #
b1011111 '
1"
#956
0$
#957
1$
#958
0$
#959
1$
#960
0$
b10000000000000000 %
b10000000000000000 (
0"
#961
b101000000000000000 !
b101000000000000000 )
1$
#962
0$
#963
1$
#964
0$
#965
1$
b1100000 #
b1100000 '
1"
#966
0$
#967
1$
#968
0$
#969
1$
#970
0$
b1000000000000000 %
b1000000000000000 (
0"
#971
b10000000000000000 !
b10000000000000000 )
1$
#972
0$
#973
1$
#974
0$
#975
1$
b1100001 #
b1100001 '
1"
#976
0$
#977
1$
#978
0$
#979
1$
#980
0$
b10100000000000000 %
b10100000000000000 (
0"
#981
b1000000000000000 !
b1000000000000000 )
1$
#982
0$
#983
1$
#984
0$
#985
1$
b1100010 #
b1100010 '
1"
#986
0$
#987
1$
#988
0$
#989
1$
#990
0$
b100010000000000000 %
b100010000000000000 (
0"
#991
b10100000000000000 !
b10100000000000000 )
1$
#992
0$
#993
1$
#994
0$
#995
1$
b1100011 #
b1100011 '
1"
#996
0$
#997
1$
#998
0$
#999
1$
#1000
0$
b1000001000000000000 %
b1000001000000000000 (
0"
#1001
b100010000000000000 !
b100010000000000000 )
1$
#1002
0$
#1003
1$
#1004
0$
#1005
1$
b1100100 #
b1100100 '
1"
#1006
0$
#1007
1$
#1008
0$
#1009
1$
#1010
0$
b10000000100000000000 %
b10000000100000000000 (
0"
#1011
b1000001000000000000 !
b1000001000000000000 )
1$
#1012
0$
#1013
1$
#1014
0$
#1015
1$
b1100101 #
b1100101 '
1"
#1016
0$
#1017
1$
#1018
0$
#1019
1$
#1020
0$
b100000000010000000000 %
b100000000010000000000 (
0"
#1021
b10000000100000000000 !
b10000000100000000000 )
1$
#1022
0$
#1023
1$
#1024
0$
#1025
1$
b1100110 #
b1100110 '
1"
#1026
0$
#1027
1$
#1028
0$
#1029
1$
#1030
0$
b1000000000001000000000 %
b1000000000001000000000 (
0"
#1031
b100000000010000000000 !
b100000000010000000000 )
1$
#1032
0$
#1033
1$
#1034
0$
#1035
1$
b1100111 #
b1100111 '
1"
#1036
0$
#1037
1$
#1038
0$
#1039
1$
#1040
0$
b10000000000000100000000 %
b10000000000000100000000 (
0"
#1041
b1000000000001000000000 !
b1000000000001000000000 )
1$
#1042
0$
#1043
1$
#1044
0$
#1045
1$
b1101000 #
b1101000 '
1"
#1046
0$
#1047
1$
#1048
0$
#1049
1$
#1050
0$
b100000000000000010000000 %
b100000000000000010000000 (
0"
#1051
b10000000000000100000000 !
b10000000000000100000000 )
1$
#1052
0$
#1053
1$
#1054
0$
#1055
1$
b1101001 #
b1101001 '
1"
#1056
0$
#1057
1$
#1058
0$
#1059
1$
#1060
0$
b1000000000000000001000000 %
b1000000000000000001000000 (
0"
#1061
b100000000000000010000000 !
b100000000000000010000000 )
1$
#1062
0$
#1063
1$
#1064
0$
#1065
1$
b1101010 #
b1101010 '
1"
#1066
0$
#1067
1$
#1068
0$
#1069
1$
#1070
0$
b10000000000000000000100000 %
b10000000000000000000100000 (
0"
#1071
b1000000000000000001000000 !
b1000000000000000001000000 )
1$
#1072
0$
#1073
1$
#1074
0$
#1075
1$
b1101011 #
b1101011 '
1"
#1076
0$
#1077
1$
#1078
0$
#1079
1$
#1080
0$
b100000000000000000000010000 %
b100000000000000000000010000 (
0"
