SRAM/SRAM.v
module SRAM(
    input clk,
    input res,
    input WE,
    input [7:0] addr,
    input [31:0] data_in,
    output reg [31:0] data_out
);

reg [31:0] mem[0:255];
integer i;  

always @(posedge clk or posedge res) begin
    if (res) begin
        for (i = 0; i < 256; i = i + 1) begin
            mem[i] = 0;
        end
    end else begin
        if (WE) begin
            mem[addr] <= data_in;
        end 
        else begin
            data_out <= mem[addr];
        end
    end
end

endmodule

SRAM/SRAM_tb.v
`include "SRAM.v"

module SRAM_tb();

reg clk;
reg res;
reg WE;
reg [7:0] addr;
reg [31:0] data_in;
wire [31:0] data_out;

always #2 clk = ~clk; 

SRAM u_sram(
    .clk(clk),
    .res(res),
    .WE(WE),
    .addr(addr),
    .data_in(data_in),
    .data_out(data_out)
);

initial begin
    $dumpfile("SRAM.vcd");
    $dumpvars(0, SRAM_tb);
    clk = 0;
    res = 1; 
    addr = 0; 
    data_in = 0; 
    WE = 0;
    
    #5; 
    res = 0;

    for (addr = 0; addr < 32; addr = addr + 1) begin
        #5;  
        if (addr <= 15) begin
            data_in = 32'b0;
            data_in[15 - addr] = 1;  
            data_in[15 + addr] = 1;  
        end else begin
            data_in = 32'b0;
            data_in[addr - 15] = 1;  
            data_in[31 - (addr - 15)] = 1;  
        end
        
        #5;
        WE = 1;
        #5;
        WE = 0;  
    end

    $finish;  
end

initial begin
    $monitor("Time: %0t | Addr: %0d | Data In: %b | Data Out: %b", $time, addr, data_in, data_out);
end

endmodule

SRAM/SRAM.vcd
$date
	Sun Dec 22 01:01:21 2024
$end
$version
	Icarus Verilog
$end
$timescale
	1s
$end
$scope module SRAM_tb $end
$var wire 32 ! data_out [31:0] $end
$var reg 1 " WE $end
$var reg 8 # addr [7:0] $end
$var reg 1 $ clk $end
$var reg 32 % data_in [31:0] $end
$var reg 1 & res $end
$scope module u_sram $end
$var wire 1 " WE $end
$var wire 8 ' addr [7:0] $end
$var wire 1 $ clk $end
$var wire 32 ( data_in [31:0] $end
$var wire 1 & res $end
$var reg 32 ) data_out [31:0] $end
$var integer 32 * i [31:0] $end
$upscope $end
$upscope $end
$enddefinitions $end
#0
$dumpvars
b100000000 *
bx )
b0 (
b0 '
1&
b0 %
0$
b0 #
0"
bx !
$end
#2
b100000000 *
1$
#4
0$
#5
0&
#6
b0 !
b0 )
1$
#8
0$
#10
1$
b1000000000000000 %
b1000000000000000 (
#12
0$
#14
1$
#15
1"
#16
0$
#18
1$
#20
0$
b1 #
b1 '
0"
#22
1$
#24
0$
#25
b10100000000000000 %
b10100000000000000 (
#26
1$
#28
0$
#30
1$
1"
#32
0$
#34
1$
#35
b10 #
b10 '
0"
#36
0$
#38
1$
#40
0$
b100010000000000000 %
b100010000000000000 (
#42
1$
#44
0$
#45
1"
#46
1$
#48
0$
#50
1$
b11 #
b11 '
0"
#52
0$
#54
1$
#55
b1000001000000000000 %
b1000001000000000000 (
#56
0$
#58
1$
#60
0$
1"
#62
1$
#64
0$
#65
b100 #
b100 '
0"
#66
1$
#68
0$
#70
1$
b10000000100000000000 %
b10000000100000000000 (
#72
0$
#74
1$
#75
1"
#76
0$
#78
1$
#80
0$
b101 #
b101 '
0"
#82
1$
#84
0$
#85
b100000000010000000000 %
b100000000010000000000 (
#86
1$
#88
0$
#90
1$
1"
#92
0$
#94
1$
#95
b110 #
b110 '
0"
#96
0$
#98
1$
#100
0$
b1000000000001000000000 %
b1000000000001000000000 (
#102
1$
#104
0$
#105
1"
#106
1$
#108
0$
#110
1$
b111 #
b111 '
0"
#112
0$
#114
1$
#115
b10000000000000100000000 %
b10000000000000100000000 (
#116
0$
#118
1$
#120
0$
1"
#122
1$
#124
0$
#125
b1000 #
b1000 '
0"
#126
1$
#128
0$
#130
1$
b100000000000000010000000 %
b100000000000000010000000 (
#132
0$
#134
1$
#135
1"
#136
0$
#138
1$
#140
0$
b1001 #
b1001 '
0"
#142
1$
#144
0$
#145
b1000000000000000001000000 %
b1000000000000000001000000 (
#146
1$
#148
0$
#150
1$
1"
#152
0$
#154
1$
#155
b1010 #
b1010 '
0"
#156
0$
#158
1$
#160
0$
b10000000000000000000100000 %
b10000000000000000000100000 (
#162
1$
#164
0$
#165
1"
#166
1$
#168
0$
#170
1$
b1011 #
b1011 '
0"
#172
0$
#174
1$
#175
b100000000000000000000010000 %
b100000000000000000000010000 (
#176
0$
#178
1$
#180
0$
1"
#182
1$
#184
0$
#185
b1100 #
b1100 '
0"
#186
1$
#188
0$
#190
1$
b1000000000000000000000001000 %
b1000000000000000000000001000 (
#192
0$
#194
1$
#195
1"
#196
0$
#198
1$
#200
0$
b1101 #
b1101 '
0"
#202
1$
#204
0$
#205
b10000000000000000000000000100 %
b10000000000000000000000000100 (
#206
1$
#208
0$
#210
1$
1"
#212
0$
#214
1$
#215
b1110 #
b1110 '
0"
#216
0$
#218
1$
#220
0$
b100000000000000000000000000010 %
b100000000000000000000000000010 (
#222
1$
#224
0$
#225
1"
#226
1$
#228
0$
#230
1$
b1111 #
b1111 '
0"
#232
0$
#234
1$
#235
b1000000000000000000000000000001 %
b1000000000000000000000000000001 (
#236
0$
#238
1$
#240
0$
1"
#242
1$
#244
0$
#245
b10000 #
b10000 '
0"
#246
1$
#248
0$
#250
1$
b1000000000000000000000000000010 %
b1000000000000000000000000000010 (
#252
0$
#254
1$
#255
1"
#256
0$
#258
1$
#260
0$
b10001 #
b10001 '
0"
#262
1$
#264
0$
#265
b100000000000000000000000000100 %
b100000000000000000000000000100 (
#266
1$
#268
0$
#270
1$
1"
#272
0$
#274
1$
#275
b10010 #
b10010 '
0"
#276
0$
#278
1$
#280
0$
b10000000000000000000000001000 %
b10000000000000000000000001000 (
#282
1$
#284
0$
#285
1"
#286
1$
#288
0$
#290
1$
b10011 #
b10011 '
0"
#292
0$
#294
1$
#295
b1000000000000000000000010000 %
b1000000000000000000000010000 (
#296
0$
#298
1$
#300
0$
1"
#302
1$
#304
0$
#305
b10100 #
b10100 '
0"
#306
1$
#308
0$
#310
1$
b100000000000000000000100000 %
b100000000000000000000100000 (
#312
0$
#314
1$
#315
1"
#316
0$
#318
1$
#320
0$
b10101 #
b10101 '
0"
#322
1$
#324
0$
#325
b10000000000000000001000000 %
b10000000000000000001000000 (
#326
1$
#328
0$
#330
1$
1"
#332
0$
#334
1$
#335
b10110 #
b10110 '
0"
#336
0$
#338
1$
#340
0$
b1000000000000000010000000 %
b1000000000000000010000000 (
#342
1$
#344
0$
#345
1"
#346
1$
#348
0$
#350
1$
b10111 #
b10111 '
0"
#352
0$
#354
1$
#355
b100000000000000100000000 %
b100000000000000100000000 (
#356
0$
#358
1$
#360
0$
1"
#362
1$
#364
0$
#365
b11000 #
b11000 '
0"
#366
1$
#368
0$
#370
1$
b10000000000001000000000 %
b10000000000001000000000 (
#372
0$
#374
1$
#375
1"
#376
0$
#378
1$
#380
0$
b11001 #
b11001 '
0"
#382
1$
#384
0$
#385
b1000000000010000000000 %
b1000000000010000000000 (
#386
1$
#388
0$
#390
1$
1"
#392
0$
#394
1$
#395
b11010 #
b11010 '
0"
#396
0$
#398
1$
#400
0$
b100000000100000000000 %
b100000000100000000000 (
#402
1$
#404
0$
#405
1"
#406
1$
#408
0$
#410
1$
b11011 #
b11011 '
0"
#412
0$
#414
1$
#415
b10000001000000000000 %
b10000001000000000000 (
#416
0$
#418
1$
#420
0$
1"
#422
1$
#424
0$
#425
b11100 #
b11100 '
0"
#426
1$
#428
0$
#430
1$
b1000010000000000000 %
b1000010000000000000 (
#432
0$
#434
1$
#435
1"
#436
0$
#438
1$
#440
0$
b11101 #
b11101 '
0"
#442
1$
#444
0$
#445
b100100000000000000 %
b100100000000000000 (
#446
1$
#448
0$
#450
1$
1"
#452
0$
#454
1$
#455
b11110 #
b11110 '
0"
#456
0$
#458
1$
#460
0$
b11000000000000000 %
b11000000000000000 (
#462
1$
#464
0$
#465
1"
#466
1$
#468
0$
#470
1$
b11111 #
b11111 '
0"
#472
0$
#474
1$
#475
b11000000000000000 %
b11000000000000000 (
#476
0$
#478
1$
#480
0$
1"
#482
1$
#484
0$
#485
b100000 #
b100000 '
0"
