SRAM/SRAM.v
module SRAM #(
    parameter ADDR=8, 
    parameter WIDTH=32, 
    parameter LENGTH=256
    )(
    input clk,
    input CS,
    input WE,
    input [ADDR-1:0] addr,
    input [WIDTH-1:0] data_in,
    output [WIDTH-1:0] instruction,
    output reg[WIDTH-1:0] data_out
);

reg [WIDTH-1:0] mem[0:LENGTH-1];

initial begin
    $readmemb("C:/Users/HP/Desktop/Verilog/SRAM/file.txt", mem);
end

assign instruction=mem[addr];

always @(posedge clk) begin
    if(CS)begin
        if (WE) begin
            mem[addr] <= data_in;
        end 
        else begin
            data_out <= mem[addr];
        end
    end
end

endmodule

SRAM/SRAM_tb.v
`include "SRAM.v"

module SRAM_tb();

reg clk;
reg WE;
reg [7:0] addr;
reg [31:0] data_in;
wire [31:0] data_out;

always #1 clk = ~clk; 

SRAM #(
    .WIDTH(32),
    .LENGTH(256)
)u_sram(
    .clk(clk),
    .WE(WE),
    .addr(addr),
    .data_in(data_in),
    .data_out(data_out)
);

integer i;

task my_task;
    begin
    clk = 0;
    #5; 
    for (i = 0; i < 256; i = i + 1) begin
        addr = i;       
        #5;
        WE = 0;
        data_in=32'b0;         
        data_in[i%32] = 1;  
        data_in[31 - i%32] = 1; 
        $display("Addr: %d | Data Out: %b", addr, data_out); 
        #5;
        WE = 1;       
    end
    // for(i=0; i<32; i=i+1)begin
    //     addr=i;
    //     $display("Addr: %d | Data Out: %b", addr, data_out); 
    // end
    
    $finish; 
    end 
endtask

initial begin
    $dumpfile("SRAM.vcd");
    $dumpvars(0, SRAM_tb);
    my_task();
end

endmodule

SRAM/SRAM.vcd
$date
	Tue Jan 28 22:02:48 2025
$end
$version
	Icarus Verilog
$end
$timescale
	1s
$end
$scope module SRAM_tb $end
$var wire 32 ! data_out [31:0] $end
$var reg 1 " WE $end
$var reg 8 # addr [7:0] $end
$var reg 1 $ clk $end
$var reg 32 % data_in [31:0] $end
$var integer 32 & i [31:0] $end
$scope module u_sram $end
$var wire 1 ' CS $end
$var wire 1 " WE $end
$var wire 8 ( addr [7:0] $end
$var wire 1 $ clk $end
$var wire 32 ) data_in [31:0] $end
$var wire 32 * instruction [31:0] $end
$var reg 32 + data_out [31:0] $end
$upscope $end
$scope task my_task $end
$upscope $end
$upscope $end
$enddefinitions $end
#0
$dumpvars
bx +
bx *
bx )
bx (
z'
bx &
bx %
0$
bx #
x"
bx !
$end
#1
1$
#2
0$
#3
1$
#4
0$
#5
1$
b0 #
b0 (
b0 &
#6
0$
#7
1$
#8
0$
#9
1$
#10
0$
b10000000000000000000000000000001 %
b10000000000000000000000000000001 )
0"
#11
1$
#12
0$
#13
1$
#14
0$
#15
1$
b1 #
b1 (
b1 &
1"
#16
0$
#17
1$
#18
0$
#19
1$
#20
0$
b1000000000000000000000000000010 %
b1000000000000000000000000000010 )
0"
#21
1$
#22
0$
#23
1$
#24
0$
#25
1$
b10 #
b10 (
b10 &
1"
#26
0$
#27
1$
#28
0$
#29
1$
#30
0$
b100000000000000000000000000100 %
b100000000000000000000000000100 )
0"
#31
1$
#32
0$
#33
1$
#34
0$
#35
1$
b11 #
b11 (
b11 &
1"
#36
0$
#37
1$
#38
0$
#39
1$
#40
0$
b10000000000000000000000001000 %
b10000000000000000000000001000 )
0"
#41
1$
#42
0$
#43
1$
#44
0$
#45
1$
b100 #
b100 (
b100 &
1"
#46
0$
#47
1$
#48
0$
#49
1$
#50
0$
b1000000000000000000000010000 %
b1000000000000000000000010000 )
0"
#51
1$
#52
0$
#53
1$
#54
0$
#55
1$
b101 #
b101 (
b101 &
1"
#56
0$
#57
1$
#58
0$
#59
1$
#60
0$
b100000000000000000000100000 %
b100000000000000000000100000 )
0"
#61
1$
#62
0$
#63
1$
#64
0$
#65
1$
b110 #
b110 (
b110 &
1"
#66
0$
#67
1$
#68
0$
#69
1$
#70
0$
b10000000000000000001000000 %
b10000000000000000001000000 )
0"
#71
1$
#72
0$
#73
1$
#74
0$
#75
1$
b111 #
b111 (
b111 &
1"
#76
0$
#77
1$
#78
0$
#79
1$
#80
0$
b1000000000000000010000000 %
b1000000000000000010000000 )
0"
#81
1$
#82
0$
#83
1$
#84
0$
#85
1$
b1000 #
b1000 (
b1000 &
1"
#86
0$
#87
1$
#88
0$
#89
1$
#90
0$
b100000000000000100000000 %
b100000000000000100000000 )
0"
#91
1$
#92
0$
#93
1$
#94
0$
#95
1$
b1001 #
b1001 (
b1001 &
1"
#96
0$
#97
1$
#98
0$
#99
1$
#100
0$
b10000000000001000000000 %
b10000000000001000000000 )
0"
#101
1$
#102
0$
#103
1$
#104
0$
#105
1$
b1010 #
b1010 (
b1010 &
1"
#106
0$
#107
1$
#108
0$
#109
1$
#110
0$
b1000000000010000000000 %
b1000000000010000000000 )
0"
#111
1$
#112
0$
#113
1$
#114
0$
#115
1$
b1011 #
b1011 (
b1011 &
1"
#116
0$
#117
1$
#118
0$
#119
1$
#120
0$
b100000000100000000000 %
b100000000100000000000 )
0"
#121
1$
#122
0$
#123
1$
#124
0$
#125
1$
b1100 #
b1100 (
b1100 &
1"
#126
0$
#127
1$
#128
0$
#129
1$
#130
0$
b10000001000000000000 %
b10000001000000000000 )
0"
#131
1$
#132
0$
#133
1$
#134
0$
#135
1$
b1101 #
b1101 (
b1101 &
1"
#136
0$
#137
1$
#138
0$
#139
1$
#140
0$
b1000010000000000000 %
b1000010000000000000 )
0"
#141
1$
#142
0$
#143
1$
#144
0$
#145
1$
b1110 #
b1110 (
b1110 &
1"
#146
0$
#147
1$
#148
0$
#149
1$
#150
0$
b100100000000000000 %
b100100000000000000 )
0"
#151
1$
#152
0$
#153
1$
#154
0$
#155
1$
b1111 #
b1111 (
b1111 &
1"
#156
0$
#157
1$
#158
0$
#159
1$
#160
0$
b11000000000000000 %
b11000000000000000 )
0"
#161
1$
#162
0$
#163
1$
#164
0$
#165
1$
b10000 #
b10000 (
b10000 &
1"
#166
0$
#167
1$
#168
0$
#169
1$
#170
0$
b11000000000000000 %
b11000000000000000 )
0"
#171
1$
#172
0$
#173
1$
#174
0$
#175
1$
b10001 #
b10001 (
b10001 &
1"
#176
0$
#177
1$
#178
0$
#179
1$
#180
0$
b100100000000000000 %
b100100000000000000 )
0"
#181
1$
#182
0$
#183
1$
#184
0$
#185
1$
b10010 #
b10010 (
b10010 &
1"
#186
0$
#187
1$
#188
0$
#189
1$
#190
0$
b1000010000000000000 %
b1000010000000000000 )
0"
#191
1$
#192
0$
#193
1$
#194
0$
#195
1$
b10011 #
b10011 (
b10011 &
1"
#196
0$
#197
1$
#198
0$
#199
1$
#200
0$
b10000001000000000000 %
b10000001000000000000 )
0"
#201
1$
#202
0$
#203
1$
#204
0$
#205
1$
b10100 #
b10100 (
b10100 &
1"
#206
0$
#207
1$
#208
0$
#209
1$
#210
0$
b100000000100000000000 %
b100000000100000000000 )
0"
#211
1$
#212
0$
#213
1$
#214
0$
#215
1$
b10101 #
b10101 (
b10101 &
1"
#216
0$
#217
1$
#218
0$
#219
1$
#220
0$
b1000000000010000000000 %
b1000000000010000000000 )
0"
#221
1$
#222
0$
#223
1$
#224
0$
#225
1$
b10110 #
b10110 (
b10110 &
1"
#226
0$
#227
1$
#228
0$
#229
1$
#230
0$
b10000000000001000000000 %
b10000000000001000000000 )
0"
#231
1$
#232
0$
#233
1$
#234
0$
#235
1$
b10111 #
b10111 (
b10111 &
1"
#236
0$
#237
1$
#238
0$
#239
1$
#240
0$
b100000000000000100000000 %
b100000000000000100000000 )
0"
#241
1$
#242
0$
#243
1$
#244
0$
#245
1$
b11000 #
b11000 (
b11000 &
1"
#246
0$
#247
1$
#248
0$
#249
1$
#250
0$
b1000000000000000010000000 %
b1000000000000000010000000 )
0"
#251
1$
#252
0$
#253
1$
#254
0$
#255
1$
b11001 #
b11001 (
b11001 &
1"
#256
0$
#257
1$
#258
0$
#259
1$
#260
0$
b10000000000000000001000000 %
b10000000000000000001000000 )
0"
#261
1$
#262
0$
#263
1$
#264
0$
#265
1$
b11010 #
b11010 (
b11010 &
1"
#266
0$
#267
1$
#268
0$
#269
1$
#270
0$
b100000000000000000000100000 %
b100000000000000000000100000 )
0"
#271
1$
#272
0$
#273
1$
#274
0$
#275
1$
b11011 #
b11011 (
b11011 &
1"
#276
0$
#277
1$
#278
0$
#279
1$
#280
0$
b1000000000000000000000010000 %
b1000000000000000000000010000 )
0"
#281
1$
#282
0$
#283
1$
#284
0$
#285
1$
b11100 #
b11100 (
b11100 &
1"
#286
0$
#287
1$
#288
0$
#289
1$
#290
0$
b10000000000000000000000001000 %
b10000000000000000000000001000 )
0"
#291
1$
#292
0$
#293
1$
#294
0$
#295
1$
b11101 #
b11101 (
b11101 &
1"
#296
0$
#297
1$
#298
0$
#299
1$
#300
0$
b100000000000000000000000000100 %
b100000000000000000000000000100 )
0"
#301
1$
#302
0$
#303
1$
#304
0$
#305
1$
b11110 #
b11110 (
b11110 &
1"
#306
0$
#307
1$
#308
0$
#309
1$
#310
0$
b1000000000000000000000000000010 %
b1000000000000000000000000000010 )
0"
#311
1$
#312
0$
#313
1$
#314
0$
#315
1$
b11111 #
b11111 (
b11111 &
1"
#316
0$
#317
1$
#318
0$
#319
1$
#320
0$
b10000000000000000000000000000001 %
b10000000000000000000000000000001 )
0"
#321
1$
#322
0$
#323
1$
#324
0$
#325
1$
b100000 #
b100000 (
b100000 &
1"
#326
0$
#327
1$
#328
0$
#329
1$
#330
0$
b10000000000000000000000000000001 %
b10000000000000000000000000000001 )
0"
#331
1$
#332
0$
#333
1$
#334
0$
#335
1$
b100001 #
b100001 (
b100001 &
1"
#336
0$
#337
1$
#338
0$
#339
1$
#340
0$
b1000000000000000000000000000010 %
b1000000000000000000000000000010 )
0"
#341
1$
#342
0$
#343
1$
#344
0$
#345
1$
b100010 #
b100010 (
b100010 &
1"
#346
0$
#347
1$
#348
0$
#349
1$
#350
0$
b100000000000000000000000000100 %
b100000000000000000000000000100 )
0"
#351
1$
#352
0$
#353
1$
#354
0$
#355
1$
b100011 #
b100011 (
b100011 &
1"
#356
0$
#357
1$
#358
0$
#359
1$
#360
0$
b10000000000000000000000001000 %
b10000000000000000000000001000 )
0"
#361
1$
#362
0$
#363
1$
#364
0$
#365
1$
b100100 #
b100100 (
b100100 &
1"
#366
0$
#367
1$
#368
0$
#369
1$
#370
0$
b1000000000000000000000010000 %
b1000000000000000000000010000 )
0"
#371
1$
#372
0$
#373
1$
#374
0$
#375
1$
b100101 #
b100101 (
b100101 &
1"
#376
0$
#377
1$
#378
0$
#379
1$
#380
0$
b100000000000000000000100000 %
b100000000000000000000100000 )
0"
#381
1$
#382
0$
#383
1$
#384
0$
#385
1$
b100110 #
b100110 (
b100110 &
1"
#386
0$
#387
1$
#388
0$
#389
1$
#390
0$
b10000000000000000001000000 %
b10000000000000000001000000 )
0"
#391
1$
#392
0$
#393
1$
#394
0$
#395
1$
b100111 #
b100111 (
b100111 &
1"
#396
0$
#397
1$
#398
0$
#399
1$
#400
0$
b1000000000000000010000000 %
b1000000000000000010000000 )
0"
#401
1$
#402
0$
#403
1$
#404
0$
#405
1$
b101000 #
b101000 (
b101000 &
1"
#406
0$
#407
1$
#408
0$
#409
1$
#410
0$
b100000000000000100000000 %
b100000000000000100000000 )
0"
#411
1$
#412
0$
#413
1$
#414
0$
#415
1$
b101001 #
b101001 (
b101001 &
1"
#416
0$
#417
1$
#418
0$
#419
1$
#420
0$
b10000000000001000000000 %
b10000000000001000000000 )
0"
#421
1$
#422
0$
#423
1$
#424
0$
#425
1$
b101010 #
b101010 (
b101010 &
1"
#426
0$
#427
1$
#428
0$
#429
1$
#430
0$
b1000000000010000000000 %
b1000000000010000000000 )
0"
#431
1$
#432
0$
#433
1$
#434
0$
#435
1$
b101011 #
b101011 (
b101011 &
1"
#436
0$
#437
1$
#438
0$
#439
1$
#440
0$
b100000000100000000000 %
b100000000100000000000 )
0"
#441
1$
#442
0$
#443
1$
#444
0$
#445
1$
b101100 #
b101100 (
b101100 &
1"
#446
0$
#447
1$
#448
0$
#449
1$
#450
0$
b10000001000000000000 %
b10000001000000000000 )
0"
#451
1$
#452
0$
#453
1$
#454
0$
#455
1$
b101101 #
b101101 (
b101101 &
1"
#456
0$
#457
1$
#458
0$
#459
1$
#460
0$
b1000010000000000000 %
b1000010000000000000 )
0"
#461
1$
#462
0$
#463
1$
#464
0$
#465
1$
b101110 #
b101110 (
b101110 &
1"
#466
0$
#467
1$
#468
0$
#469
1$
#470
0$
b100100000000000000 %
b100100000000000000 )
0"
#471
1$
#472
0$
#473
1$
#474
0$
#475
1$
b101111 #
b101111 (
b101111 &
1"
#476
0$
#477
1$
#478
0$
#479
1$
#480
0$
b11000000000000000 %
b11000000000000000 )
0"
#481
1$
#482
0$
#483
1$
#484
0$
#485
1$
b110000 #
b110000 (
b110000 &
1"
#486
0$
#487
1$
#488
0$
#489
1$
#490
0$
b11000000000000000 %
b11000000000000000 )
0"
#491
1$
#492
0$
#493
1$
#494
0$
#495
1$
b110001 #
b110001 (
b110001 &
1"
#496
0$
#497
1$
#498
0$
#499
1$
#500
0$
b100100000000000000 %
b100100000000000000 )
0"
#501
1$
#502
0$
#503
1$
#504
0$
#505
1$
b110010 #
b110010 (
b110010 &
1"
#506
0$
#507
1$
#508
0$
#509
1$
#510
0$
b1000010000000000000 %
b1000010000000000000 )
0"
#511
1$
#512
0$
#513
1$
#514
0$
#515
1$
b110011 #
b110011 (
b110011 &
1"
#516
0$
#517
1$
#518
0$
#519
1$
#520
0$
b10000001000000000000 %
b10000001000000000000 )
0"
#521
1$
#522
0$
#523
1$
#524
0$
#525
1$
b110100 #
b110100 (
b110100 &
1"
#526
0$
#527
1$
#528
0$
#529
1$
#530
0$
b100000000100000000000 %
b100000000100000000000 )
0"
#531
1$
#532
0$
#533
1$
#534
0$
#535
1$
b110101 #
b110101 (
b110101 &
1"
#536
0$
#537
1$
#538
0$
#539
1$
#540
0$
b1000000000010000000000 %
b1000000000010000000000 )
0"
#541
1$
#542
0$
#543
1$
#544
0$
#545
1$
b110110 #
b110110 (
b110110 &
1"
#546
0$
#547
1$
#548
0$
#549
1$
#550
0$
b10000000000001000000000 %
b10000000000001000000000 )
0"
#551
1$
#552
0$
#553
1$
#554
0$
#555
1$
b110111 #
b110111 (
b110111 &
1"
#556
0$
#557
1$
#558
0$
#559
1$
#560
0$
b100000000000000100000000 %
b100000000000000100000000 )
0"
#561
1$
#562
0$
#563
1$
#564
0$
#565
1$
b111000 #
b111000 (
b111000 &
1"
#566
0$
#567
1$
#568
0$
#569
1$
#570
0$
b1000000000000000010000000 %
b1000000000000000010000000 )
0"
#571
1$
#572
0$
#573
1$
#574
0$
#575
1$
b111001 #
b111001 (
b111001 &
1"
#576
0$
#577
1$
#578
0$
#579
1$
#580
0$
b10000000000000000001000000 %
b10000000000000000001000000 )
0"
#581
1$
#582
0$
#583
1$
#584
0$
#585
1$
b111010 #
b111010 (
b111010 &
1"
#586
0$
#587
1$
#588
0$
#589
1$
#590
0$
b100000000000000000000100000 %
b100000000000000000000100000 )
0"
#591
1$
#592
0$
#593
1$
#594
0$
#595
1$
b111011 #
b111011 (
b111011 &
1"
#596
0$
#597
1$
#598
0$
#599
1$
#600
0$
b1000000000000000000000010000 %
b1000000000000000000000010000 )
0"
#601
1$
#602
0$
#603
1$
#604
0$
#605
1$
b111100 #
b111100 (
b111100 &
1"
#606
0$
#607
1$
#608
0$
#609
1$
#610
0$
b10000000000000000000000001000 %
b10000000000000000000000001000 )
0"
#611
1$
#612
0$
#613
1$
#614
0$
#615
1$
b111101 #
b111101 (
b111101 &
1"
#616
0$
#617
1$
#618
0$
#619
1$
#620
0$
b100000000000000000000000000100 %
b100000000000000000000000000100 )
0"
#621
1$
#622
0$
#623
1$
#624
0$
#625
1$
b111110 #
b111110 (
b111110 &
1"
#626
0$
#627
1$
#628
0$
#629
1$
#630
0$
b1000000000000000000000000000010 %
b1000000000000000000000000000010 )
0"
#631
1$
#632
0$
#633
1$
#634
0$
#635
1$
b111111 #
b111111 (
b111111 &
1"
#636
0$
#637
1$
#638
0$
#639
1$
#640
0$
b10000000000000000000000000000001 %
b10000000000000000000000000000001 )
0"
#641
1$
#642
0$
#643
1$
#644
0$
#645
1$
b1000000 #
b1000000 (
b1000000 &
1"
#646
0$
#647
1$
#648
0$
#649
1$
#650
0$
b10000000000000000000000000000001 %
b10000000000000000000000000000001 )
0"
#651
1$
#652
0$
#653
1$
#654
0$
#655
1$
b1000001 #
b1000001 (
b1000001 &
1"
#656
0$
#657
1$
#658
0$
#659
1$
#660
0$
b1000000000000000000000000000010 %
b1000000000000000000000000000010 )
0"
#661
1$
#662
0$
#663
1$
#664
0$
#665
1$
b1000010 #
b1000010 (
b1000010 &
1"
#666
0$
#667
1$
#668
0$
#669
1$
#670
0$
b100000000000000000000000000100 %
b100000000000000000000000000100 )
0"
#671
1$
#672
0$
#673
1$
#674
0$
#675
1$
b1000011 #
b1000011 (
b1000011 &
1"
#676
0$
#677
1$
#678
0$
#679
1$
#680
0$
b10000000000000000000000001000 %
b10000000000000000000000001000 )
0"
#681
1$
#682
0$
#683
1$
#684
0$
#685
1$
b1000100 #
b1000100 (
b1000100 &
1"
#686
0$
#687
1$
#688
0$
#689
1$
#690
0$
b1000000000000000000000010000 %
b1000000000000000000000010000 )
0"
#691
1$
#692
0$
#693
1$
#694
0$
#695
1$
b1000101 #
b1000101 (
b1000101 &
1"
#696
0$
#697
1$
#698
0$
#699
1$
#700
0$
b100000000000000000000100000 %
b100000000000000000000100000 )
0"
#701
1$
#702
0$
#703
1$
#704
0$
#705
1$
b1000110 #
b1000110 (
b1000110 &
1"
#706
0$
#707
1$
#708
0$
#709
1$
#710
0$
b10000000000000000001000000 %
b10000000000000000001000000 )
0"
#711
1$
#712
0$
#713
1$
#714
0$
#715
1$
b1000111 #
b1000111 (
b1000111 &
1"
#716
0$
#717
1$
#718
0$
#719
1$
#720
0$
b1000000000000000010000000 %
b1000000000000000010000000 )
0"
#721
1$
#722
0$
#723
1$
#724
0$
#725
1$
b1001000 #
b1001000 (
b1001000 &
1"
#726
0$
#727
1$
#728
0$
#729
1$
#730
0$
b100000000000000100000000 %
b100000000000000100000000 )
0"
#731
1$
#732
0$
#733
1$
#734
0$
#735
1$
b1001001 #
b1001001 (
b1001001 &
1"
#736
0$
#737
1$
#738
0$
#739
1$
#740
0$
b10000000000001000000000 %
b10000000000001000000000 )
0"
#741
1$
#742
0$
#743
1$
#744
0$
#745
1$
b1001010 #
b1001010 (
b1001010 &
1"
#746
0$
#747
1$
#748
0$
#749
1$
#750
0$
b1000000000010000000000 %
b1000000000010000000000 )
0"
#751
1$
#752
0$
#753
1$
#754
0$
#755
1$
b1001011 #
b1001011 (
b1001011 &
1"
#756
0$
#757
1$
#758
0$
#759
1$
#760
0$
b100000000100000000000 %
b100000000100000000000 )
0"
#761
1$
#762
0$
#763
1$
#764
0$
#765
1$
b1001100 #
b1001100 (
b1001100 &
1"
#766
0$
#767
1$
#768
0$
#769
1$
#770
0$
b10000001000000000000 %
b10000001000000000000 )
0"
#771
1$
#772
0$
#773
1$
#774
0$
#775
1$
b1001101 #
b1001101 (
b1001101 &
1"
#776
0$
#777
1$
#778
0$
#779
1$
#780
0$
b1000010000000000000 %
b1000010000000000000 )
0"
#781
1$
#782
0$
#783
1$
#784
0$
#785
1$
b1001110 #
b1001110 (
b1001110 &
1"
#786
0$
#787
1$
#788
0$
#789
1$
#790
0$
b100100000000000000 %
b100100000000000000 )
0"
#791
1$
#792
0$
#793
1$
#794
0$
#795
1$
b1001111 #
b1001111 (
b1001111 &
1"
#796
0$
#797
1$
#798
0$
#799
1$
#800
0$
b11000000000000000 %
b11000000000000000 )
0"
#801
1$
#802
0$
#803
1$
#804
0$
#805
1$
b1010000 #
b1010000 (
b1010000 &
1"
#806
0$
#807
1$
#808
0$
#809
1$
#810
0$
b11000000000000000 %
b11000000000000000 )
0"
#811
1$
#812
0$
#813
1$
#814
0$
#815
1$
b1010001 #
b1010001 (
b1010001 &
1"
#816
0$
#817
1$
#818
0$
#819
1$
#820
0$
b100100000000000000 %
b100100000000000000 )
0"
#821
1$
#822
0$
#823
1$
#824
0$
#825
1$
b1010010 #
b1010010 (
b1010010 &
1"
#826
0$
#827
1$
#828
0$
#829
1$
#830
0$
b1000010000000000000 %
b1000010000000000000 )
0"
#831
1$
#832
0$
#833
1$
#834
0$
#835
1$
b1010011 #
b1010011 (
b1010011 &
1"
#836
0$
#837
1$
#838
0$
#839
1$
#840
0$
b10000001000000000000 %
b10000001000000000000 )
0"
#841
1$
#842
0$
#843
1$
#844
0$
#845
1$
b1010100 #
b1010100 (
b1010100 &
1"
#846
0$
#847
1$
#848
0$
#849
1$
#850
0$
b100000000100000000000 %
b100000000100000000000 )
0"
#851
1$
#852
0$
#853
1$
#854
0$
#855
1$
b1010101 #
b1010101 (
b1010101 &
1"
#856
0$
#857
1$
#858
0$
#859
1$
#860
0$
b1000000000010000000000 %
b1000000000010000000000 )
0"
#861
1$
#862
0$
#863
1$
#864
0$
#865
1$
b1010110 #
b1010110 (
b1010110 &
1"
#866
0$
#867
1$
#868
0$
#869
1$
#870
0$
b10000000000001000000000 %
b10000000000001000000000 )
0"
#871
1$
#872
0$
#873
1$
#874
0$
#875
1$
b1010111 #
b1010111 (
b1010111 &
1"
#876
0$
#877
1$
#878
0$
#879
1$
#880
0$
b100000000000000100000000 %
b100000000000000100000000 )
0"
#881
1$
#882
0$
#883
1$
#884
0$
#885
1$
b1011000 #
b1011000 (
b1011000 &
1"
#886
0$
#887
1$
#888
0$
#889
1$
#890
0$
b1000000000000000010000000 %
b1000000000000000010000000 )
0"
#891
1$
#892
0$
#893
1$
#894
0$
#895
1$
b1011001 #
b1011001 (
b1011001 &
1"
#896
0$
#897
1$
#898
0$
#899
1$
#900
0$
b10000000000000000001000000 %
b10000000000000000001000000 )
0"
#901
1$
#902
0$
#903
1$
#904
0$
#905
1$
b1011010 #
b1011010 (
b1011010 &
1"
#906
0$
#907
1$
#908
0$
#909
1$
#910
0$
b100000000000000000000100000 %
b100000000000000000000100000 )
0"
#911
1$
#912
0$
#913
1$
#914
0$
#915
1$
b1011011 #
b1011011 (
b1011011 &
1"
#916
0$
#917
1$
#918
0$
#919
1$
#920
0$
b1000000000000000000000010000 %
b1000000000000000000000010000 )
0"
#921
1$
#922
0$
#923
1$
#924
0$
#925
1$
b1011100 #
b1011100 (
b1011100 &
1"
#926
0$
#927
1$
#928
0$
#929
1$
#930
0$
b10000000000000000000000001000 %
b10000000000000000000000001000 )
0"
#931
1$
#932
0$
#933
1$
#934
0$
#935
1$
b1011101 #
b1011101 (
b1011101 &
1"
#936
0$
#937
1$
#938
0$
#939
1$
#940
0$
b100000000000000000000000000100 %
b100000000000000000000000000100 )
0"
#941
1$
#942
0$
#943
1$
#944
0$
#945
1$
b1011110 #
b1011110 (
b1011110 &
1"
#946
0$
#947
1$
#948
0$
#949
1$
#950
0$
b1000000000000000000000000000010 %
b1000000000000000000000000000010 )
0"
#951
1$
#952
0$
#953
1$
#954
0$
#955
1$
b1011111 #
b1011111 (
b1011111 &
1"
#956
0$
#957
1$
#958
0$
#959
1$
#960
0$
b10000000000000000000000000000001 %
b10000000000000000000000000000001 )
0"
#961
1$
#962
0$
#963
1$
#964
0$
#965
1$
b1100000 #
b1100000 (
b1100000 &
1"
#966
0$
#967
1$
#968
0$
#969
1$
#970
0$
b10000000000000000000000000000001 %
b10000000000000000000000000000001 )
0"
#971
1$
#972
0$
#973
1$
#974
0$
#975
1$
b1100001 #
b1100001 (
b1100001 &
1"
#976
0$
#977
1$
#978
0$
#979
1$
#980
0$
b1000000000000000000000000000010 %
b1000000000000000000000000000010 )
0"
#981
1$
#982
0$
#983
1$
#984
0$
#985
1$
b1100010 #
b1100010 (
b1100010 &
1"
#986
0$
#987
1$
#988
0$
#989
1$
#990
0$
b100000000000000000000000000100 %
b100000000000000000000000000100 )
0"
#991
1$
#992
0$
#993
1$
#994
0$
#995
1$
b1100011 #
b1100011 (
b1100011 &
1"
#996
0$
#997
1$
#998
0$
#999
1$
#1000
0$
b10000000000000000000000001000 %
b10000000000000000000000001000 )
0"
#1001
1$
#1002
0$
#1003
1$
#1004
0$
#1005
1$
b1100100 #
b1100100 (
b1100100 &
1"
#1006
0$
#1007
1$
#1008
0$
#1009
1$
#1010
0$
b1000000000000000000000010000 %
b1000000000000000000000010000 )
0"
#1011
1$
#1012
0$
#1013
1$
#1014
0$
#1015
1$
b1100101 #
b1100101 (
b1100101 &
1"
#1016
0$
#1017
1$
#1018
0$
#1019
1$
#1020
0$
b100000000000000000000100000 %
b100000000000000000000100000 )
0"
#1021
1$
#1022
0$
#1023
1$
#1024
0$
#1025
1$
b1100110 #
b1100110 (
b1100110 &
1"
#1026
0$
#1027
1$
#1028
0$
#1029
1$
#1030
0$
b10000000000000000001000000 %
b10000000000000000001000000 )
0"
#1031
1$
#1032
0$
#1033
1$
#1034
0$
#1035
1$
b1100111 #
b1100111 (
b1100111 &
1"
#1036
0$
#1037
1$
#1038
0$
#1039
1$
#1040
0$
b1000000000000000010000000 %
b1000000000000000010000000 )
0"
#1041
1$
#1042
0$
#1043
1$
#1044
0$
#1045
1$
b1101000 #
b1101000 (
b1101000 &
1"
#1046
0$
#1047
1$
#1048
0$
#1049
1$
#1050
0$
b100000000000000100000000 %
b100000000000000100000000 )
0"
#1051
1$
#1052
0$
#1053
1$
#1054
0$
#1055
1$
b1101001 #
b1101001 (
b1101001 &
1"
#1056
0$
#1057
1$
#1058
0$
#1059
1$
#1060
0$
b10000000000001000000000 %
b10000000000001000000000 )
0"
#1061
1$
#1062
0$
#1063
1$
#1064
0$
#1065
1$
b1101010 #
b1101010 (
b1101010 &
1"
#1066
0$
#1067
1$
#1068
0$
#1069
1$
#1070
0$
b1000000000010000000000 %
b1000000000010000000000 )
0"
#1071
1$
#1072
0$
#1073
1$
#1074
0$
#1075
1$
b1101011 #
b1101011 (
b1101011 &
1"
#1076
0$
#1077
1$
#1078
0$
#1079
1$
#1080
0$
b100000000100000000000 %
b100000000100000000000 )
0"
#1081
1$
#1082
0$
#1083
1$
#1084
0$
#1085
1$
b1101100 #
b1101100 (
b1101100 &
1"
#1086
0$
#1087
1$
#1088
0$
#1089
1$
#1090
0$
b10000001000000000000 %
b10000001000000000000 )
0"
#1091
1$
#1092
0$
#1093
1$
#1094
0$
#1095
1$
b1101101 #
b1101101 (
b1101101 &
1"
#1096
0$
#1097
1$
#1098
0$
#1099
1$
#1100
0$
b1000010000000000000 %
b1000010000000000000 )
0"
#1101
1$
#1102
0$
#1103
1$
#1104
0$
#1105
1$
b1101110 #
b1101110 (
b1101110 &
1"
#1106
0$
#1107
1$
#1108
0$
#1109
1$
#1110
0$
b100100000000000000 %
b100100000000000000 )
0"
#1111
1$
#1112
0$
#1113
1$
#1114
0$
#1115
1$
b1101111 #
b1101111 (
b1101111 &
1"
#1116
0$
#1117
1$
#1118
0$
#1119
1$
#1120
0$
b11000000000000000 %
b11000000000000000 )
0"
#1121
1$
#1122
0$
#1123
1$
#1124
0$
#1125
1$
b1110000 #
b1110000 (
b1110000 &
1"
#1126
0$
#1127
1$
#1128
0$
#1129
1$
#1130
0$
b11000000000000000 %
b11000000000000000 )
0"
#1131
1$
#1132
0$
#1133
1$
#1134
0$
#1135
1$
b1110001 #
b1110001 (
b1110001 &
1"
#1136
0$
#1137
1$
#1138
0$
#1139
1$
#1140
0$
b100100000000000000 %
b100100000000000000 )
0"
#1141
1$
#1142
0$
#1143
1$
#1144
0$
#1145
1$
b1110010 #
b1110010 (
b1110010 &
1"
#1146
0$
#1147
1$
#1148
0$
#1149
1$
#1150
0$
b1000010000000000000 %
b1000010000000000000 )
0"
#1151
1$
#1152
0$
#1153
1$
#1154
0$
#1155
1$
b1110011 #
b1110011 (
b1110011 &
1"
#1156
0$
#1157
1$
#1158
0$
#1159
1$
#1160
0$
b10000001000000000000 %
b10000001000000000000 )
0"
#1161
1$
#1162
0$
#1163
1$
#1164
0$
#1165
1$
b1110100 #
b1110100 (
b1110100 &
1"
#1166
0$
#1167
1$
#1168
0$
#1169
1$
#1170
0$
b100000000100000000000 %
b100000000100000000000 )
0"
#1171
1$
#1172
0$
#1173
1$
#1174
0$
#1175
1$
b1110101 #
b1110101 (
b1110101 &
1"
#1176
0$
#1177
1$
#1178
0$
#1179
1$
#1180
0$
b1000000000010000000000 %
b1000000000010000000000 )
0"
#1181
1$
#1182
0$
#1183
1$
#1184
0$
#1185
1$
b1110110 #
b1110110 (
b1110110 &
1"
#1186
0$
#1187
1$
#1188
0$
#1189
1$
#1190
0$
b10000000000001000000000 %
b10000000000001000000000 )
0"
#1191
1$
#1192
0$
#1193
1$
#1194
0$
#1195
1$
b1110111 #
b1110111 (
b1110111 &
1"
#1196
0$
#1197
1$
#1198
0$
#1199
1$
#1200
0$
b100000000000000100000000 %
b100000000000000100000000 )
0"
#1201
1$
#1202
0$
#1203
1$
#1204
0$
#1205
1$
b1111000 #
b1111000 (
b1111000 &
1"
#1206
0$
#1207
1$
#1208
0$
#1209
1$
#1210
0$
b1000000000000000010000000 %
b1000000000000000010000000 )
0"
#1211
1$
#1212
0$
#1213
1$
#1214
0$
#1215
1$
b1111001 #
b1111001 (
b1111001 &
1"
#1216
0$
#1217
1$
#1218
0$
#1219
1$
#1220
0$
b10000000000000000001000000 %
b10000000000000000001000000 )
0"
#1221
1$
#1222
0$
#1223
1$
#1224
0$
#1225
1$
b1111010 #
b1111010 (
b1111010 &
1"
#1226
0$
#1227
1$
#1228
0$
#1229
1$
#1230
0$
b100000000000000000000100000 %
b100000000000000000000100000 )
0"
#1231
1$
#1232
0$
#1233
1$
