CNTR_MUX_SR/CNTR_MUX_SR.v
//counter description

module cntr(
    input clk,
    input res,
    input en,
    output reg [2:0]ctr
);

always@(posedge clk or posedge res) begin
    if(res) begin
        ctr<=0;
    end
    else begin
        if(en) begin
            ctr<=ctr+1;
        end
    end
end

endmodule

//multiplexor 8-1 description

module mux8_1(
    input [7:0]in,
    input [2:0]sel,
    output out
);

assign out=in[sel];

endmodule

//dff description for shift register

module dff(
    input clk,
    input res,
    input d,
    output reg q
);

always@(posedge clk or posedge res) begin
    if(res) begin
        q<=0;
    end
    else begin
        q<=d;
    end
end

endmodule

//shift register description

module SR(
    input clk,
    input res,
    input en,
    input d,
    output q_out
);

wire [7:0] q;  
genvar i;

generate
    for(i=0; i<8; i=i+1) begin: SR
        if(i == 0) begin
            dff u_dff(
                .clk(clk),
                .res(res),
                .d(en ? d : q[0]), 
                .q(q[i])
            );
        end
        else if(i < 7) begin
            dff u_dff(
                .clk(clk),
                .res(res),
                .d(en ? q[i-1] : q[i]),  
                .q(q[i])
            );
        end
        else begin
            dff u_dff(
                .clk(clk),
                .res(res),
                .d(en ? q[i-1] : q[i]),  
                .q(q_out)
            );
        end
    end
endgenerate

endmodule

//description of the whole scheme

module Scheme(
    input clk,
    input res,
    input en,
    input [7:0]in,
    output out
);

wire d;
wire [2:0]ctr;

cntr u_cntr(
    .clk(clk),
    .res(res),
    .en(en),
    .ctr(ctr)
);

mux8_1 u_mux(
    .in(in),
    .sel(ctr),
    .out(d)
);

SR u_sr(
    .clk(clk),
    .res(res),
    .en(en),
    .d(d),
    .q_out(out)
);

endmodule

CNTR_MUX_SR/CNTR_MUX_SR_tb.v
`include "CNTR_MUX_SR.v"

module tb();

reg clk;
reg res;
reg en;
reg [7:0]in;
wire out;

always #5 clk=~clk;

Scheme u_scheme(
    .clk(clk),
    .res(res),
    .en(en),
    .in(in),
    .out(out)
);

integer i;

initial begin
    $dumpfile("CNTR_MUX_SR.vcd");
    $dumpvars(0, u_scheme);
    res=1;
    clk=0;
    en=0;
    #15;
    res=0;
    en=1;
    for(i=0; i<256; i=i+1)begin
        in=i;
        #10;
    end
    $finish;
end

initial begin
    $monitor("Input = %b | Out = %b", in, out);
end

endmodule

CNTR_MUX_SR/CNTR_MUX_SR.vcd
$date
	Sun Dec 22 22:01:06 2024
$end
$version
	Icarus Verilog
$end
$timescale
	1s
$end
$scope module tb $end
$scope module u_scheme $end
$var wire 1 ! clk $end
$var wire 1 " en $end
$var wire 8 # in [7:0] $end
$var wire 1 $ res $end
$var wire 1 % out $end
$var wire 1 & d $end
$var wire 3 ' ctr [2:0] $end
$scope module u_cntr $end
$var wire 1 ! clk $end
$var wire 1 " en $end
$var wire 1 $ res $end
$var reg 3 ( ctr [2:0] $end
$upscope $end
$scope module u_mux $end
$var wire 8 ) in [7:0] $end
$var wire 3 * sel [2:0] $end
$var wire 1 & out $end
$upscope $end
$scope module u_sr $end
$var wire 1 ! clk $end
$var wire 1 & d $end
$var wire 1 " en $end
$var wire 1 $ res $end
$var wire 1 % q_out $end
$var wire 8 + q [7:0] $end
$scope begin SR[0] $end
$scope begin genblk2 $end
$scope module u_dff $end
$var wire 1 ! clk $end
$var wire 1 , d $end
$var wire 1 $ res $end
$var reg 1 - q $end
$upscope $end
$upscope $end
$upscope $end
$scope begin SR[1] $end
$scope begin genblk4 $end
$scope module u_dff $end
$var wire 1 ! clk $end
$var wire 1 . d $end
$var wire 1 $ res $end
$var reg 1 / q $end
$upscope $end
$upscope $end
$upscope $end
$scope begin SR[2] $end
$scope begin genblk4 $end
$scope module u_dff $end
$var wire 1 ! clk $end
$var wire 1 0 d $end
$var wire 1 $ res $end
$var reg 1 1 q $end
$upscope $end
$upscope $end
$upscope $end
$scope begin SR[3] $end
$scope begin genblk4 $end
$scope module u_dff $end
$var wire 1 ! clk $end
$var wire 1 2 d $end
$var wire 1 $ res $end
$var reg 1 3 q $end
$upscope $end
$upscope $end
$upscope $end
$scope begin SR[4] $end
$scope begin genblk4 $end
$scope module u_dff $end
$var wire 1 ! clk $end
$var wire 1 4 d $end
$var wire 1 $ res $end
$var reg 1 5 q $end
$upscope $end
$upscope $end
$upscope $end
$scope begin SR[5] $end
$scope begin genblk4 $end
$scope module u_dff $end
$var wire 1 ! clk $end
$var wire 1 6 d $end
$var wire 1 $ res $end
$var reg 1 7 q $end
$upscope $end
$upscope $end
$upscope $end
$scope begin SR[6] $end
$scope begin genblk4 $end
$scope module u_dff $end
$var wire 1 ! clk $end
$var wire 1 8 d $end
$var wire 1 $ res $end
$var reg 1 9 q $end
$upscope $end
$upscope $end
$upscope $end
$scope begin SR[7] $end
$scope begin genblk5 $end
$scope module u_dff $end
$var wire 1 ! clk $end
$var wire 1 : d $end
$var wire 1 $ res $end
$var reg 1 % q $end
$upscope $end
$upscope $end
$upscope $end
$upscope $end
$upscope $end
$upscope $end
$enddefinitions $end
#0
$dumpvars
z:
09
08
07
06
05
04
03
02
01
00
0/
0.
0-
0,
bz0000000 +
b0 *
bx )
b0 (
b0 '
x&
0%
1$
bx #
0"
0!
$end
#5
1!
#10
0!
#15
b1 '
b1 (
b1 *
0:
1!
0&
b0 #
b0 )
1"
0$
#20
0!
#25
b10 '
b10 (
b10 *
1!
b1 #
b1 )
#30
0!
#35
b11 '
b11 (
b11 *
1!
b10 #
b10 )
#40
0!
#45
b100 '
b100 (
b100 *
1!
b11 #
b11 )
#50
0!
#55
b101 '
b101 (
b101 *
1!
b100 #
b100 )
#60
0!
#65
b110 '
b110 (
b110 *
1!
b101 #
b101 )
#70
0!
#75
b111 '
b111 (
b111 *
1!
b110 #
b110 )
#80
0!
#85
1,
1&
b0 '
b0 (
b0 *
1!
b111 #
b111 )
#90
0!
#95
b1 '
b1 (
b1 *
0,
1!
0&
b1000 #
b1000 )
#100
0!
#105
b10 '
b10 (
b10 *
1!
b1001 #
b1001 )
#110
0!
#115
1,
1&
b11 '
b11 (
b11 *
1!
b1010 #
b1010 )
#120
0!
#125
1.
0,
bz0000001 +
1-
0&
b100 '
b100 (
b100 *
1!
b1011 #
b1011 )
#130
0!
#135
0.
10
b101 '
b101 (
b101 *
0-
bz0000010 +
1/
1!
b1100 #
b1100 )
#140
0!
#145
12
00
11
bz0000100 +
0/
b110 '
b110 (
b110 *
1!
b1101 #
b1101 )
#150
0!
#155
02
14
b111 '
b111 (
b111 *
01
bz0001000 +
13
1!
b1110 #
b1110 )
#160
0!
#165
16
04
1,
15
bz0010000 +
03
1&
b0 '
b0 (
b0 *
1!
b1111 #
b1111 )
#170
0!
#175
06
18
b1 '
b1 (
b1 *
05
bz0100000 +
17
0,
1!
0&
b10000 #
b10000 )
#180
0!
#185
1:
08
19
bz1000000 +
07
b10 '
b10 (
b10 *
1!
b10001 #
b10001 )
#190
0!
#195
0:
b11 '
b11 (
b11 *
bz0000000 +
09
1%
1!
b10010 #
b10010 )
#200
0!
#205
1,
0%
1&
b100 '
b100 (
b100 *
1!
b10011 #
b10011 )
#210
0!
#215
1.
0,
0&
b101 '
b101 (
b101 *
bz0000001 +
1-
1!
b10100 #
b10100 )
#220
0!
#225
10
0.
1/
bz0000010 +
0-
b110 '
b110 (
b110 *
1!
b10101 #
b10101 )
#230
0!
#235
00
12
b111 '
b111 (
b111 *
0/
bz0000100 +
11
1!
b10110 #
b10110 )
#240
0!
#245
14
02
1,
13
bz0001000 +
01
1&
b0 '
b0 (
b0 *
1!
b10111 #
b10111 )
#250
0!
#255
04
16
b1 '
b1 (
b1 *
03
bz0010000 +
15
0,
1!
0&
b11000 #
b11000 )
#260
0!
#265
18
06
17
bz0100000 +
05
b10 '
b10 (
b10 *
1!
b11001 #
b11001 )
#270
0!
#275
08
1:
1,
1&
b11 '
b11 (
b11 *
07
bz1000000 +
19
1!
b11010 #
b11010 )
#280
0!
#285
0:
1.
1%
09
bz0000001 +
1-
b100 '
b100 (
b100 *
1!
b11011 #
b11011 )
#290
0!
#295
10
0,
0&
b101 '
b101 (
b101 *
bz0000011 +
1/
0%
1!
b11100 #
b11100 )
#300
0!
#305
12
0.
11
bz0000110 +
0-
b110 '
b110 (
b110 *
1!
b11101 #
b11101 )
#310
0!
#315
00
14
b111 '
b111 (
b111 *
0/
bz0001100 +
13
1!
b11110 #
b11110 )
#320
0!
#325
16
02
1,
15
bz0011000 +
01
1&
b0 '
b0 (
b0 *
1!
b11111 #
b11111 )
#330
0!
#335
04
18
b1 '
b1 (
b1 *
03
bz0110000 +
17
0,
1!
0&
b100000 #
b100000 )
#340
0!
#345
1:
06
19
bz1100000 +
05
b10 '
b10 (
b10 *
1!
b100001 #
b100001 )
#350
0!
#355
08
b11 '
b11 (
b11 *
bz1000000 +
07
1%
1!
b100010 #
b100010 )
#360
0!
#365
0:
bz0000000 +
09
b100 '
b100 (
b100 *
1!
b100011 #
b100011 )
#370
0!
#375
1,
1&
b101 '
b101 (
b101 *
0%
1!
b100100 #
b100100 )
#380
0!
#385
1.
0,
bz0000001 +
1-
0&
b110 '
b110 (
b110 *
1!
b100101 #
b100101 )
#390
0!
#395
0.
10
b111 '
b111 (
b111 *
0-
bz0000010 +
1/
1!
b100110 #
b100110 )
#400
0!
#405
12
00
1,
11
bz0000100 +
0/
1&
b0 '
b0 (
b0 *
1!
b100111 #
b100111 )
#410
0!
#415
02
14
b1 '
b1 (
b1 *
01
bz0001000 +
13
0,
1!
0&
b101000 #
b101000 )
#420
0!
#425
16
04
15
bz0010000 +
03
b10 '
b10 (
b10 *
1!
b101001 #
b101001 )
#430
0!
#435
06
18
1,
1&
b11 '
b11 (
b11 *
05
bz0100000 +
17
1!
b101010 #
b101010 )
#440
0!
#445
1:
08
1.
0,
19
07
bz1000001 +
1-
0&
b100 '
b100 (
b100 *
1!
b101011 #
b101011 )
#450
0!
#455
0.
10
0:
1,
1&
b101 '
b101 (
b101 *
0-
1/
bz0000010 +
09
1%
1!
b101100 #
b101100 )
#460
0!
#465
12
00
1.
0,
0%
11
0/
bz0000101 +
1-
0&
b110 '
b110 (
b110 *
1!
b101101 #
b101101 )
#470
0!
#475
0.
10
02
14
b111 '
b111 (
b111 *
0-
1/
01
bz0001010 +
13
1!
b101110 #
b101110 )
#480
0!
#485
16
04
12
00
1,
15
03
11
bz0010100 +
0/
1&
b0 '
b0 (
b0 *
1!
b101111 #
b101111 )
#490
0!
#495
02
14
06
18
b1 '
b1 (
b1 *
01
13
05
bz0101000 +
17
0,
1!
0&
b110000 #
b110000 )
#500
0!
#505
1:
08
16
04
19
07
15
bz1010000 +
03
b10 '
b10 (
b10 *
1!
b110001 #
b110001 )
#510
0!
#515
06
18
0:
b11 '
b11 (
b11 *
05
17
bz0100000 +
09
1%
1!
b110010 #
b110010 )
#520
0!
#525
1:
08
1,
0%
19
bz1000000 +
07
1&
b100 '
b100 (
b100 *
1!
b110011 #
b110011 )
#530
0!
#535
1.
0:
b101 '
b101 (
b101 *
1-
bz0000001 +
09
1%
1!
b110100 #
b110100 )
#540
0!
#545
10
0,
0%
bz0000011 +
1/
0&
b110 '
b110 (
b110 *
1!
b110101 #
b110101 )
#550
0!
#555
0.
12
b111 '
b111 (
b111 *
0-
bz0000110 +
11
1!
b110110 #
b110110 )
#560
0!
#565
14
00
1,
13
bz0001100 +
0/
1&
b0 '
b0 (
b0 *
1!
b110111 #
b110111 )
#570
0!
#575
02
16
b1 '
b1 (
b1 *
01
bz0011000 +
15
0,
1!
0&
b111000 #
b111000 )
#580
0!
#585
18
04
17
bz0110000 +
03
b10 '
b10 (
b10 *
1!
b111001 #
b111001 )
#590
0!
#595
06
1:
1,
1&
b11 '
b11 (
b11 *
05
bz1100000 +
19
1!
b111010 #
b111010 )
#600
0!
#605
08
1.
1%
07
bz1000001 +
1-
b100 '
b100 (
b100 *
1!
b111011 #
b111011 )
#610
0!
#615
10
0:
b101 '
b101 (
b101 *
1/
bz0000011 +
09
1!
b111100 #
b111100 )
#620
0!
#625
12
0,
0%
bz0000111 +
11
0&
b110 '
b110 (
b110 *
1!
b111101 #
b111101 )
#630
0!
#635
0.
14
b111 '
b111 (
b111 *
0-
bz0001110 +
13
1!
b111110 #
b111110 )
#640
0!
#645
16
00
1,
15
bz0011100 +
0/
1&
b0 '
b0 (
b0 *
1!
b111111 #
b111111 )
#650
0!
#655
02
18
b1 '
b1 (
b1 *
01
bz0111000 +
17
0,
1!
0&
b1000000 #
b1000000 )
#660
0!
#665
1:
04
19
bz1110000 +
03
b10 '
b10 (
b10 *
1!
b1000001 #
b1000001 )
#670
0!
#675
06
b11 '
b11 (
b11 *
bz1100000 +
05
1%
1!
b1000010 #
b1000010 )
#680
0!
#685
08
bz1000000 +
07
b100 '
b100 (
b100 *
1!
b1000011 #
b1000011 )
#690
0!
#695
0:
b101 '
b101 (
b101 *
bz0000000 +
09
1!
b1000100 #
b1000100 )
#700
0!
#705
1,
0%
1&
b110 '
b110 (
b110 *
1!
b1000101 #
b1000101 )
#710
0!
#715
1.
0,
0&
b111 '
b111 (
b111 *
bz0000001 +
1-
1!
b1000110 #
b1000110 )
#720
0!
#725
10
0.
1,
1/
bz0000010 +
0-
1&
b0 '
b0 (
b0 *
1!
b1000111 #
b1000111 )
#730
0!
#735
00
12
b1 '
b1 (
b1 *
0/
bz0000100 +
11
0,
1!
0&
b1001000 #
b1001000 )
#740
0!
#745
14
02
13
bz0001000 +
01
b10 '
b10 (
b10 *
1!
b1001001 #
b1001001 )
#750
0!
#755
04
16
1,
1&
b11 '
b11 (
b11 *
03
bz0010000 +
15
1!
b1001010 #
b1001010 )
#760
0!
#765
18
06
1.
0,
17
05
bz0100001 +
1-
0&
b100 '
b100 (
b100 *
1!
b1001011 #
b1001011 )
#770
0!
#775
0.
10
08
1:
b101 '
b101 (
b101 *
0-
1/
07
bz1000010 +
19
1!
b1001100 #
b1001100 )
#780
0!
#785
0:
12
00
1,
1%
09
11
bz0000100 +
0/
1&
b110 '
b110 (
b110 *
1!
b1001101 #
b1001101 )
#790
0!
#795
1.
02
14
0,
0&
b111 '
b111 (
b111 *
1-
01
bz0001001 +
13
0%
1!
b1001110 #
b1001110 )
#800
0!
#805
16
04
10
0.
1,
15
03
1/
bz0010010 +
0-
1&
b0 '
b0 (
b0 *
1!
b1001111 #
b1001111 )
#810
0!
#815
00
12
06
18
b1 '
b1 (
b1 *
0/
11
05
bz0100100 +
17
0,
1!
0&
b1010000 #
b1010000 )
#820
0!
#825
1:
08
14
02
19
07
13
bz1001000 +
01
b10 '
b10 (
b10 *
1!
b1010001 #
b1010001 )
#830
0!
#835
04
16
0:
b11 '
b11 (
b11 *
03
15
bz0010000 +
09
1%
1!
b1010010 #
b1010010 )
#840
0!
#845
18
06
1,
0%
17
bz0100000 +
05
1&
b100 '
b100 (
b100 *
1!
b1010011 #
b1010011 )
#850
0!
#855
1.
08
1:
0,
0&
b101 '
b101 (
b101 *
1-
07
bz1000001 +
19
1!
b1010100 #
b1010100 )
#860
0!
#865
0:
10
0.
1,
1%
09
1/
bz0000010 +
0-
1&
b110 '
b110 (
b110 *
1!
b1010101 #
b1010101 )
#870
0!
#875
1.
00
12
0,
0&
b111 '
b111 (
b111 *
1-
0/
bz0000101 +
11
0%
1!
b1010110 #
b1010110 )
#880
0!
#885
14
02
10
0.
1,
13
01
1/
bz0001010 +
0-
1&
b0 '
b0 (
b0 *
1!
b1010111 #
b1010111 )
#890
0!
#895
00
12
04
16
b1 '
b1 (
b1 *
0/
11
03
bz0010100 +
15
0,
1!
0&
b1011000 #
b1011000 )
#900
0!
#905
18
06
14
02
17
05
13
bz0101000 +
01
b10 '
b10 (
b10 *
1!
b1011001 #
b1011001 )
#910
0!
#915
04
16
08
1:
1,
1&
b11 '
b11 (
b11 *
03
15
07
bz1010000 +
19
1!
b1011010 #
b1011010 )
#920
0!
#925
0:
18
06
1.
1%
09
17
05
bz0100001 +
1-
b100 '
b100 (
b100 *
1!
b1011011 #
b1011011 )
#930
0!
#935
10
08
1:
0,
0&
b101 '
b101 (
b101 *
1/
07
bz1000011 +
19
0%
1!
b1011100 #
b1011100 )
#940
0!
#945
0:
12
0.
1,
1%
09
11
bz0000110 +
0-
1&
b110 '
b110 (
b110 *
1!
b1011101 #
b1011101 )
#950
0!
#955
1.
00
14
0,
0&
b111 '
b111 (
b111 *
1-
0/
bz0001101 +
13
0%
1!
b1011110 #
b1011110 )
#960
0!
#965
16
02
10
0.
1,
15
01
1/
bz0011010 +
0-
1&
b0 '
b0 (
b0 *
1!
b1011111 #
b1011111 )
#970
0!
#975
00
12
04
18
b1 '
b1 (
b1 *
0/
11
03
bz0110100 +
17
0,
1!
0&
b1100000 #
b1100000 )
#980
0!
#985
1:
06
14
02
19
05
13
bz1101000 +
01
b10 '
b10 (
b10 *
1!
b1100001 #
b1100001 )
#990
0!
#995
04
16
08
b11 '
b11 (
b11 *
03
15
bz1010000 +
07
1%
1!
b1100010 #
b1100010 )
#1000
0!
#1005
0:
18
06
09
17
bz0100000 +
05
b100 '
b100 (
b100 *
1!
b1100011 #
b1100011 )
#1010
0!
#1015
08
1:
1,
1&
b101 '
b101 (
b101 *
07
bz1000000 +
19
0%
1!
b1100100 #
b1100100 )
#1020
0!
#1025
0:
1.
1%
09
bz0000001 +
1-
b110 '
b110 (
b110 *
1!
b1100101 #
b1100101 )
#1030
0!
#1035
10
0,
0&
b111 '
b111 (
b111 *
bz0000011 +
1/
0%
1!
b1100110 #
b1100110 )
#1040
0!
#1045
12
0.
1,
11
bz0000110 +
0-
1&
b0 '
b0 (
b0 *
1!
b1100111 #
b1100111 )
#1050
0!
#1055
00
14
b1 '
b1 (
b1 *
0/
bz0001100 +
13
0,
1!
0&
b1101000 #
b1101000 )
#1060
0!
#1065
16
02
15
bz0011000 +
01
b10 '
b10 (
b10 *
1!
b1101001 #
b1101001 )
#1070
0!
#1075
04
18
1,
1&
b11 '
b11 (
b11 *
03
bz0110000 +
17
1!
b1101010 #
b1101010 )
#1080
0!
#1085
1:
06
1.
0,
19
05
bz1100001 +
1-
0&
b100 '
b100 (
b100 *
1!
b1101011 #
b1101011 )
#1090
0!
#1095
0.
10
08
1,
1&
b101 '
b101 (
b101 *
0-
1/
bz1000010 +
07
1%
1!
b1101100 #
b1101100 )
#1100
0!
#1105
0:
12
00
1.
09
11
0/
bz0000101 +
1-
b110 '
b110 (
b110 *
1!
b1101101 #
b1101101 )
#1110
0!
#1115
10
02
14
0,
0&
b111 '
b111 (
b111 *
1/
01
bz0001011 +
13
0%
1!
b1101110 #
b1101110 )
#1120
0!
#1125
16
04
12
0.
1,
15
03
11
bz0010110 +
0-
1&
b0 '
b0 (
b0 *
1!
b1101111 #
b1101111 )
#1130
0!
#1135
00
14
06
18
b1 '
b1 (
b1 *
0/
13
05
bz0101100 +
17
0,
1!
0&
b1110000 #
b1110000 )
#1140
0!
#1145
1:
08
16
02
19
07
15
bz1011000 +
01
b10 '
b10 (
b10 *
1!
b1110001 #
b1110001 )
#1150
0!
#1155
04
18
0:
b11 '
b11 (
b11 *
03
17
bz0110000 +
09
1%
1!
b1110010 #
b1110010 )
#1160
0!
#1165
1:
06
1,
0%
19
bz1100000 +
05
1&
b100 '
b100 (
b100 *
1!
b1110011 #
b1110011 )
#1170
0!
#1175
1.
08
b101 '
b101 (
b101 *
1-
bz1000001 +
07
1%
1!
b1110100 #
b1110100 )
#1180
0!
#1185
0:
10
09
bz0000011 +
1/
b110 '
b110 (
b110 *
1!
b1110101 #
b1110101 )
#1190
0!
#1195
12
0,
0&
b111 '
b111 (
b111 *
bz0000111 +
11
0%
1!
b1110110 #
b1110110 )
#1200
0!
#1205
14
0.
1,
13
bz0001110 +
0-
1&
b0 '
b0 (
b0 *
1!
b1110111 #
b1110111 )
#1210
0!
#1215
00
16
b1 '
b1 (
b1 *
0/
bz0011100 +
15
0,
1!
0&
b1111000 #
b1111000 )
#1220
0!
#1225
18
02
17
bz0111000 +
01
b10 '
b10 (
b10 *
1!
b1111001 #
b1111001 )
#1230
0!
#1235
04
1:
1,
1&
b11 '
b11 (
b11 *
03
bz1110000 +
19
1!
b1111010 #
b1111010 )
#1240
0!
#1245
06
1.
1%
05
bz1100001 +
1-
b100 '
b100 (
b100 *
1!
b1111011 #
b1111011 )
#1250
0!
#1255
10
08
b101 '
b101 (
b101 *
1/
bz1000011 +
07
1!
b1111100 #
b1111100 )
#1260
0!
#1265
0:
12
09
bz0000111 +
11
b110 '
b110 (
b110 *
1!
b1111101 #
b1111101 )
#1270
0!
#1275
14
0,
0&
b111 '
b111 (
b111 *
bz0001111 +
13
0%
1!
b1111110 #
b1111110 )
#1280
0!
#1285
16
0.
1,
15
bz0011110 +
0-
1&
b0 '
b0 (
b0 *
1!
b1111111 #
b1111111 )
#1290
0!
#1295
00
18
b1 '
b1 (
b1 *
0/
bz0111100 +
17
0,
1!
0&
b10000000 #
b10000000 )
#1300
0!
#1305
1:
02
19
bz1111000 +
01
b10 '
b10 (
b10 *
1!
b10000001 #
b10000001 )
#1310
0!
#1315
04
b11 '
b11 (
b11 *
bz1110000 +
03
1%
1!
b10000010 #
b10000010 )
#1320
0!
#1325
06
bz1100000 +
05
b100 '
b100 (
b100 *
1!
b10000011 #
b10000011 )
#1330
0!
#1335
08
b101 '
b101 (
b101 *
bz1000000 +
07
1!
b10000100 #
b10000100 )
#1340
0!
#1345
0:
bz0000000 +
09
b110 '
b110 (
b110 *
1!
b10000101 #
b10000101 )
#1350
0!
#1355
1,
1&
b111 '
b111 (
b111 *
0%
1!
b10000110 #
b10000110 )
#1360
0!
#1365
1.
bz0000001 +
1-
b0 '
b0 (
b0 *
1!
b10000111 #
b10000111 )
#1370
0!
#1375
0.
10
b1 '
b1 (
b1 *
0-
bz0000010 +
1/
0,
1!
0&
b10001000 #
b10001000 )
#1380
0!
#1385
12
00
11
bz0000100 +
0/
b10 '
b10 (
b10 *
1!
b10001001 #
b10001001 )
#1390
0!
#1395
02
14
1,
1&
b11 '
b11 (
b11 *
01
bz0001000 +
13
1!
b10001010 #
b10001010 )
#1400
0!
#1405
16
04
1.
0,
15
03
bz0010001 +
1-
0&
b100 '
b100 (
b100 *
1!
b10001011 #
b10001011 )
#1410
0!
#1415
0.
10
06
18
b101 '
b101 (
b101 *
0-
1/
05
bz0100010 +
17
1!
b10001100 #
b10001100 )
#1420
0!
#1425
1:
08
12
00
19
07
11
bz1000100 +
0/
b110 '
b110 (
b110 *
1!
b10001101 #
b10001101 )
#1430
0!
#1435
02
14
0:
1,
1&
b111 '
b111 (
b111 *
01
13
bz0001000 +
09
1%
1!
b10001110 #
b10001110 )
#1440
0!
#1445
16
04
1.
0%
15
03
bz0010001 +
1-
b0 '
b0 (
b0 *
1!
b10001111 #
b10001111 )
#1450
0!
#1455
0.
10
06
18
b1 '
b1 (
b1 *
0-
1/
05
bz0100010 +
17
0,
1!
0&
b10010000 #
b10010000 )
#1460
0!
#1465
1:
08
12
00
19
07
11
bz1000100 +
0/
b10 '
b10 (
b10 *
1!
b10010001 #
b10010001 )
#1470
0!
#1475
02
14
0:
b11 '
b11 (
b11 *
01
13
bz0001000 +
09
1%
1!
b10010010 #
b10010010 )
#1480
0!
#1485
16
04
1,
0%
15
bz0010000 +
03
1&
b100 '
b100 (
b100 *
1!
b10010011 #
b10010011 )
#1490
0!
#1495
1.
06
18
0,
0&
b101 '
b101 (
b101 *
1-
05
bz0100001 +
17
1!
b10010100 #
b10010100 )
#1500
0!
#1505
1:
08
10
0.
19
07
1/
bz1000010 +
0-
b110 '
b110 (
b110 *
1!
b10010101 #
b10010101 )
#1510
0!
#1515
00
12
0:
1,
1&
b111 '
b111 (
b111 *
0/
11
bz0000100 +
09
1%
1!
b10010110 #
b10010110 )
#1520
0!
#1525
14
02
1.
0%
13
01
bz0001001 +
1-
b0 '
b0 (
b0 *
1!
b10010111 #
b10010111 )
#1530
0!
#1535
0.
10
04
16
b1 '
b1 (
b1 *
0-
1/
03
bz0010010 +
15
0,
1!
0&
b10011000 #
b10011000 )
#1540
0!
#1545
18
06
12
00
17
05
11
bz0100100 +
0/
b10 '
b10 (
b10 *
1!
b10011001 #
b10011001 )
#1550
0!
#1555
02
14
08
1:
1,
1&
b11 '
b11 (
b11 *
01
13
07
bz1001000 +
19
1!
b10011010 #
b10011010 )
#1560
0!
#1565
0:
16
04
1.
1%
09
15
03
bz0010001 +
1-
b100 '
b100 (
b100 *
1!
b10011011 #
b10011011 )
#1570
0!
#1575
10
06
18
0,
0&
b101 '
b101 (
b101 *
1/
05
bz0100011 +
17
0%
1!
b10011100 #
b10011100 )
#1580
0!
#1585
1:
08
12
0.
19
07
11
bz1000110 +
0-
b110 '
b110 (
b110 *
1!
b10011101 #
b10011101 )
#1590
0!
#1595
00
14
0:
1,
1&
b111 '
b111 (
b111 *
0/
13
bz0001100 +
09
1%
1!
b10011110 #
b10011110 )
#1600
0!
#1605
16
02
1.
0%
15
01
bz0011001 +
1-
b0 '
b0 (
b0 *
1!
b10011111 #
b10011111 )
#1610
0!
#1615
0.
10
04
18
b1 '
b1 (
b1 *
0-
1/
03
bz0110010 +
17
0,
1!
0&
b10100000 #
b10100000 )
#1620
0!
#1625
1:
06
12
00
19
05
11
bz1100100 +
0/
b10 '
b10 (
b10 *
1!
b10100001 #
b10100001 )
#1630
0!
#1635
02
14
08
b11 '
b11 (
b11 *
01
13
bz1001000 +
07
1%
1!
b10100010 #
b10100010 )
#1640
0!
#1645
0:
16
04
09
15
bz0010000 +
03
b100 '
b100 (
b100 *
1!
b10100011 #
b10100011 )
#1650
0!
#1655
06
18
1,
1&
b101 '
b101 (
b101 *
05
bz0100000 +
17
0%
1!
b10100100 #
b10100100 )
#1660
0!
#1665
1:
08
1.
0,
19
07
bz1000001 +
1-
0&
b110 '
b110 (
b110 *
1!
b10100101 #
b10100101 )
#1670
0!
#1675
0.
10
0:
1,
1&
b111 '
b111 (
b111 *
0-
1/
bz0000010 +
09
1%
1!
b10100110 #
b10100110 )
#1680
0!
#1685
12
00
1.
0%
11
0/
bz0000101 +
1-
b0 '
b0 (
b0 *
1!
b10100111 #
b10100111 )
#1690
0!
#1695
0.
10
02
14
b1 '
b1 (
b1 *
0-
1/
01
bz0001010 +
13
0,
1!
0&
b10101000 #
b10101000 )
#1700
0!
#1705
16
04
12
00
15
03
11
bz0010100 +
0/
b10 '
b10 (
b10 *
1!
b10101001 #
b10101001 )
#1710
0!
#1715
02
14
06
18
1,
1&
b11 '
b11 (
b11 *
01
13
05
bz0101000 +
17
1!
b10101010 #
b10101010 )
#1720
0!
#1725
1:
08
16
04
1.
0,
19
07
15
03
bz1010001 +
1-
0&
b100 '
b100 (
b100 *
1!
b10101011 #
b10101011 )
#1730
0!
#1735
0.
10
06
18
0:
1,
1&
b101 '
b101 (
b101 *
0-
1/
05
17
bz0100010 +
09
1%
1!
b10101100 #
b10101100 )
#1740
0!
#1745
1:
08
12
00
1.
0,
0%
19
07
11
0/
bz1000101 +
1-
0&
b110 '
b110 (
b110 *
1!
b10101101 #
b10101101 )
#1750
0!
#1755
0.
10
02
14
0:
1,
1&
b111 '
b111 (
b111 *
0-
1/
01
13
bz0001010 +
09
1%
1!
b10101110 #
b10101110 )
#1760
0!
#1765
16
04
12
00
1.
0%
15
03
11
0/
bz0010101 +
1-
b0 '
b0 (
b0 *
1!
b10101111 #
b10101111 )
#1770
0!
#1775
0.
10
02
14
06
18
b1 '
b1 (
b1 *
0-
1/
01
13
05
bz0101010 +
17
0,
1!
0&
b10110000 #
b10110000 )
#1780
0!
#1785
1:
08
16
04
12
00
19
07
15
03
11
bz1010100 +
0/
b10 '
b10 (
b10 *
1!
b10110001 #
b10110001 )
#1790
0!
#1795
02
14
06
18
0:
b11 '
b11 (
b11 *
01
13
05
17
bz0101000 +
09
1%
1!
b10110010 #
b10110010 )
#1800
0!
#1805
1:
08
16
04
1,
0%
19
07
15
bz1010000 +
03
1&
b100 '
b100 (
b100 *
1!
b10110011 #
b10110011 )
#1810
0!
#1815
1.
06
18
0:
b101 '
b101 (
b101 *
1-
05
17
bz0100001 +
09
1%
1!
b10110100 #
b10110100 )
#1820
0!
#1825
1:
08
10
0,
0%
19
07
bz1000011 +
1/
0&
b110 '
b110 (
b110 *
1!
b10110101 #
b10110101 )
#1830
0!
#1835
0.
12
0:
1,
1&
b111 '
b111 (
b111 *
0-
11
bz0000110 +
09
1%
1!
b10110110 #
b10110110 )
#1840
0!
#1845
14
00
1.
0%
13
0/
bz0001101 +
1-
b0 '
b0 (
b0 *
1!
b10110111 #
b10110111 )
#1850
0!
#1855
0.
10
02
16
b1 '
b1 (
b1 *
0-
1/
01
bz0011010 +
15
0,
1!
0&
b10111000 #
b10111000 )
#1860
0!
#1865
18
04
12
00
17
03
11
bz0110100 +
0/
b10 '
b10 (
b10 *
1!
b10111001 #
b10111001 )
#1870
0!
#1875
02
14
06
1:
1,
1&
b11 '
b11 (
b11 *
01
13
05
bz1101000 +
19
1!
b10111010 #
b10111010 )
#1880
0!
#1885
08
16
04
1.
1%
07
15
03
bz1010001 +
1-
b100 '
b100 (
b100 *
1!
b10111011 #
b10111011 )
#1890
0!
#1895
10
06
18
0:
b101 '
b101 (
b101 *
1/
05
17
bz0100011 +
09
1!
b10111100 #
b10111100 )
#1900
0!
#1905
1:
08
12
0,
0%
19
07
bz1000111 +
11
0&
b110 '
b110 (
b110 *
1!
b10111101 #
b10111101 )
#1910
0!
#1915
0.
14
0:
1,
1&
b111 '
b111 (
b111 *
0-
13
bz0001110 +
09
1%
1!
b10111110 #
b10111110 )
#1920
0!
#1925
16
00
1.
0%
15
0/
bz0011101 +
1-
b0 '
b0 (
b0 *
1!
b10111111 #
b10111111 )
#1930
0!
