TL/Traffic_Light.v
module TL(
    input clk,
    input res,
    output out
);

    reg [8:0] inp1, inp2, inp3; 
    reg GTY, YTR, RTG;

    assign out = RTG; 

    initial begin
        GTY = 1;   
        YTR = 0;
        RTG = 0;
        inp1 = 0;
        inp2 = 0;
        inp3 = 0;
    end

    always @(posedge clk) begin
        if (res) begin
            GTY <= 1;
            YTR <= 0;
            RTG <= 0;
            inp1 <= 0;
            inp2 <= 0;
            inp3 <= 0;
        end 
        else begin
            if (GTY) begin
                if (inp1 == 8'b11111111) begin
                    GTY <= 0;
                    YTR <= 1;
                    RTG <= 0;
                    inp1 <= 0;
                end else begin
                    inp1 <= inp1 + 1;
                end
            end
            if (YTR) begin
                if (inp2 == 8'b11111111) begin
                    GTY <= 0;
                    YTR <= 0;
                    RTG <= 1;
                    inp2 <= 0;
                end else begin
                    inp2 <= inp2 + 1;
                end
            end
            if (RTG) begin
                if (inp3 == 8'b11111111) begin
                    GTY <= 1;
                    YTR <= 0;
                    RTG <= 0;
                    inp3 <= 0;
                end else begin
                    inp3 <= inp3 + 1;
                end
            end
        end
    end

endmodule

TL/Traffic_Light_tb.v
`include "Traffic_Light.v"

module TL_tb();

    reg clk = 0;  
    reg res=1;
    wire out;     

    TL u_tl (
        .clk(clk),
        .res(res),
        .out(out)
    );

    always #1 clk = ~clk;

    initial 
        $display("Time=%0t | GTY=%b, YTR=%b, RTG=%b, Out=%b, res=%b", $time, u_tl.GTY, u_tl.YTR, u_tl.RTG, out, res);

    initial begin
        $dumpfile("Traffic_Light.vcd"); 
        $dumpvars(0, u_tl);
        res=0;
        $monitor("Time=%0t | GTY=%b, YTR=%b, RTG=%b, Out=%b, res=%b", $time, u_tl.GTY, u_tl.YTR, u_tl.RTG, out, res);
    end

    always@(posedge u_tl.RTG) begin
        $finish;
    end
endmodule

TL/Traffic_Light.vcd
$date
	Tue Dec 17 17:22:04 2024
$end
$version
	Icarus Verilog
$end
$timescale
	1s
$end
$scope module TL_tb $end
$scope module u_tl $end
$var wire 1 ! clk $end
$var wire 1 " out $end
$var wire 1 # res $end
$var reg 1 $ GTY $end
$var reg 1 % RTG $end
$var reg 1 & YTR $end
$var reg 9 ' inp1 [8:0] $end
$var reg 9 ( inp2 [8:0] $end
$var reg 9 ) inp3 [8:0] $end
$upscope $end
$upscope $end
$enddefinitions $end
#0
$dumpvars
b0 )
b0 (
b0 '
0&
0%
1$
0#
0"
0!
$end
#1
b1 '
1!
#2
0!
#3
b10 '
1!
#4
0!
#5
b11 '
1!
#6
0!
#7
b100 '
1!
#8
0!
#9
b101 '
1!
#10
0!
#11
b110 '
1!
#12
0!
#13
b111 '
1!
#14
0!
#15
b1000 '
1!
#16
0!
#17
b1001 '
1!
#18
0!
#19
b1010 '
1!
#20
0!
#21
b1011 '
1!
#22
0!
#23
b1100 '
1!
#24
0!
#25
b1101 '
1!
#26
0!
#27
b1110 '
1!
#28
0!
#29
b1111 '
1!
#30
0!
#31
b10000 '
1!
#32
0!
#33
b10001 '
1!
#34
0!
#35
b10010 '
1!
#36
0!
#37
b10011 '
1!
#38
0!
#39
b10100 '
1!
#40
0!
#41
b10101 '
1!
#42
0!
#43
b10110 '
1!
#44
0!
#45
b10111 '
1!
#46
0!
#47
b11000 '
1!
#48
0!
#49
b11001 '
1!
#50
0!
#51
b11010 '
1!
#52
0!
#53
b11011 '
1!
#54
0!
#55
b11100 '
1!
#56
0!
#57
b11101 '
1!
#58
0!
#59
b11110 '
1!
#60
0!
#61
b11111 '
1!
#62
0!
#63
b100000 '
1!
#64
0!
#65
b100001 '
1!
#66
0!
#67
b100010 '
1!
#68
0!
#69
b100011 '
1!
#70
0!
#71
b100100 '
1!
#72
0!
#73
b100101 '
1!
#74
0!
#75
b100110 '
1!
#76
0!
#77
b100111 '
1!
#78
0!
#79
b101000 '
1!
#80
0!
#81
b101001 '
1!
#82
0!
#83
b101010 '
1!
#84
0!
#85
b101011 '
1!
#86
0!
#87
b101100 '
1!
#88
0!
#89
b101101 '
1!
#90
0!
#91
b101110 '
1!
#92
0!
#93
b101111 '
1!
#94
0!
#95
b110000 '
1!
#96
0!
#97
b110001 '
1!
#98
0!
#99
b110010 '
1!
#100
0!
#101
b110011 '
1!
#102
0!
#103
b110100 '
1!
#104
0!
#105
b110101 '
1!
#106
0!
#107
b110110 '
1!
#108
0!
#109
b110111 '
1!
#110
0!
#111
b111000 '
1!
#112
0!
#113
b111001 '
1!
#114
0!
#115
b111010 '
1!
#116
0!
#117
b111011 '
1!
#118
0!
#119
b111100 '
1!
#120
0!
#121
b111101 '
1!
#122
0!
#123
b111110 '
1!
#124
0!
#125
b111111 '
1!
#126
0!
#127
b1000000 '
1!
#128
0!
#129
b1000001 '
1!
#130
0!
#131
b1000010 '
1!
#132
0!
#133
b1000011 '
1!
#134
0!
#135
b1000100 '
1!
#136
0!
#137
b1000101 '
1!
#138
0!
#139
b1000110 '
1!
#140
0!
#141
b1000111 '
1!
#142
0!
#143
b1001000 '
1!
#144
0!
#145
b1001001 '
1!
#146
0!
#147
b1001010 '
1!
#148
0!
#149
b1001011 '
1!
#150
0!
#151
b1001100 '
1!
#152
0!
#153
b1001101 '
1!
#154
0!
#155
b1001110 '
1!
#156
0!
#157
b1001111 '
1!
#158
0!
#159
b1010000 '
1!
#160
0!
#161
b1010001 '
1!
#162
0!
#163
b1010010 '
1!
#164
0!
#165
b1010011 '
1!
#166
0!
#167
b1010100 '
1!
#168
0!
#169
b1010101 '
1!
#170
0!
#171
b1010110 '
1!
#172
0!
#173
b1010111 '
1!
#174
0!
#175
b1011000 '
1!
#176
0!
#177
b1011001 '
1!
#178
0!
#179
b1011010 '
1!
#180
0!
#181
b1011011 '
1!
#182
0!
#183
b1011100 '
1!
#184
0!
#185
b1011101 '
1!
#186
0!
#187
b1011110 '
1!
#188
0!
#189
b1011111 '
1!
#190
0!
#191
b1100000 '
1!
#192
0!
#193
b1100001 '
1!
#194
0!
#195
b1100010 '
1!
#196
0!
#197
b1100011 '
1!
#198
0!
#199
b1100100 '
1!
#200
0!
#201
b1100101 '
1!
#202
0!
#203
b1100110 '
1!
#204
0!
#205
b1100111 '
1!
#206
0!
#207
b1101000 '
1!
#208
0!
#209
b1101001 '
1!
#210
0!
#211
b1101010 '
1!
#212
0!
#213
b1101011 '
1!
#214
0!
#215
b1101100 '
1!
#216
0!
#217
b1101101 '
1!
#218
0!
#219
b1101110 '
1!
#220
0!
#221
b1101111 '
1!
#222
0!
#223
b1110000 '
1!
#224
0!
#225
b1110001 '
1!
#226
0!
#227
b1110010 '
1!
#228
0!
#229
b1110011 '
1!
#230
0!
#231
b1110100 '
1!
#232
0!
#233
b1110101 '
1!
#234
0!
#235
b1110110 '
1!
#236
0!
#237
b1110111 '
1!
#238
0!
#239
b1111000 '
1!
#240
0!
#241
b1111001 '
1!
#242
0!
#243
b1111010 '
1!
#244
0!
#245
b1111011 '
1!
#246
0!
#247
b1111100 '
1!
#248
0!
#249
b1111101 '
1!
#250
0!
#251
b1111110 '
1!
#252
0!
#253
b1111111 '
1!
#254
0!
#255
b10000000 '
1!
#256
0!
#257
b10000001 '
1!
#258
0!
#259
b10000010 '
1!
#260
0!
#261
b10000011 '
1!
#262
0!
#263
b10000100 '
1!
#264
0!
#265
b10000101 '
1!
#266
0!
#267
b10000110 '
1!
#268
0!
#269
b10000111 '
1!
#270
0!
#271
b10001000 '
1!
#272
0!
#273
b10001001 '
1!
#274
0!
#275
b10001010 '
1!
#276
0!
#277
b10001011 '
1!
#278
0!
#279
b10001100 '
1!
#280
0!
#281
b10001101 '
1!
#282
0!
#283
b10001110 '
1!
#284
0!
#285
b10001111 '
1!
#286
0!
#287
b10010000 '
1!
#288
0!
#289
b10010001 '
1!
#290
0!
#291
b10010010 '
1!
#292
0!
#293
b10010011 '
1!
#294
0!
#295
b10010100 '
1!
#296
0!
#297
b10010101 '
1!
#298
0!
#299
b10010110 '
1!
#300
0!
#301
b10010111 '
1!
#302
0!
#303
b10011000 '
1!
#304
0!
#305
b10011001 '
1!
#306
0!
#307
b10011010 '
1!
#308
0!
#309
b10011011 '
1!
#310
0!
#311
b10011100 '
1!
#312
0!
#313
b10011101 '
1!
#314
0!
#315
b10011110 '
1!
#316
0!
#317
b10011111 '
1!
#318
0!
#319
b10100000 '
1!
#320
0!
#321
b10100001 '
1!
#322
0!
#323
b10100010 '
1!
#324
0!
#325
b10100011 '
1!
#326
0!
#327
b10100100 '
1!
#328
0!
#329
b10100101 '
1!
#330
0!
#331
b10100110 '
1!
#332
0!
#333
b10100111 '
1!
#334
0!
#335
b10101000 '
1!
#336
0!
#337
b10101001 '
1!
#338
0!
#339
b10101010 '
1!
#340
0!
#341
b10101011 '
1!
#342
0!
#343
b10101100 '
1!
#344
0!
#345
b10101101 '
1!
#346
0!
#347
b10101110 '
1!
#348
0!
#349
b10101111 '
1!
#350
0!
#351
b10110000 '
1!
#352
0!
#353
b10110001 '
1!
#354
0!
#355
b10110010 '
1!
#356
0!
#357
b10110011 '
1!
#358
0!
#359
b10110100 '
1!
#360
0!
#361
b10110101 '
1!
#362
0!
#363
b10110110 '
1!
#364
0!
#365
b10110111 '
1!
#366
0!
#367
b10111000 '
1!
#368
0!
#369
b10111001 '
1!
#370
0!
#371
b10111010 '
1!
#372
0!
#373
b10111011 '
1!
#374
0!
#375
b10111100 '
1!
#376
0!
#377
b10111101 '
1!
#378
0!
#379
b10111110 '
1!
#380
0!
#381
b10111111 '
1!
#382
0!
#383
b11000000 '
1!
#384
0!
#385
b11000001 '
1!
#386
0!
#387
b11000010 '
1!
#388
0!
#389
b11000011 '
1!
#390
0!
#391
b11000100 '
1!
#392
0!
#393
b11000101 '
1!
#394
0!
#395
b11000110 '
1!
#396
0!
#397
b11000111 '
1!
#398
0!
#399
b11001000 '
1!
#400
0!
#401
b11001001 '
1!
#402
0!
#403
b11001010 '
1!
#404
0!
#405
b11001011 '
1!
#406
0!
#407
b11001100 '
1!
#408
0!
#409
b11001101 '
1!
#410
0!
#411
b11001110 '
1!
#412
0!
#413
b11001111 '
1!
#414
0!
#415
b11010000 '
1!
#416
0!
#417
b11010001 '
1!
#418
0!
#419
b11010010 '
1!
#420
0!
#421
b11010011 '
1!
#422
0!
#423
b11010100 '
1!
#424
0!
#425
b11010101 '
1!
#426
0!
#427
b11010110 '
1!
#428
0!
#429
b11010111 '
1!
#430
0!
#431
b11011000 '
1!
#432
0!
#433
b11011001 '
1!
#434
0!
#435
b11011010 '
1!
#436
0!
#437
b11011011 '
1!
#438
0!
#439
b11011100 '
1!
#440
0!
#441
b11011101 '
1!
#442
0!
#443
b11011110 '
1!
#444
0!
#445
b11011111 '
1!
#446
0!
#447
b11100000 '
1!
#448
0!
#449
b11100001 '
1!
#450
0!
#451
b11100010 '
1!
#452
0!
#453
b11100011 '
1!
#454
0!
#455
b11100100 '
1!
#456
0!
#457
b11100101 '
1!
#458
0!
#459
b11100110 '
1!
#460
0!
#461
b11100111 '
1!
#462
0!
#463
b11101000 '
1!
#464
0!
#465
b11101001 '
1!
#466
0!
#467
b11101010 '
1!
#468
0!
#469
b11101011 '
1!
#470
0!
#471
b11101100 '
1!
#472
0!
#473
b11101101 '
1!
#474
0!
#475
b11101110 '
1!
#476
0!
#477
b11101111 '
1!
#478
0!
#479
b11110000 '
1!
#480
0!
#481
b11110001 '
1!
#482
0!
#483
b11110010 '
1!
#484
0!
#485
b11110011 '
1!
#486
0!
#487
b11110100 '
1!
#488
0!
#489
b11110101 '
1!
#490
0!
#491
b11110110 '
1!
#492
0!
#493
b11110111 '
1!
#494
0!
#495
b11111000 '
1!
#496
0!
#497
b11111001 '
1!
#498
0!
#499
b11111010 '
1!
#500
0!
#501
b11111011 '
1!
#502
0!
#503
b11111100 '
1!
#504
0!
#505
b11111101 '
1!
#506
0!
#507
b11111110 '
1!
#508
0!
#509
b11111111 '
1!
#510
0!
#511
b0 '
1&
0$
1!
#512
0!
#513
b1 (
1!
#514
0!
#515
b10 (
1!
#516
0!
#517
b11 (
1!
#518
0!
#519
b100 (
1!
#520
0!
#521
b101 (
1!
#522
0!
#523
b110 (
1!
#524
0!
#525
b111 (
1!
#526
0!
#527
b1000 (
1!
#528
0!
#529
b1001 (
1!
#530
0!
#531
b1010 (
1!
#532
0!
#533
b1011 (
1!
#534
0!
#535
b1100 (
1!
#536
0!
#537
b1101 (
1!
#538
0!
#539
b1110 (
1!
#540
0!
#541
b1111 (
1!
#542
0!
#543
b10000 (
1!
#544
0!
#545
b10001 (
1!
#546
0!
#547
b10010 (
1!
#548
0!
#549
b10011 (
1!
#550
0!
#551
b10100 (
1!
#552
0!
#553
b10101 (
1!
#554
0!
#555
b10110 (
1!
#556
0!
#557
b10111 (
1!
#558
0!
#559
b11000 (
1!
#560
0!
#561
b11001 (
1!
#562
0!
#563
b11010 (
1!
#564
0!
#565
b11011 (
1!
#566
0!
#567
b11100 (
1!
#568
0!
#569
b11101 (
1!
#570
0!
#571
b11110 (
1!
#572
0!
#573
b11111 (
1!
#574
0!
#575
b100000 (
1!
#576
0!
#577
b100001 (
1!
#578
0!
#579
b100010 (
1!
#580
0!
#581
b100011 (
1!
#582
0!
#583
b100100 (
1!
#584
0!
#585
b100101 (
1!
#586
0!
#587
b100110 (
1!
#588
0!
#589
b100111 (
1!
#590
0!
#591
b101000 (
1!
#592
0!
#593
b101001 (
1!
#594
0!
#595
b101010 (
1!
#596
0!
#597
b101011 (
1!
#598
0!
#599
b101100 (
1!
#600
0!
#601
b101101 (
1!
#602
0!
#603
b101110 (
1!
#604
0!
#605
b101111 (
1!
#606
0!
#607
b110000 (
1!
#608
0!
#609
b110001 (
1!
#610
0!
#611
b110010 (
1!
#612
0!
#613
b110011 (
1!
#614
0!
#615
b110100 (
1!
#616
0!
#617
b110101 (
1!
#618
0!
#619
b110110 (
1!
#620
0!
#621
b110111 (
1!
#622
0!
#623
b111000 (
1!
#624
0!
#625
b111001 (
1!
#626
0!
#627
b111010 (
1!
#628
0!
#629
b111011 (
1!
#630
0!
#631
b111100 (
1!
#632
0!
#633
b111101 (
1!
#634
0!
#635
b111110 (
1!
#636
0!
#637
b111111 (
1!
#638
0!
#639
b1000000 (
1!
#640
0!
#641
b1000001 (
1!
#642
0!
#643
b1000010 (
1!
#644
0!
#645
b1000011 (
1!
#646
0!
#647
b1000100 (
1!
#648
0!
#649
b1000101 (
1!
#650
0!
#651
b1000110 (
1!
#652
0!
#653
b1000111 (
1!
#654
0!
#655
b1001000 (
1!
#656
0!
#657
b1001001 (
1!
#658
0!
#659
b1001010 (
1!
#660
0!
#661
b1001011 (
1!
#662
0!
#663
b1001100 (
1!
#664
0!
#665
b1001101 (
1!
#666
0!
#667
b1001110 (
1!
#668
0!
#669
b1001111 (
1!
#670
0!
#671
b1010000 (
1!
#672
0!
#673
b1010001 (
1!
#674
0!
#675
b1010010 (
1!
#676
0!
#677
b1010011 (
1!
#678
0!
#679
b1010100 (
1!
#680
0!
#681
b1010101 (
1!
#682
0!
#683
b1010110 (
1!
#684
0!
#685
b1010111 (
1!
#686
0!
#687
b1011000 (
1!
#688
0!
#689
b1011001 (
1!
#690
0!
#691
b1011010 (
1!
#692
0!
#693
b1011011 (
1!
#694
0!
#695
b1011100 (
1!
#696
0!
#697
b1011101 (
1!
#698
0!
#699
b1011110 (
1!
#700
0!
#701
b1011111 (
1!
#702
0!
#703
b1100000 (
1!
#704
0!
#705
b1100001 (
1!
#706
0!
#707
b1100010 (
1!
#708
0!
#709
b1100011 (
1!
#710
0!
#711
b1100100 (
1!
#712
0!
#713
b1100101 (
1!
#714
0!
#715
b1100110 (
1!
#716
0!
#717
b1100111 (
1!
#718
0!
#719
b1101000 (
1!
#720
0!
#721
b1101001 (
1!
#722
0!
#723
b1101010 (
1!
#724
0!
#725
b1101011 (
1!
#726
0!
#727
b1101100 (
1!
#728
0!
#729
b1101101 (
1!
#730
0!
#731
b1101110 (
1!
#732
0!
#733
b1101111 (
1!
#734
0!
#735
b1110000 (
1!
#736
0!
#737
b1110001 (
1!
#738
0!
#739
b1110010 (
1!
#740
0!
#741
b1110011 (
1!
#742
0!
#743
b1110100 (
1!
#744
0!
#745
b1110101 (
1!
#746
0!
#747
b1110110 (
1!
#748
0!
#749
b1110111 (
1!
#750
0!
#751
b1111000 (
1!
#752
0!
#753
b1111001 (
1!
#754
0!
#755
b1111010 (
1!
#756
0!
#757
b1111011 (
1!
#758
0!
#759
b1111100 (
1!
#760
0!
#761
b1111101 (
1!
#762
0!
#763
b1111110 (
1!
#764
0!
#765
b1111111 (
1!
#766
0!
#767
b10000000 (
1!
#768
0!
#769
b10000001 (
1!
#770
0!
#771
b10000010 (
1!
#772
0!
#773
b10000011 (
1!
#774
0!
#775
b10000100 (
1!
#776
0!
#777
b10000101 (
1!
#778
0!
#779
b10000110 (
1!
#780
0!
#781
b10000111 (
1!
#782
0!
#783
b10001000 (
1!
#784
0!
#785
b10001001 (
1!
#786
0!
#787
b10001010 (
1!
#788
0!
#789
b10001011 (
1!
#790
0!
#791
b10001100 (
1!
#792
0!
#793
b10001101 (
1!
#794
0!
#795
b10001110 (
1!
#796
0!
#797
b10001111 (
1!
#798
0!
#799
b10010000 (
1!
#800
0!
#801
b10010001 (
1!
#802
0!
#803
b10010010 (
1!
#804
0!
#805
b10010011 (
1!
#806
0!
#807
b10010100 (
1!
#808
0!
#809
b10010101 (
1!
#810
0!
#811
b10010110 (
1!
#812
0!
#813
b10010111 (
1!
#814
0!
#815
b10011000 (
1!
#816
0!
#817
b10011001 (
1!
#818
0!
#819
b10011010 (
1!
#820
0!
#821
b10011011 (
1!
#822
0!
#823
b10011100 (
1!
#824
0!
#825
b10011101 (
1!
#826
0!
#827
b10011110 (
1!
#828
0!
#829
b10011111 (
1!
#830
0!
#831
b10100000 (
1!
#832
0!
#833
b10100001 (
1!
#834
0!
#835
b10100010 (
1!
#836
0!
#837
b10100011 (
1!
#838
0!
#839
b10100100 (
1!
#840
0!
#841
b10100101 (
1!
#842
0!
#843
b10100110 (
1!
#844
0!
#845
b10100111 (
1!
#846
0!
#847
b10101000 (
1!
#848
0!
#849
b10101001 (
1!
#850
0!
#851
b10101010 (
1!
#852
0!
#853
b10101011 (
1!
#854
0!
#855
b10101100 (
1!
#856
0!
#857
b10101101 (
1!
#858
0!
#859
b10101110 (
1!
#860
0!
#861
b10101111 (
1!
#862
0!
#863
b10110000 (
1!
#864
0!
#865
b10110001 (
1!
#866
0!
#867
b10110010 (
1!
#868
0!
#869
b10110011 (
1!
#870
0!
#871
b10110100 (
1!
#872
0!
#873
b10110101 (
1!
#874
0!
#875
b10110110 (
1!
#876
0!
#877
b10110111 (
1!
#878
0!
#879
b10111000 (
1!
#880
0!
#881
b10111001 (
1!
#882
0!
#883
b10111010 (
1!
#884
0!
#885
b10111011 (
1!
#886
0!
#887
b10111100 (
1!
#888
0!
#889
b10111101 (
1!
#890
0!
#891
b10111110 (
1!
#892
0!
#893
b10111111 (
1!
#894
0!
#895
b11000000 (
1!
#896
0!
#897
b11000001 (
1!
#898
0!
#899
b11000010 (
1!
#900
0!
#901
b11000011 (
1!
#902
0!
#903
b11000100 (
1!
#904
0!
#905
b11000101 (
1!
#906
0!
#907
b11000110 (
1!
#908
0!
#909
b11000111 (
1!
#910
0!
#911
b11001000 (
1!
#912
0!
#913
b11001001 (
1!
#914
0!
#915
b11001010 (
1!
#916
0!
#917
b11001011 (
1!
#918
0!
#919
b11001100 (
1!
#920
0!
#921
b11001101 (
1!
#922
0!
#923
b11001110 (
1!
#924
0!
#925
b11001111 (
1!
#926
0!
#927
b11010000 (
1!
#928
0!
#929
b11010001 (
1!
#930
0!
#931
b11010010 (
1!
#932
0!
#933
b11010011 (
1!
#934
0!
#935
b11010100 (
1!
#936
0!
#937
b11010101 (
1!
#938
0!
#939
b11010110 (
1!
#940
0!
#941
b11010111 (
1!
#942
0!
#943
b11011000 (
1!
#944
0!
#945
b11011001 (
1!
#946
0!
#947
b11011010 (
1!
#948
0!
#949
b11011011 (
1!
#950
0!
#951
b11011100 (
1!
#952
0!
#953
b11011101 (
1!
#954
0!
#955
b11011110 (
1!
#956
0!
#957
b11011111 (
1!
#958
0!
#959
b11100000 (
1!
#960
0!
#961
b11100001 (
1!
#962
0!
#963
b11100010 (
1!
#964
0!
#965
b11100011 (
1!
#966
0!
#967
b11100100 (
1!
#968
0!
#969
b11100101 (
1!
#970
0!
#971
b11100110 (
1!
#972
0!
#973
b11100111 (
1!
#974
0!
#975
b11101000 (
1!
#976
0!
#977
b11101001 (
1!
#978
0!
#979
b11101010 (
1!
#980
0!
#981
b11101011 (
1!
#982
0!
#983
b11101100 (
1!
#984
0!
#985
b11101101 (
1!
#986
0!
#987
b11101110 (
1!
#988
0!
#989
b11101111 (
1!
#990
0!
#991
b11110000 (
1!
#992
0!
#993
b11110001 (
1!
#994
0!
#995
b11110010 (
1!
#996
0!
#997
b11110011 (
1!
#998
0!
#999
b11110100 (
1!
#1000
0!
#1001
b11110101 (
1!
#1002
0!
#1003
b11110110 (
1!
#1004
0!
#1005
b11110111 (
1!
#1006
0!
#1007
b11111000 (
1!
#1008
0!
#1009
b11111001 (
1!
#1010
0!
#1011
b11111010 (
1!
#1012
0!
#1013
b11111011 (
1!
#1014
0!
#1015
b11111100 (
1!
#1016
0!
#1017
b11111101 (
1!
#1018
0!
#1019
b11111110 (
1!
#1020
0!
#1021
b11111111 (
1!
#1022
0!
#1023
b0 (
1"
1%
0&
1!
