FULL_ADDER/FULL_ADDER.v
module FA(
    input a,
    input b,
    input cin,
    output s,
    output cout
);

assign s = (a ^ b) ^ cin;
assign cout = ((a ^ b) & cin) | (a & b);

endmodule

module bit_FA8(
    input [7:0] a,      
    input [7:0] b,      
    input cin,          
    output [8:0] s,     
    output cout         
);

genvar i;
wire [7:0] carry;  

generate
    for (i = 0; i < 8; i = i + 1) begin: adder
        if (i == 0) begin
            FA u_fa (
                .a(a[i]),
                .b(b[i]),
                .cin(cin),
                .s(s[i]),
                .cout(carry[i])
            );
        end 
        else begin
            FA u_fa (
                .a(a[i]),
                .b(b[i]),
                .cin(carry[i-1]),
                .s(s[i]),
                .cout(carry[i])
            );
        end
    end
endgenerate

assign s[8] = carry[7];

endmodule

FULL_ADDER/FULL_ADDER_tb.v
`include "FULL_ADDER.v"

module FA_tb();

reg cin = 1'b0;
reg [7:0] a = 8'b00000000, b = 8'b00000000;
wire [8:0] s;
wire cout;

bit_FA8 u_fa (
    .a(a),
    .b(b),
    .cin(cin),
    .s(s),
    .cout(cout)
);

integer i, j;

initial begin
    $dumpfile("FULL_ADDER.vcd");
    $dumpvars(0, u_fa);
    for (i = 0; i < 8; i = i + 1) begin  
        for(j=0; j<8; j=j+1) begin
            b=b+1;
            #10;
        end
        a=a+1;
        #10;
        b=0;
    end
end

initial begin
    $monitor("%d + %d = %d\n", a, b, s[8:0]);
end
    

endmodule

FULL_ADDER/FULL_ADDER.vcd
$date
	Sat Dec 14 00:41:33 2024
$end
$version
	Icarus Verilog
$end
$timescale
	1s
$end
$scope module FA_tb $end
$scope module u_fa $end
$var wire 8 ! a [7:0] $end
$var wire 8 " b [7:0] $end
$var wire 1 # cin $end
$var wire 1 $ cout $end
$var wire 9 % s [8:0] $end
$var wire 8 & carry [7:0] $end
$scope begin adder[0] $end
$scope begin genblk2 $end
$scope module u_fa $end
$var wire 1 ' a $end
$var wire 1 ( b $end
$var wire 1 # cin $end
$var wire 1 ) cout $end
$var wire 1 * s $end
$upscope $end
$upscope $end
$upscope $end
$scope begin adder[1] $end
$scope begin genblk3 $end
$scope module u_fa $end
$var wire 1 + a $end
$var wire 1 , b $end
$var wire 1 - cin $end
$var wire 1 . cout $end
$var wire 1 / s $end
$upscope $end
$upscope $end
$upscope $end
$scope begin adder[2] $end
$scope begin genblk3 $end
$scope module u_fa $end
$var wire 1 0 a $end
$var wire 1 1 b $end
$var wire 1 2 cin $end
$var wire 1 3 cout $end
$var wire 1 4 s $end
$upscope $end
$upscope $end
$upscope $end
$scope begin adder[3] $end
$scope begin genblk3 $end
$scope module u_fa $end
$var wire 1 5 a $end
$var wire 1 6 b $end
$var wire 1 7 cin $end
$var wire 1 8 cout $end
$var wire 1 9 s $end
$upscope $end
$upscope $end
$upscope $end
$scope begin adder[4] $end
$scope begin genblk3 $end
$scope module u_fa $end
$var wire 1 : a $end
$var wire 1 ; b $end
$var wire 1 < cin $end
$var wire 1 = cout $end
$var wire 1 > s $end
$upscope $end
$upscope $end
$upscope $end
$scope begin adder[5] $end
$scope begin genblk3 $end
$scope module u_fa $end
$var wire 1 ? a $end
$var wire 1 @ b $end
$var wire 1 A cin $end
$var wire 1 B cout $end
$var wire 1 C s $end
$upscope $end
$upscope $end
$upscope $end
$scope begin adder[6] $end
$scope begin genblk3 $end
$scope module u_fa $end
$var wire 1 D a $end
$var wire 1 E b $end
$var wire 1 F cin $end
$var wire 1 G cout $end
$var wire 1 H s $end
$upscope $end
$upscope $end
$upscope $end
$scope begin adder[7] $end
$scope begin genblk3 $end
$scope module u_fa $end
$var wire 1 I a $end
$var wire 1 J b $end
$var wire 1 K cin $end
$var wire 1 L cout $end
$var wire 1 M s $end
$upscope $end
$upscope $end
$upscope $end
$upscope $end
$upscope $end
$enddefinitions $end
#0
$dumpvars
0M
0L
0K
0J
0I
0H
0G
0F
0E
0D
0C
0B
0A
0@
0?
0>
0=
0<
0;
0:
09
08
07
06
05
04
03
02
01
00
0/
0.
0-
0,
0+
1*
0)
1(
0'
b0 &
b1 %
z$
0#
b1 "
b0 !
$end
#10
0*
b10 %
1/
0(
1,
b10 "
#20
b11 %
1*
1(
b11 "
#30
0*
0/
b100 %
14
0(
0,
11
b100 "
#40
b101 %
1*
1(
b101 "
#50
0*
b110 %
1/
0(
1,
b110 "
#60
b111 %
1*
1(
b111 "
#70
0*
0/
04
b1000 %
19
0(
0,
01
16
b1000 "
#80
b1001 %
1*
1(
b1001 "
#90
0*
b1010 %
1/
0(
1,
b1010 "
#100
b1011 %
1*
1(
b1011 "
#110
0*
0/
b1100 %
14
0(
0,
11
b1100 "
#120
b1101 %
1*
1(
b1101 "
#130
0*
b1110 %
1/
0(
1,
b1110 "
#140
b1111 %
1*
1(
b1111 "
#150
0*
0/
04
09
b10000 %
1>
0(
0,
01
06
1;
b10000 "
#160
b10001 %
1*
1(
b10001 "
#170
0*
b10010 %
1/
0(
1,
b10010 "
#180
b10011 %
1*
1(
b10011 "
#190
0*
0/
b10100 %
14
0(
0,
11
b10100 "
#200
b10101 %
1*
1(
b10101 "
#210
0*
b10110 %
1/
0(
1,
b10110 "
#220
b10111 %
1*
1(
b10111 "
#230
0*
0/
04
b11000 %
19
0(
0,
01
16
b11000 "
#240
b11001 %
1*
1(
b11001 "
#250
0*
b11010 %
1/
0(
1,
b11010 "
#260
b11011 %
1*
1(
b11011 "
#270
0*
0/
b11100 %
14
0(
0,
11
b11100 "
#280
b11101 %
1*
1(
b11101 "
#290
0*
b11110 %
1/
0(
1,
b11110 "
#300
b11111 %
1*
1(
b11111 "
#310
0*
0/
04
09
0>
b100000 %
1C
0(
0,
01
06
0;
1@
b100000 "
#320
b100001 %
1*
1'
b1 !
#330
1/
1-
0*
b1 &
1)
b10 %
0C
1(
0@
b1 "
#340
04
02
0-
0.
1*
b0 &
0)
b11 %
1/
0(
1,
b10 "
#350
14
12
1.
0/
1-
b100 %
0*
b11 &
1)
1(
b11 "
#360
09
02
07
0-
0.
03
1*
b0 &
0)
0/
b101 %
14
0(
0,
11
b100 "
#370
1/
1-
b110 %
0*
b1 &
1)
1(
b101 "
#380
09
07
03
14
02
0-
0.
1*
b0 &
0)
b111 %
1/
0(
1,
b110 "
#390
19
17
13
04
12
1.
0/
1-
b1000 %
0*
b111 &
1)
1(
b111 "
#400
0>
02
07
0<
0-
0.
03
08
1*
b0 &
0)
0/
04
b1001 %
19
0(
0,
01
16
b1000 "
#410
1/
1-
b1010 %
0*
b1 &
1)
1(
b1001 "
#420
04
02
0-
0.
1*
b0 &
0)
b1011 %
1/
0(
1,
b1010 "
#430
14
12
1.
0/
1-
b1100 %
0*
b11 &
1)
1(
b1011 "
#440
0>
0<
08
19
02
07
0-
0.
03
1*
b0 &
0)
0/
b1101 %
14
0(
0,
11
b1100 "
#450
1/
1-
b1110 %
0*
b1 &
1)
1(
b1101 "
#460
0>
0<
08
19
07
03
14
02
0-
0.
1*
b0 &
0)
b1111 %
1/
0(
1,
b1110 "
#470
1>
1<
18
09
17
13
04
12
1.
0/
1-
b10000 %
0*
b1111 &
1)
1(
b1111 "
#480
0C
02
07
0<
0A
0-
0.
03
08
0=
1*
b0 &
0)
0/
04
09
b10001 %
1>
0(
0,
01
06
1;
b10000 "
#490
1/
1-
b10010 %
0*
b1 &
1)
1(
b10001 "
#500
04
02
0-
0.
1*
b0 &
0)
b10011 %
1/
0(
1,
b10010 "
#510
14
12
1.
0/
1-
b10100 %
0*
b11 &
1)
1(
b10011 "
#520
09
02
07
0-
0.
03
1*
b0 &
0)
0/
b10101 %
14
0(
0,
11
b10100 "
#530
1/
1-
b10110 %
0*
b1 &
1)
1(
b10101 "
#540
09
07
03
14
02
0-
0.
1*
b0 &
0)
b10111 %
1/
0(
1,
b10110 "
#550
19
17
13
04
12
1.
0/
1-
b11000 %
0*
b111 &
1)
1(
b10111 "
#560
0C
0A
0=
1>
02
07
0<
0-
0.
03
08
1*
b0 &
0)
0/
04
b11001 %
19
0(
0,
01
16
b11000 "
#570
1/
1-
b11010 %
0*
b1 &
1)
1(
b11001 "
#580
04
02
0-
0.
1*
b0 &
0)
b11011 %
1/
0(
1,
b11010 "
#590
14
12
1.
0/
1-
b11100 %
0*
b11 &
1)
1(
b11011 "
#600
0C
0A
0=
1>
0<
08
19
02
07
0-
0.
03
1*
b0 &
0)
0/
b11101 %
14
0(
0,
11
b11100 "
#610
1/
1-
b11110 %
0*
b1 &
1)
1(
b11101 "
#620
0C
0A
0=
1>
0<
08
19
07
03
14
02
0-
0.
1*
b0 &
0)
b11111 %
1/
0(
1,
b11110 "
#630
1C
1A
1=
0>
1<
18
09
17
13
04
12
1.
0/
1-
b100000 %
0*
b11111 &
1)
1(
b11111 "
#640
0H
02
07
0<
0A
0F
0-
0.
03
08
0=
0B
1*
b0 &
0)
0/
04
09
0>
b100001 %
1C
0(
0,
01
06
0;
1@
b100000 "
#650
0*
b100010 %
1/
0'
1+
b10 !
#660
1*
b11 %
0C
1(
0@
b1 "
#670
14
12
0*
b100 %
0/
b10 &
1.
0(
1,
b10 "
#680
b101 %
1*
1(
b11 "
#690
09
07
02
03
0*
1/
b0 &
0.
b110 %
14
0(
0,
11
b100 "
#700
b111 %
1*
1(
b101 "
#710
19
17
13
04
12
0*
b1000 %
0/
b110 &
1.
0(
1,
b110 "
#720
b1001 %
1*
1(
b111 "
#730
0>
07
0<
02
03
08
0*
1/
b0 &
0.
04
b1010 %
19
0(
0,
01
16
b1000 "
#740
b1011 %
1*
1(
b1001 "
#750
14
12
0*
b1100 %
0/
b10 &
1.
0(
1,
b1010 "
#760
b1101 %
1*
1(
b1011 "
#770
0>
0<
08
19
07
02
03
0*
1/
b0 &
0.
b1110 %
14
0(
0,
11
b1100 "
#780
b1111 %
1*
1(
b1101 "
#790
1>
1<
18
09
17
13
04
12
0*
b10000 %
0/
b1110 &
1.
0(
1,
b1110 "
#800
b10001 %
1*
1(
b1111 "
#810
0C
07
0<
0A
02
03
08
0=
0*
1/
b0 &
0.
04
09
b10010 %
1>
0(
0,
01
06
1;
b10000 "
#820
b10011 %
1*
1(
b10001 "
#830
14
12
0*
b10100 %
0/
b10 &
1.
0(
1,
b10010 "
#840
b10101 %
1*
1(
b10011 "
#850
09
07
02
03
0*
1/
b0 &
0.
b10110 %
14
0(
0,
11
b10100 "
#860
b10111 %
1*
1(
b10101 "
#870
19
17
13
04
12
0*
b11000 %
0/
b110 &
1.
0(
1,
b10110 "
#880
b11001 %
1*
1(
b10111 "
#890
0C
0A
0=
1>
07
0<
02
03
08
0*
1/
b0 &
0.
04
b11010 %
19
0(
0,
01
16
b11000 "
#900
b11011 %
1*
1(
b11001 "
#910
14
12
0*
b11100 %
0/
b10 &
1.
0(
1,
b11010 "
#920
b11101 %
1*
1(
b11011 "
#930
0C
0A
0=
1>
0<
08
19
07
02
03
0*
1/
b0 &
0.
b11110 %
14
0(
0,
11
b11100 "
#940
b11111 %
1*
1(
b11101 "
#950
1C
1A
1=
0>
1<
18
09
17
13
04
12
0*
b100000 %
0/
b11110 &
1.
0(
1,
b11110 "
#960
b100001 %
1*
1(
b11111 "
#970
0H
07
0<
0A
0F
02
03
08
0=
0B
0*
1/
b0 &
0.
04
09
0>
b100010 %
1C
0(
0,
01
06
0;
1@
b100000 "
#980
b100011 %
1*
1'
b11 !
#990
14
12
1.
0/
1-
0*
b11 &
1)
b100 %
0C
1(
0@
b1 "
#1000
0-
1*
b10 &
0)
b101 %
0/
0(
1,
b10 "
#1010
1/
1-
b110 %
0*
b11 &
1)
1(
b11 "
#1020
09
07
0-
02
03
1*
0)
1/
b0 &
0.
b111 %
14
0(
0,
11
b100 "
#1030
19
17
13
04
12
1.
0/
1-
b1000 %
0*
b111 &
1)
1(
b101 "
#1040
0-
1*
b110 &
0)
b1001 %
0/
0(
1,
b110 "
#1050
1/
1-
b1010 %
0*
b111 &
1)
1(
b111 "
#1060
0>
07
0<
0-
02
03
08
1*
0)
1/
b0 &
0.
04
b1011 %
19
0(
0,
01
16
b1000 "
#1070
14
12
1.
0/
1-
b1100 %
0*
b11 &
1)
1(
b1001 "
#1080
0-
1*
b10 &
0)
b1101 %
0/
0(
1,
b1010 "
#1090
1/
1-
b1110 %
0*
b11 &
1)
1(
b1011 "
#1100
0>
0<
08
19
07
0-
02
03
1*
0)
1/
b0 &
0.
b1111 %
14
0(
0,
11
b1100 "
#1110
1>
1<
18
09
17
13
04
12
1.
0/
1-
b10000 %
0*
b1111 &
1)
1(
b1101 "
#1120
0-
1*
b1110 &
0)
b10001 %
0/
0(
1,
b1110 "
#1130
1/
1-
b10010 %
0*
b1111 &
1)
1(
b1111 "
#1140
0C
07
0<
0A
0-
02
03
08
0=
1*
0)
1/
b0 &
0.
04
09
b10011 %
1>
0(
0,
01
06
1;
b10000 "
#1150
14
12
1.
0/
1-
b10100 %
0*
b11 &
1)
1(
b10001 "
#1160
0-
1*
b10 &
0)
b10101 %
0/
0(
1,
b10010 "
#1170
1/
1-
b10110 %
0*
b11 &
1)
1(
b10011 "
#1180
09
07
0-
02
03
1*
0)
1/
b0 &
0.
b10111 %
14
0(
0,
11
b10100 "
#1190
19
17
13
04
12
1.
0/
1-
b11000 %
0*
b111 &
1)
1(
b10101 "
#1200
0-
1*
b110 &
0)
b11001 %
0/
0(
1,
b10110 "
#1210
1/
1-
b11010 %
0*
b111 &
1)
1(
b10111 "
#1220
0C
0A
0=
1>
07
0<
0-
02
03
08
1*
0)
1/
b0 &
0.
04
b11011 %
19
0(
0,
01
16
b11000 "
#1230
14
12
1.
0/
1-
b11100 %
0*
b11 &
1)
1(
b11001 "
#1240
0-
1*
b10 &
0)
b11101 %
0/
0(
1,
b11010 "
#1250
1/
1-
b11110 %
0*
b11 &
1)
1(
b11011 "
#1260
0C
0A
0=
1>
0<
08
19
07
0-
02
03
1*
0)
1/
b0 &
0.
b11111 %
14
0(
0,
11
b11100 "
#1270
1C
1A
1=
0>
1<
18
09
17
13
04
12
1.
0/
1-
b100000 %
0*
b11111 &
1)
1(
b11101 "
#1280
0-
1*
b11110 &
0)
b100001 %
0/
0(
1,
b11110 "
#1290
1/
1-
b100010 %
0*
b11111 &
1)
1(
b11111 "
#1300
0H
07
0<
0A
0F
0-
02
03
08
0=
0B
1*
0)
1/
b0 &
0.
04
09
0>
b100011 %
1C
0(
0,
01
06
0;
1@
b100000 "
#1310
0*
0/
b100100 %
14
0'
0+
10
b100 !
#1320
1*
b101 %
0C
1(
0@
b1 "
#1330
0*
b110 %
1/
0(
1,
b10 "
#1340
b111 %
1*
1(
b11 "
#1350
19
17
0*
0/
b1000 %
04
b100 &
13
0(
0,
11
b100 "
#1360
b1001 %
1*
1(
b101 "
#1370
0*
b1010 %
1/
0(
1,
b110 "
#1380
b1011 %
1*
1(
b111 "
#1390
0>
0<
07
08
0*
0/
14
b0 &
03
b1100 %
19
0(
0,
01
16
b1000 "
#1400
b1101 %
1*
1(
b1001 "
#1410
0*
b1110 %
1/
0(
1,
b1010 "
#1420
b1111 %
1*
1(
b1011 "
#1430
1>
1<
18
09
17
0*
0/
b10000 %
04
b1100 &
13
0(
0,
11
b1100 "
#1440
b10001 %
1*
1(
b1101 "
#1450
0*
b10010 %
1/
0(
1,
b1110 "
#1460
b10011 %
1*
1(
b1111 "
#1470
0C
0<
0A
07
08
0=
0*
0/
14
b0 &
03
09
b10100 %
1>
0(
0,
01
06
1;
b10000 "
#1480
b10101 %
1*
1(
b10001 "
#1490
0*
b10110 %
1/
0(
1,
b10010 "
#1500
b10111 %
1*
1(
b10011 "
#1510
19
17
0*
0/
b11000 %
04
b100 &
13
0(
0,
11
b10100 "
#1520
b11001 %
1*
1(
b10101 "
#1530
0*
b11010 %
1/
0(
1,
b10110 "
#1540
b11011 %
1*
1(
b10111 "
#1550
0C
0A
0=
1>
0<
07
08
0*
0/
14
b0 &
03
b11100 %
19
0(
0,
01
16
b11000 "
#1560
b11101 %
1*
1(
b11001 "
#1570
0*
b11110 %
1/
0(
1,
b11010 "
#1580
b11111 %
1*
1(
b11011 "
#1590
1C
1A
1=
0>
1<
18
09
17
0*
0/
b100000 %
04
b11100 &
13
0(
0,
11
b11100 "
#1600
b100001 %
1*
1(
b11101 "
#1610
0*
b100010 %
1/
0(
1,
b11110 "
#1620
b100011 %
1*
1(
b11111 "
#1630
0H
0<
0A
0F
07
08
0=
0B
0*
0/
14
b0 &
03
09
0>
b100100 %
1C
0(
0,
01
06
0;
1@
b100000 "
#1640
b100101 %
1*
1'
b101 !
#1650
1/
1-
0*
b1 &
1)
b110 %
0C
1(
0@
b1 "
#1660
09
07
03
14
02
0-
0.
1*
b0 &
0)
b111 %
1/
0(
1,
b10 "
#1670
19
17
13
04
12
1.
0/
1-
b1000 %
0*
b111 &
1)
1(
b11 "
#1680
02
0-
0.
1*
b100 &
0)
0/
b1001 %
04
0(
0,
11
b100 "
#1690
1/
1-
b1010 %
0*
b101 &
1)
1(
b101 "
#1700
04
02
0-
0.
1*
b100 &
0)
b1011 %
1/
0(
1,
b110 "
#1710
14
12
1.
0/
1-
b1100 %
0*
b111 &
1)
1(
b111 "
#1720
0>
02
0<
0-
0.
07
08
1*
0)
0/
14
b0 &
03
b1101 %
19
0(
0,
01
16
b1000 "
#1730
1/
1-
b1110 %
0*
b1 &
1)
1(
b1001 "
#1740
0>
0<
08
19
07
03
14
02
0-
0.
1*
b0 &
0)
b1111 %
1/
0(
1,
b1010 "
#1750
1>
1<
18
09
17
13
04
12
1.
0/
1-
b10000 %
0*
b1111 &
1)
1(
b1011 "
#1760
02
0-
0.
1*
b1100 &
0)
0/
b10001 %
04
0(
0,
11
b1100 "
#1770
1/
1-
b10010 %
0*
b1101 &
1)
1(
b1101 "
#1780
04
02
0-
0.
1*
b1100 &
0)
b10011 %
1/
0(
1,
b1110 "
#1790
14
12
1.
0/
1-
b10100 %
0*
b1111 &
1)
1(
b1111 "
#1800
0C
02
0<
0A
0-
0.
07
08
0=
1*
0)
0/
14
b0 &
03
09
b10101 %
1>
0(
0,
01
06
1;
b10000 "
#1810
1/
1-
b10110 %
0*
b1 &
1)
1(
b10001 "
#1820
09
07
03
14
02
0-
0.
1*
b0 &
0)
b10111 %
1/
0(
1,
b10010 "
#1830
19
17
13
04
12
1.
0/
1-
b11000 %
0*
b111 &
1)
1(
b10011 "
#1840
02
0-
0.
1*
b100 &
0)
0/
b11001 %
04
0(
0,
11
b10100 "
#1850
1/
1-
b11010 %
0*
b101 &
1)
1(
b10101 "
#1860
04
02
0-
0.
1*
b100 &
0)
b11011 %
1/
0(
1,
b10110 "
#1870
14
12
1.
0/
1-
b11100 %
0*
b111 &
1)
1(
b10111 "
#1880
0C
0A
0=
1>
02
0<
0-
0.
07
08
1*
0)
0/
14
b0 &
03
b11101 %
19
0(
0,
01
16
b11000 "
#1890
1/
1-
b11110 %
0*
b1 &
1)
1(
b11001 "
#1900
0C
0A
0=
1>
0<
08
19
07
03
14
02
0-
0.
1*
b0 &
0)
b11111 %
1/
0(
1,
b11010 "
#1910
1C
1A
1=
0>
1<
18
09
17
13
04
12
1.
0/
1-
b100000 %
0*
b11111 &
1)
1(
b11011 "
#1920
02
0-
0.
1*
b11100 &
0)
0/
b100001 %
04
0(
0,
11
b11100 "
#1930
1/
1-
b100010 %
0*
b11101 &
1)
1(
b11101 "
#1940
04
02
0-
0.
1*
b11100 &
0)
b100011 %
1/
0(
1,
b11110 "
#1950
14
12
1.
0/
1-
b100100 %
0*
b11111 &
1)
1(
b11111 "
#1960
0H
02
0<
0A
0F
0-
0.
07
08
0=
0B
1*
0)
0/
14
b0 &
03
09
0>
b100101 %
1C
0(
0,
01
06
0;
1@
b100000 "
#1970
0*
b100110 %
1/
0'
1+
b110 !
#1980
1*
b111 %
0C
1(
0@
b1 "
#1990
19
17
13
04
12
0*
b1000 %
0/
b110 &
1.
0(
1,
b10 "
#2000
b1001 %
1*
1(
b11 "
#2010
02
0*
1/
b100 &
0.
b1010 %
04
0(
0,
11
b100 "
#2020
b1011 %
1*
1(
b101 "
#2030
14
12
0*
b1100 %
0/
b110 &
1.
0(
1,
b110 "
#2040
b1101 %
1*
1(
b111 "
#2050
0>
0<
02
07
08
0*
1/
0.
14
b0 &
03
b1110 %
19
0(
0,
01
16
b1000 "
#2060
b1111 %
1*
1(
b1001 "
#2070
1>
1<
18
09
17
13
04
12
0*
b10000 %
0/
b1110 &
1.
0(
1,
b1010 "
#2080
b10001 %
1*
1(
b1011 "
#2090
02
0*
1/
b1100 &
0.
b10010 %
04
0(
0,
11
b1100 "
#2100
b10011 %
1*
1(
b1101 "
#2110
14
12
0*
b10100 %
0/
b1110 &
1.
0(
1,
b1110 "
#2120
b10101 %
1*
1(
b1111 "
#2130
0C
0<
0A
02
07
08
0=
0*
1/
0.
14
b0 &
03
09
b10110 %
1>
0(
0,
01
06
1;
b10000 "
#2140
b10111 %
1*
1(
b10001 "
#2150
19
17
13
04
12
0*
b11000 %
0/
b110 &
1.
0(
1,
b10010 "
#2160
b11001 %
1*
1(
b10011 "
#2170
02
0*
1/
b100 &
0.
b11010 %
04
0(
0,
11
b10100 "
#2180
b11011 %
1*
1(
b10101 "
#2190
14
12
0*
b11100 %
0/
b110 &
1.
0(
1,
b10110 "
#2200
b11101 %
1*
1(
b10111 "
#2210
0C
0A
0=
1>
0<
02
07
08
0*
1/
0.
14
b0 &
03
b11110 %
19
0(
0,
01
16
b11000 "
#2220
b11111 %
1*
1(
b11001 "
#2230
1C
1A
1=
0>
1<
18
09
17
13
04
12
0*
b100000 %
0/
b11110 &
1.
0(
1,
b11010 "
#2240
b100001 %
1*
1(
b11011 "
#2250
02
0*
1/
b11100 &
0.
b100010 %
04
0(
0,
11
b11100 "
#2260
b100011 %
1*
1(
b11101 "
#2270
14
12
0*
b100100 %
0/
b11110 &
1.
0(
1,
b11110 "
#2280
b100101 %
1*
1(
b11111 "
#2290
0H
0<
0A
0F
02
07
08
0=
0B
0*
1/
0.
14
b0 &
03
09
0>
b100110 %
1C
0(
0,
01
06
0;
1@
b100000 "
#2300
b100111 %
1*
1'
b111 !
#2310
19
17
13
04
12
1.
0/
1-
0*
b111 &
1)
b1000 %
0C
1(
0@
b1 "
#2320
0-
1*
b110 &
0)
b1001 %
0/
0(
1,
b10 "
#2330
1/
1-
b1010 %
0*
b111 &
1)
1(
b11 "
#2340
0-
02
1*
0)
1/
b100 &
0.
b1011 %
04
0(
0,
11
b100 "
#2350
14
12
1.
0/
1-
b1100 %
0*
b111 &
1)
1(
b101 "
#2360
0-
1*
b110 &
0)
b1101 %
0/
0(
1,
b110 "
#2370
1/
1-
b1110 %
0*
b111 &
1)
1(
b111 "
#2380
0>
0<
0-
02
07
08
1*
0)
1/
0.
14
b0 &
03
b1111 %
19
0(
0,
01
16
b1000 "
#2390
1>
1<
18
09
17
13
04
12
1.
0/
1-
b10000 %
0*
b1111 &
1)
1(
b1001 "
#2400
0-
1*
b1110 &
0)
b10001 %
0/
0(
1,
b1010 "
#2410
1/
1-
b10010 %
0*
b1111 &
1)
1(
b1011 "
#2420
0-
02
1*
0)
1/
b1100 &
0.
b10011 %
04
0(
0,
11
b1100 "
#2430
14
12
1.
0/
1-
b10100 %
0*
b1111 &
1)
1(
b1101 "
#2440
0-
1*
b1110 &
0)
b10101 %
0/
0(
1,
b1110 "
#2450
1/
1-
b10110 %
0*
b1111 &
1)
1(
b1111 "
#2460
0C
0<
0A
0-
02
07
08
0=
1*
0)
1/
0.
14
b0 &
03
09
b10111 %
1>
0(
0,
01
06
1;
b10000 "
#2470
19
17
13
04
12
1.
0/
1-
b11000 %
0*
b111 &
1)
1(
b10001 "
#2480
0-
1*
b110 &
0)
b11001 %
0/
0(
1,
b10010 "
#2490
1/
1-
b11010 %
0*
b111 &
1)
1(
b10011 "
#2500
0-
02
1*
0)
1/
b100 &
0.
b11011 %
04
0(
0,
11
b10100 "
#2510
14
12
1.
0/
1-
b11100 %
0*
b111 &
1)
1(
b10101 "
#2520
0-
1*
b110 &
0)
b11101 %
0/
0(
1,
b10110 "
#2530
1/
1-
b11110 %
0*
b111 &
1)
1(
b10111 "
#2540
0C
0A
0=
1>
0<
0-
02
07
08
1*
0)
1/
0.
14
b0 &
03
b11111 %
19
0(
0,
01
16
b11000 "
#2550
1C
1A
1=
0>
1<
18
09
17
13
04
12
1.
0/
1-
b100000 %
0*
b11111 &
1)
1(
b11001 "
#2560
0-
1*
b11110 &
0)
b100001 %
0/
0(
1,
b11010 "
#2570
1/
1-
b100010 %
0*
b11111 &
1)
1(
b11011 "
#2580
0-
02
1*
0)
1/
b11100 &
0.
b100011 %
04
0(
0,
11
b11100 "
#2590
14
12
1.
0/
1-
b100100 %
0*
b11111 &
1)
1(
b11101 "
#2600
0-
1*
b11110 &
0)
b100101 %
0/
0(
1,
b11110 "
#2610
1/
1-
b100110 %
0*
b11111 &
1)
1(
b11111 "
#2620
0H
0<
0A
0F
0-
02
07
08
0=
0B
1*
0)
1/
0.
14
b0 &
03
09
0>
b100111 %
1C
0(
0,
01
06
0;
1@
b100000 "
#2630
0*
0/
04
b101000 %
19
0'
0+
00
15
b1000 !
#2640
1*
b1001 %
0C
1(
0@
b1 "
#2650
0*
b1010 %
1/
0(
1,
b10 "
#2660
b1011 %
1*
1(
b11 "
#2670
0*
0/
b1100 %
14
0(
0,
11
b100 "
#2680
b1101 %
1*
1(
b101 "
#2690
0*
b1110 %
1/
0(
1,
b110 "
#2700
b1111 %
1*
1(
b111 "
#2710
1>
1<
0*
0/
04
b10000 %
09
b1000 &
18
0(
0,
01
16
b1000 "
#2720
b10001 %
1*
1(
b1001 "
#2730
0*
b10010 %
1/
0(
1,
b1010 "
#2740
b10011 %
1*
1(
b1011 "
#2750
0*
0/
b10100 %
14
0(
0,
11
b1100 "
#2760
b10101 %
1*
1(
b1101 "
#2770
0*
b10110 %
1/
0(
1,
b1110 "
#2780
b10111 %
1*
1(
b1111 "
#2790
0C
0A
0<
0=
0*
0/
04
19
b0 &
08
b11000 %
1>
0(
0,
01
06
1;
b10000 "
#2800
b11001 %
1*
1(
b10001 "
#2810
0*
b11010 %
1/
0(
1,
b10010 "
#2820
b11011 %
1*
1(
b10011 "
#2830
0*
0/
b11100 %
14
0(
0,
11
b10100 "
#2840
b11101 %
1*
1(
b10101 "
#2850
0*
b11110 %
1/
0(
1,
b10110 "
#2860
b11111 %
1*
1(
b10111 "
#2870
1C
1A
1=
0>
1<
0*
0/
04
b100000 %
09
b11000 &
18
0(
0,
01
16
b11000 "
#2880
b100001 %
1*
1(
b11001 "
#2890
0*
b100010 %
1/
0(
1,
b11010 "
#2900
b100011 %
1*
1(
b11011 "
#2910
0*
0/
b100100 %
14
0(
0,
11
b11100 "
#2920
b100101 %
1*
1(
b11101 "
#2930
0*
b100110 %
1/
0(
1,
b11110 "
#2940
b100111 %
1*
1(
b11111 "
#2950
0H
0A
0F
0<
0=
0B
0*
0/
04
19
b0 &
08
0>
b101000 %
1C
0(
0,
01
06
0;
1@
b100000 "
#2960
b101001 %
1*
1'
b1001 !
#2970
1/
1-
0*
b1 &
1)
b1010 %
0C
1(
0@
b1 "
#2980
04
02
0-
0.
1*
b0 &
0)
b1011 %
1/
0(
1,
b10 "
#2990
14
12
1.
0/
1-
b1100 %
0*
b11 &
1)
1(
b11 "
#3000
0>
0<
08
19
02
07
0-
0.
03
1*
b0 &
0)
0/
b1101 %
14
0(
0,
11
b100 "
#3010
1/
1-
b1110 %
0*
b1 &
1)
1(
b101 "
#3020
0>
0<
08
19
07
03
14
02
0-
0.
1*
b0 &
0)
b1111 %
1/
0(
1,
b110 "
#3030
1>
1<
18
09
17
13
04
12
1.
0/
1-
b10000 %
0*
b1111 &
1)
1(
b111 "
#3040
02
07
0-
0.
03
1*
b1000 &
0)
0/
04
b10001 %
09
0(
0,
01
16
b1000 "
#3050
1/
1-
b10010 %
0*
b1001 &
1)
1(
b1001 "
#3060
04
02
0-
0.
1*
b1000 &
0)
b10011 %
1/
0(
1,
b1010 "
#3070
14
12
1.
0/
1-
b10100 %
0*
b1011 &
1)
1(
b1011 "
#3080
09
02
07
0-
0.
03
1*
b1000 &
0)
0/
b10101 %
14
0(
0,
11
b1100 "
#3090
1/
1-
b10110 %
0*
b1001 &
1)
1(
b1101 "
#3100
09
07
03
14
02
0-
0.
1*
b1000 &
0)
b10111 %
1/
0(
1,
b1110 "
#3110
19
17
13
04
12
1.
0/
1-
b11000 %
0*
b1111 &
1)
1(
b1111 "
#3120
0C
02
07
0A
0-
0.
03
0<
0=
1*
0)
0/
04
19
b0 &
08
b11001 %
1>
0(
0,
01
06
1;
b10000 "
#3130
1/
1-
b11010 %
0*
b1 &
1)
1(
b10001 "
#3140
04
02
0-
0.
1*
b0 &
0)
b11011 %
1/
0(
1,
b10010 "
#3150
14
12
1.
0/
1-
b11100 %
0*
b11 &
1)
1(
b10011 "
#3160
0C
0A
0=
1>
0<
08
19
02
07
0-
0.
03
1*
b0 &
0)
0/
b11101 %
14
0(
0,
11
b10100 "
#3170
1/
1-
b11110 %
0*
b1 &
1)
1(
b10101 "
#3180
0C
0A
0=
1>
0<
08
19
07
03
14
02
0-
0.
1*
b0 &
0)
b11111 %
1/
0(
1,
b10110 "
#3190
1C
1A
1=
0>
1<
18
09
17
13
04
12
1.
0/
1-
b100000 %
0*
b11111 &
1)
1(
b10111 "
#3200
02
07
0-
0.
03
1*
b11000 &
0)
0/
04
b100001 %
09
0(
0,
01
16
b11000 "
#3210
1/
1-
b100010 %
0*
b11001 &
1)
1(
b11001 "
#3220
04
02
0-
0.
1*
b11000 &
0)
b100011 %
1/
0(
1,
b11010 "
#3230
14
12
1.
0/
1-
b100100 %
0*
b11011 &
1)
1(
b11011 "
